Report5/Ex3/fourBitCLAFA.v
module fourBitAheadAdder(inA, inB, carryIn, sum, carryOut);
	input [3:0]inA, inB;
	input carryIn;
	output [3:0]sum;
	output carryOut;
	
	assign {carryOut, sum}={((inA[3]&inB[3])|(inA[3]^inB[3])&((inA[2]&inB[2])|((inA[2]^inB[2])&((inA[1]&inB[1])|((inA[1]^inB[1])&((inA[0]&inB[0])|((inA[0]^inB[0])&carryIn)))))))
							, inA[3]^inB[3]^((inA[2]&inB[2])|((inA[2]^inB[2])&((inA[1]&inB[1])|((inA[1]^inB[1])&((inA[0]&inB[0])|((inA[0]^inB[0])&carryIn))))))
							, inA[2]^inB[2]^((inA[1]&inB[1])|((inA[1]^inB[1])&((inA[0]&inB[0])|((inA[0]^inB[0])&carryIn))))
							, inA[1]^inB[1]^((inA[0]&inB[0])|((inA[0]^inB[0])&carryIn))
							, inA[0]^inB[0]^carryIn};

endmodule

Report5/Ex3/testFourBitCLAFA.v
module fourBitLACTest;
	reg [3:0]inA, inB;
	reg carryIn;
	wire [3:0]sum;
	wire carryOut;
	
	fourBitAheadAdder FA0(inA, inB, carryIn, sum, carryOut);
	
	initial begin
		for(inA=0; inA<15; inA=inA+1)begin
			for(inB=0; inB<15; inB=inB+1)begin
				carryIn=0;
				#1 carryIn=1;
				#1;
			end
			carryIn=0;
			#1 carryIn=1;
			#1;
		end
		for(inB=0; inB<15; inB=inB+1)begin
				carryIn=0;
				#1 carryIn=1;
				#1;
		end
		carryIn=0;
		#1 carryIn=1;
		#1;
	end
	
	initial begin
		$monitor(" carryIn=%b, inA=%b, inB=%b, Sum=%b, CarryOut=%b", carryIn, inA, inB, sum, carryOut);
	end
	
	initial begin
		$dumpfile("testFourBitFA.vcd");
		$dumpvars;
	end
	
endmodule

Report5/Ex3/testFourBitFA.vcd
$date
	Mon Apr 23 21:07:21 2018
$end
$version
	Icarus Verilog
$end
$timescale
	1s
$end
$scope module fourBitLACTest $end
$var wire 4 ! sum [3:0] $end
$var wire 1 " carryOut $end
$var reg 1 # carryIn $end
$var reg 4 $ inA [3:0] $end
$var reg 4 % inB [3:0] $end
$scope module FA0 $end
$var wire 1 # carryIn $end
$var wire 4 & inA [3:0] $end
$var wire 4 ' inB [3:0] $end
$var wire 4 ( sum [3:0] $end
$var wire 1 " carryOut $end
$upscope $end
$upscope $end
$enddefinitions $end
#0
$dumpvars
b0 (
b0 '
b0 &
b0 %
b0 $
0#
0"
b0 !
$end
#1
b1 !
b1 (
1#
#2
b1 !
b1 (
0#
b1 %
b1 '
#3
b10 !
b10 (
1#
#4
b10 !
b10 (
0#
b10 %
b10 '
#5
b11 !
b11 (
1#
#6
b11 !
b11 (
0#
b11 %
b11 '
#7
b100 !
b100 (
1#
#8
b100 !
b100 (
0#
b100 %
b100 '
#9
b101 !
b101 (
1#
#10
b101 !
b101 (
0#
b101 %
b101 '
#11
b110 !
b110 (
1#
#12
b110 !
b110 (
0#
b110 %
b110 '
#13
b111 !
b111 (
1#
#14
b111 !
b111 (
0#
b111 %
b111 '
#15
b1000 !
b1000 (
1#
#16
0"
b1000 !
b1000 (
0#
b1000 %
b1000 '
#17
b1001 !
b1001 (
1#
#18
b1001 !
b1001 (
0#
b1001 %
b1001 '
#19
b1010 !
b1010 (
1#
#20
b1010 !
b1010 (
0#
b1010 %
b1010 '
#21
b1011 !
b1011 (
1#
#22
b1011 !
b1011 (
0#
b1011 %
b1011 '
#23
b1100 !
b1100 (
1#
#24
0"
b1100 !
b1100 (
0#
b1100 %
b1100 '
#25
b1101 !
b1101 (
1#
#26
b1101 !
b1101 (
0#
b1101 %
b1101 '
#27
b1110 !
b1110 (
1#
#28
b1110 !
b1110 (
0#
b1110 %
b1110 '
#29
b1111 !
b1111 (
1#
#30
b1111 !
b1111 (
0#
b1111 %
b1111 '
#31
1"
b0 !
b0 (
1#
#32
0"
b1 !
b1 (
0#
b0 %
b0 '
b1 $
b1 &
#33
b10 !
b10 (
1#
#34
b10 !
b10 (
0#
b1 %
b1 '
#35
b11 !
b11 (
1#
#36
b11 !
b11 (
0#
b10 %
b10 '
#37
b100 !
b100 (
1#
#38
b100 !
b100 (
0#
b11 %
b11 '
#39
b101 !
b101 (
1#
#40
b101 !
b101 (
0#
b100 %
b100 '
#41
b110 !
b110 (
1#
#42
b110 !
b110 (
0#
b101 %
b101 '
#43
b111 !
b111 (
1#
#44
b111 !
b111 (
0#
b110 %
b110 '
#45
b1000 !
b1000 (
1#
#46
b1000 !
b1000 (
0#
b111 %
b111 '
#47
b1001 !
b1001 (
1#
#48
0"
b1001 !
b1001 (
0#
b1000 %
b1000 '
#49
b1010 !
b1010 (
1#
#50
b1010 !
b1010 (
0#
b1001 %
b1001 '
#51
b1011 !
b1011 (
1#
#52
b1011 !
b1011 (
0#
b1010 %
b1010 '
#53
b1100 !
b1100 (
1#
#54
b1100 !
b1100 (
0#
b1011 %
b1011 '
#55
b1101 !
b1101 (
1#
#56
0"
b1101 !
b1101 (
0#
b1100 %
b1100 '
#57
b1110 !
b1110 (
1#
#58
b1110 !
b1110 (
0#
b1101 %
b1101 '
#59
b1111 !
b1111 (
1#
#60
b1111 !
b1111 (
0#
b1110 %
b1110 '
#61
1"
b0 !
b0 (
1#
#62
b0 !
b0 (
0#
b1111 %
b1111 '
#63
b1 !
b1 (
1#
#64
0"
b10 !
b10 (
0#
b0 %
b0 '
b10 $
b10 &
#65
b11 !
b11 (
1#
#66
b11 !
b11 (
0#
b1 %
b1 '
#67
b100 !
b100 (
1#
#68
b100 !
b100 (
0#
b10 %
b10 '
#69
b101 !
b101 (
1#
#70
b101 !
b101 (
0#
b11 %
b11 '
#71
b110 !
b110 (
1#
#72
b110 !
b110 (
0#
b100 %
b100 '
#73
b111 !
b111 (
1#
#74
b111 !
b111 (
0#
b101 %
b101 '
#75
b1000 !
b1000 (
1#
#76
b1000 !
b1000 (
0#
b110 %
b110 '
#77
b1001 !
b1001 (
1#
#78
b1001 !
b1001 (
0#
b111 %
b111 '
#79
b1010 !
b1010 (
1#
#80
0"
b1010 !
b1010 (
0#
b1000 %
b1000 '
#81
b1011 !
b1011 (
1#
#82
b1011 !
b1011 (
0#
b1001 %
b1001 '
#83
b1100 !
b1100 (
1#
#84
b1100 !
b1100 (
0#
b1010 %
b1010 '
#85
b1101 !
b1101 (
1#
#86
b1101 !
b1101 (
0#
b1011 %
b1011 '
#87
b1110 !
b1110 (
1#
#88
b1110 !
b1110 (
0#
b1100 %
b1100 '
#89
b1111 !
b1111 (
1#
#90
b1111 !
b1111 (
0#
b1101 %
b1101 '
#91
1"
b0 !
b0 (
1#
#92
b0 !
b0 (
0#
b1110 %
b1110 '
#93
b1 !
b1 (
1#
#94
b1 !
b1 (
0#
b1111 %
b1111 '
#95
b10 !
b10 (
1#
#96
0"
b11 !
b11 (
0#
b0 %
b0 '
b11 $
b11 &
#97
b100 !
b100 (
1#
#98
b100 !
b100 (
0#
b1 %
b1 '
#99
b101 !
b101 (
1#
#100
b101 !
b101 (
0#
b10 %
b10 '
#101
b110 !
b110 (
1#
#102
b110 !
b110 (
0#
b11 %
b11 '
#103
b111 !
b111 (
1#
#104
b111 !
b111 (
0#
b100 %
b100 '
#105
b1000 !
b1000 (
1#
#106
b1000 !
b1000 (
0#
b101 %
b101 '
#107
b1001 !
b1001 (
1#
#108
b1001 !
b1001 (
0#
b110 %
b110 '
#109
b1010 !
b1010 (
1#
#110
b1010 !
b1010 (
0#
b111 %
b111 '
#111
b1011 !
b1011 (
1#
#112
0"
b1011 !
b1011 (
0#
b1000 %
b1000 '
#113
b1100 !
b1100 (
1#
#114
b1100 !
b1100 (
0#
b1001 %
b1001 '
#115
b1101 !
b1101 (
1#
#116
b1101 !
b1101 (
0#
b1010 %
b1010 '
#117
b1110 !
b1110 (
1#
#118
b1110 !
b1110 (
0#
b1011 %
b1011 '
#119
b1111 !
b1111 (
1#
#120
b1111 !
b1111 (
0#
b1100 %
b1100 '
#121
1"
b0 !
b0 (
1#
#122
b0 !
b0 (
0#
b1101 %
b1101 '
#123
b1 !
b1 (
1#
#124
b1 !
b1 (
0#
b1110 %
b1110 '
#125
b10 !
b10 (
1#
#126
b10 !
b10 (
0#
b1111 %
b1111 '
#127
b11 !
b11 (
1#
#128
0"
b100 !
b100 (
0#
b0 %
b0 '
b100 $
b100 &
#129
b101 !
b101 (
1#
#130
b101 !
b101 (
0#
b1 %
b1 '
#131
b110 !
b110 (
1#
#132
b110 !
b110 (
0#
b10 %
b10 '
#133
b111 !
b111 (
1#
#134
b111 !
b111 (
0#
b11 %
b11 '
#135
b1000 !
b1000 (
1#
#136
b1000 !
b1000 (
0#
b100 %
b100 '
#137
b1001 !
b1001 (
1#
#138
b1001 !
b1001 (
0#
b101 %
b101 '
#139
b1010 !
b1010 (
1#
#140
b1010 !
b1010 (
0#
b110 %
b110 '
#141
b1011 !
b1011 (
1#
#142
b1011 !
b1011 (
0#
b111 %
b111 '
#143
b1100 !
b1100 (
1#
#144
0"
b1100 !
b1100 (
0#
b1000 %
b1000 '
#145
b1101 !
b1101 (
1#
#146
b1101 !
b1101 (
0#
b1001 %
b1001 '
#147
b1110 !
b1110 (
1#
#148
b1110 !
b1110 (
0#
b1010 %
b1010 '
#149
b1111 !
b1111 (
1#
#150
b1111 !
b1111 (
0#
b1011 %
b1011 '
#151
1"
b0 !
b0 (
1#
#152
b0 !
b0 (
0#
b1100 %
b1100 '
#153
b1 !
b1 (
1#
#154
b1 !
b1 (
0#
b1101 %
b1101 '
#155
b10 !
b10 (
1#
#156
b10 !
b10 (
0#
b1110 %
b1110 '
#157
b11 !
b11 (
1#
#158
b11 !
b11 (
0#
b1111 %
b1111 '
#159
b100 !
b100 (
1#
#160
0"
b101 !
b101 (
0#
b0 %
b0 '
b101 $
b101 &
#161
b110 !
b110 (
1#
#162
b110 !
b110 (
0#
b1 %
b1 '
#163
b111 !
b111 (
1#
#164
b111 !
b111 (
0#
b10 %
b10 '
#165
b1000 !
b1000 (
1#
#166
b1000 !
b1000 (
0#
b11 %
b11 '
#167
b1001 !
b1001 (
1#
#168
b1001 !
b1001 (
0#
b100 %
b100 '
#169
b1010 !
b1010 (
1#
#170
b1010 !
b1010 (
0#
b101 %
b101 '
#171
b1011 !
b1011 (
1#
#172
b1011 !
b1011 (
0#
b110 %
b110 '
#173
b1100 !
b1100 (
1#
#174
b1100 !
b1100 (
0#
b111 %
b111 '
#175
b1101 !
b1101 (
1#
#176
0"
b1101 !
b1101 (
0#
b1000 %
b1000 '
#177
b1110 !
b1110 (
1#
#178
b1110 !
b1110 (
0#
b1001 %
b1001 '
#179
b1111 !
b1111 (
1#
#180
b1111 !
b1111 (
0#
b1010 %
b1010 '
#181
1"
b0 !
b0 (
1#
#182
b0 !
b0 (
0#
b1011 %
b1011 '
#183
b1 !
b1 (
1#
#184
b1 !
b1 (
0#
b1100 %
b1100 '
#185
b10 !
b10 (
1#
#186
b10 !
b10 (
0#
b1101 %
b1101 '
#187
b11 !
b11 (
1#
#188
b11 !
b11 (
0#
b1110 %
b1110 '
#189
b100 !
b100 (
1#
#190
b100 !
b100 (
0#
b1111 %
b1111 '
#191
b101 !
b101 (
1#
#192
0"
b110 !
b110 (
0#
b0 %
b0 '
b110 $
b110 &
#193
b111 !
b111 (
1#
#194
b111 !
b111 (
0#
b1 %
b1 '
#195
b1000 !
b1000 (
1#
#196
b1000 !
b1000 (
0#
b10 %
b10 '
#197
b1001 !
b1001 (
1#
#198
b1001 !
b1001 (
0#
b11 %
b11 '
#199
b1010 !
b1010 (
1#
#200
b1010 !
b1010 (
0#
b100 %
b100 '
#201
b1011 !
b1011 (
1#
#202
b1011 !
b1011 (
0#
b101 %
b101 '
#203
b1100 !
b1100 (
1#
#204
b1100 !
b1100 (
0#
b110 %
b110 '
#205
b1101 !
b1101 (
1#
#206
b1101 !
b1101 (
0#
b111 %
b111 '
#207
b1110 !
b1110 (
1#
#208
b1110 !
b1110 (
0#
b1000 %
b1000 '
#209
b1111 !
b1111 (
1#
#210
b1111 !
b1111 (
0#
b1001 %
b1001 '
#211
1"
b0 !
b0 (
1#
#212
b0 !
b0 (
0#
b1010 %
b1010 '
#213
b1 !
b1 (
1#
#214
b1 !
b1 (
0#
b1011 %
b1011 '
#215
b10 !
b10 (
1#
#216
b10 !
b10 (
0#
b1100 %
b1100 '
#217
b11 !
b11 (
1#
#218
b11 !
b11 (
0#
b1101 %
b1101 '
#219
b100 !
b100 (
1#
#220
b100 !
b100 (
0#
b1110 %
b1110 '
#221
b101 !
b101 (
1#
#222
b101 !
b101 (
0#
b1111 %
b1111 '
#223
b110 !
b110 (
1#
#224
0"
b111 !
b111 (
0#
b0 %
b0 '
b111 $
b111 &
#225
b1000 !
b1000 (
1#
#226
b1000 !
b1000 (
0#
b1 %
b1 '
#227
b1001 !
b1001 (
1#
#228
b1001 !
b1001 (
0#
b10 %
b10 '
#229
b1010 !
b1010 (
1#
#230
b1010 !
b1010 (
0#
b11 %
b11 '
#231
b1011 !
b1011 (
1#
#232
b1011 !
b1011 (
0#
b100 %
b100 '
#233
b1100 !
b1100 (
1#
#234
b1100 !
b1100 (
0#
b101 %
b101 '
#235
b1101 !
b1101 (
1#
#236
b1101 !
b1101 (
0#
b110 %
b110 '
#237
b1110 !
b1110 (
1#
#238
b1110 !
b1110 (
0#
b111 %
b111 '
#239
b1111 !
b1111 (
1#
#240
b1111 !
b1111 (
0#
b1000 %
b1000 '
#241
1"
b0 !
b0 (
1#
#242
b0 !
b0 (
0#
b1001 %
b1001 '
#243
b1 !
b1 (
1#
#244
b1 !
b1 (
0#
b1010 %
b1010 '
#245
b10 !
b10 (
1#
#246
b10 !
b10 (
0#
b1011 %
b1011 '
#247
b11 !
b11 (
1#
#248
b11 !
b11 (
0#
b1100 %
b1100 '
#249
b100 !
b100 (
1#
#250
b100 !
b100 (
0#
b1101 %
b1101 '
#251
b101 !
b101 (
1#
#252
b101 !
b101 (
0#
b1110 %
b1110 '
#253
b110 !
b110 (
1#
#254
b110 !
b110 (
0#
b1111 %
b1111 '
#255
b111 !
b111 (
1#
#256
0"
b1000 !
b1000 (
0#
b0 %
b0 '
b1000 $
b1000 &
#257
b1001 !
b1001 (
1#
#258
b1001 !
b1001 (
0#
b1 %
b1 '
#259
b1010 !
b1010 (
1#
#260
b1010 !
b1010 (
0#
b10 %
b10 '
#261
b1011 !
b1011 (
1#
#262
b1011 !
b1011 (
0#
b11 %
b11 '
#263
b1100 !
b1100 (
1#
#264
0"
b1100 !
b1100 (
0#
b100 %
b100 '
#265
b1101 !
b1101 (
1#
#266
b1101 !
b1101 (
0#
b101 %
b101 '
#267
b1110 !
b1110 (
1#
#268
b1110 !
b1110 (
0#
b110 %
b110 '
#269
b1111 !
b1111 (
1#
#270
b1111 !
b1111 (
0#
b111 %
b111 '
#271
1"
b0 !
b0 (
1#
#272
b0 !
b0 (
0#
b1000 %
b1000 '
#273
b1 !
b1 (
1#
#274
b1 !
b1 (
0#
b1001 %
b1001 '
#275
b10 !
b10 (
1#
#276
b10 !
b10 (
0#
b1010 %
b1010 '
#277
b11 !
b11 (
1#
#278
b11 !
b11 (
0#
b1011 %
b1011 '
#279
b100 !
b100 (
1#
#280
b100 !
b100 (
0#
b1100 %
b1100 '
#281
b101 !
b101 (
1#
#282
b101 !
b101 (
0#
b1101 %
b1101 '
#283
b110 !
b110 (
1#
#284
b110 !
b110 (
0#
b1110 %
b1110 '
#285
b111 !
b111 (
1#
#286
b111 !
b111 (
0#
b1111 %
b1111 '
#287
b1000 !
b1000 (
1#
#288
0"
b1001 !
b1001 (
0#
b0 %
b0 '
b1001 $
b1001 &
#289
b1010 !
b1010 (
1#
#290
b1010 !
b1010 (
0#
b1 %
b1 '
#291
b1011 !
b1011 (
1#
#292
b1011 !
b1011 (
0#
b10 %
b10 '
#293
b1100 !
b1100 (
1#
#294
b1100 !
b1100 (
0#
b11 %
b11 '
#295
b1101 !
b1101 (
1#
#296
0"
b1101 !
b1101 (
0#
b100 %
b100 '
#297
b1110 !
b1110 (
1#
#298
b1110 !
b1110 (
0#
b101 %
b101 '
#299
b1111 !
b1111 (
1#
#300
b1111 !
b1111 (
0#
b110 %
b110 '
#301
1"
b0 !
b0 (
1#
#302
b0 !
b0 (
0#
b111 %
b111 '
#303
b1 !
b1 (
1#
#304
b1 !
b1 (
0#
b1000 %
b1000 '
#305
b10 !
b10 (
1#
#306
b10 !
b10 (
0#
b1001 %
b1001 '
#307
b11 !
b11 (
1#
#308
b11 !
b11 (
0#
b1010 %
b1010 '
#309
b100 !
b100 (
1#
#310
b100 !
b100 (
0#
b1011 %
b1011 '
#311
b101 !
b101 (
1#
#312
b101 !
b101 (
0#
b1100 %
b1100 '
#313
b110 !
b110 (
1#
#314
b110 !
b110 (
0#
b1101 %
b1101 '
#315
b111 !
b111 (
1#
#316
b111 !
b111 (
0#
b1110 %
b1110 '
#317
b1000 !
b1000 (
1#
#318
b1000 !
b1000 (
0#
b1111 %
b1111 '
#319
b1001 !
b1001 (
1#
#320
0"
b1010 !
b1010 (
0#
b0 %
b0 '
b1010 $
b1010 &
#321
b1011 !
b1011 (
1#
#322
b1011 !
b1011 (
0#
b1 %
b1 '
#323
b1100 !
b1100 (
1#
#324
b1100 !
b1100 (
0#
b10 %
b10 '
#325
b1101 !
b1101 (
1#
#326
b1101 !
b1101 (
0#
b11 %
b11 '
#327
b1110 !
b1110 (
1#
#328
b1110 !
b1110 (
0#
b100 %
b100 '
#329
b1111 !
b1111 (
1#
#330
b1111 !
b1111 (
0#
b101 %
b101 '
#331
1"
b0 !
b0 (
1#
#332
b0 !
b0 (
0#
b110 %
b110 '
#333
b1 !
b1 (
1#
#334
b1 !
b1 (
0#
b111 %
b111 '
#335
b10 !
b10 (
1#
#336
b10 !
b10 (
0#
b1000 %
b1000 '
#337
b11 !
b11 (
1#
#338
b11 !
b11 (
0#
b1001 %
b1001 '
#339
b100 !
b100 (
1#
#340
b100 !
b100 (
0#
b1010 %
b1010 '
#341
b101 !
b101 (
1#
#342
b101 !
b101 (
0#
b1011 %
b1011 '
#343
b110 !
b110 (
1#
#344
b110 !
b110 (
0#
b1100 %
b1100 '
#345
b111 !
b111 (
1#
#346
b111 !
b111 (
0#
b1101 %
b1101 '
#347
b1000 !
b1000 (
1#
#348
b1000 !
b1000 (
0#
b1110 %
b1110 '
#349
b1001 !
b1001 (
1#
#350
b1001 !
b1001 (
0#
b1111 %
b1111 '
#351
b1010 !
b1010 (
1#
#352
0"
b1011 !
b1011 (
0#
b0 %
b0 '
b1011 $
b1011 &
#353
b1100 !
b1100 (
1#
#354
b1100 !
b1100 (
0#
b1 %
b1 '
#355
b1101 !
b1101 (
1#
#356
b1101 !
b1101 (
0#
b10 %
b10 '
#357
b1110 !
b1110 (
1#
#358
b1110 !
b1110 (
0#
b11 %
b11 '
#359
b1111 !
b1111 (
1#
#360
b1111 !
b1111 (
0#
b100 %
b100 '
#361
1"
b0 !
b0 (
1#
#362
b0 !
b0 (
0#
b101 %
b101 '
#363
b1 !
b1 (
1#
#364
b1 !
b1 (
0#
b110 %
b110 '
#365
b10 !
b10 (
1#
#366
b10 !
b10 (
0#
b111 %
b111 '
#367
b11 !
b11 (
1#
#368
b11 !
b11 (
0#
b1000 %
b1000 '
#369
b100 !
b100 (
1#
#370
b100 !
b100 (
0#
b1001 %
b1001 '
#371
b101 !
b101 (
1#
#372
b101 !
b101 (
0#
b1010 %
b1010 '
#373
b110 !
b110 (
1#
#374
b110 !
b110 (
0#
b1011 %
b1011 '
#375
b111 !
b111 (
1#
#376
b111 !
b111 (
0#
b1100 %
b1100 '
#377
b1000 !
b1000 (
1#
#378
b1000 !
b1000 (
0#
b1101 %
b1101 '
#379
b1001 !
b1001 (
1#
#380
b1001 !
b1001 (
0#
b1110 %
b1110 '
#381
b1010 !
b1010 (
1#
#382
b1010 !
b1010 (
0#
b1111 %
b1111 '
#383
b1011 !
b1011 (
1#
#384
0"
b1100 !
b1100 (
0#
b0 %
b0 '
b1100 $
b1100 &
#385
b1101 !
b1101 (
1#
#386
b1101 !
b1101 (
0#
b1 %
b1 '
#387
b1110 !
b1110 (
1#
#388
b1110 !
b1110 (
0#
b10 %
b10 '
#389
b1111 !
b1111 (
1#
#390
b1111 !
b1111 (
0#
b11 %
b11 '
#391
1"
b0 !
b0 (
1#
#392
b0 !
b0 (
0#
b100 %
b100 '
#393
b1 !
b1 (
1#
#394
b1 !
b1 (
0#
b101 %
b101 '
#395
b10 !
b10 (
1#
#396
b10 !
b10 (
0#
b110 %
b110 '
#397
b11 !
b11 (
1#
#398
b11 !
b11 (
0#
b111 %
b111 '
#399
b100 !
b100 (
1#
#400
b100 !
b100 (
0#
b1000 %
b1000 '
#401
b101 !
b101 (
1#
#402
b101 !
b101 (
0#
b1001 %
b1001 '
#403
b110 !
b110 (
1#
#404
b110 !
b110 (
0#
b1010 %
b1010 '
#405
b111 !
b111 (
1#
#406
b111 !
b111 (
0#
b1011 %
b1011 '
#407
b1000 !
b1000 (
1#
#408
b1000 !
b1000 (
0#
b1100 %
b1100 '
#409
b1001 !
b1001 (
1#
#410
b1001 !
b1001 (
0#
b1101 %
b1101 '
#411
b1010 !
b1010 (
1#
#412
b1010 !
b1010 (
0#
b1110 %
b1110 '
#413
b1011 !
b1011 (
1#
#414
b1011 !
b1011 (
0#
b1111 %
b1111 '
#415
b1100 !
b1100 (
1#
#416
0"
b1101 !
b1101 (
0#
b0 %
b0 '
b1101 $
b1101 &
#417
b1110 !
b1110 (
1#
#418
b1110 !
b1110 (
0#
b1 %
b1 '
#419
b1111 !
b1111 (
1#
#420
b1111 !
b1111 (
0#
b10 %
b10 '
#421
1"
b0 !
b0 (
1#
#422
b0 !
b0 (
0#
b11 %
b11 '
#423
b1 !
b1 (
1#
#424
b1 !
b1 (
0#
b100 %
b100 '
#425
b10 !
b10 (
1#
#426
b10 !
b10 (
0#
b101 %
b101 '
#427
b11 !
b11 (
1#
#428
b11 !
b11 (
0#
b110 %
b110 '
#429
b100 !
b100 (
1#
#430
b100 !
b100 (
0#
b111 %
b111 '
#431
b101 !
b101 (
1#
#432
b101 !
b101 (
0#
b1000 %
b1000 '
#433
b110 !
b110 (
1#
#434
b110 !
b110 (
0#
b1001 %
b1001 '
#435
b111 !
b111 (
1#
#436
b111 !
b111 (
0#
b1010 %
b1010 '
#437
b1000 !
b1000 (
1#
#438
b1000 !
b1000 (
0#
b1011 %
b1011 '
#439
b1001 !
b1001 (
1#
#440
b1001 !
b1001 (
0#
b1100 %
b1100 '
#441
b1010 !
b1010 (
1#
#442
b1010 !
b1010 (
0#
b1101 %
b1101 '
#443
b1011 !
b1011 (
1#
#444
b1011 !
b1011 (
0#
b1110 %
b1110 '
#445
b1100 !
b1100 (
1#
#446
b1100 !
b1100 (
0#
b1111 %
b1111 '
#447
b1101 !
b1101 (
1#
#448
0"
b1110 !
b1110 (
0#
b0 %
b0 '
b1110 $
b1110 &
#449
b1111 !
b1111 (
1#
#450
b1111 !
b1111 (
0#
b1 %
b1 '
#451
1"
b0 !
b0 (
1#
#452
b0 !
b0 (
0#
b10 %
b10 '
#453
b1 !
b1 (
1#
#454
b1 !
b1 (
0#
b11 %
b11 '
#455
b10 !
b10 (
1#
#456
b10 !
b10 (
0#
b100 %
b100 '
#457
b11 !
b11 (
1#
#458
b11 !
b11 (
0#
b101 %
b101 '
#459
b100 !
b100 (
1#
#460
b100 !
b100 (
0#
b110 %
b110 '
#461
b101 !
b101 (
1#
#462
b101 !
b101 (
0#
b111 %
b111 '
#463
b110 !
b110 (
1#
#464
b110 !
b110 (
0#
b1000 %
b1000 '
#465
b111 !
b111 (
1#
#466
b111 !
b111 (
0#
b1001 %
b1001 '
#467
b1000 !
b1000 (
1#
#468
b1000 !
b1000 (
0#
b1010 %
b1010 '
#469
b1001 !
b1001 (
1#
#470
b1001 !
b1001 (
0#
b1011 %
b1011 '
#471
b1010 !
b1010 (
1#
#472
b1010 !
b1010 (
0#
b1100 %
b1100 '
#473
b1011 !
b1011 (
1#
#474
b1011 !
b1011 (
0#
b1101 %
b1101 '
#475
b1100 !
b1100 (
1#
#476
b1100 !
b1100 (
0#
b1110 %
b1110 '
#477
b1101 !
b1101 (
1#
#478
b1101 !
b1101 (
0#
b1111 %
b1111 '
#479
b1110 !
b1110 (
1#
#480
0"
b1111 !
b1111 (
0#
b0 %
b0 '
b1111 $
b1111 &
#481
1"
b0 !
b0 (
1#
#482
b0 !
b0 (
0#
b1 %
b1 '
#483
b1 !
b1 (
1#
#484
b1 !
b1 (
0#
b10 %
b10 '
#485
b10 !
b10 (
1#
#486
b10 !
b10 (
0#
b11 %
b11 '
#487
b11 !
b11 (
1#
#488
b11 !
b11 (
0#
b100 %
b100 '
#489
b100 !
b100 (
1#
#490
b100 !
b100 (
0#
b101 %
b101 '
#491
b101 !
b101 (
1#
#492
b101 !
b101 (
0#
b110 %
b110 '
#493
b110 !
b110 (
1#
#494
b110 !
b110 (
0#
b111 %
b111 '
#495
b111 !
b111 (
1#
#496
b111 !
b111 (
0#
b1000 %
b1000 '
#497
b1000 !
b1000 (
1#
#498
b1000 !
b1000 (
0#
b1001 %
b1001 '
#499
b1001 !
b1001 (
1#
#500
b1001 !
b1001 (
0#
b1010 %
b1010 '
#501
b1010 !
b1010 (
1#
#502
b1010 !
b1010 (
0#
b1011 %
b1011 '
#503
b1011 !
b1011 (
1#
#504
b1011 !
b1011 (
0#
b1100 %
b1100 '
#505
b1100 !
b1100 (
1#
#506
b1100 !
b1100 (
0#
b1101 %
b1101 '
#507
b1101 !
b1101 (
1#
#508
b1101 !
b1101 (
0#
b1110 %
b1110 '
#509
b1110 !
b1110 (
1#
#510
b1110 !
b1110 (
0#
b1111 %
b1111 '
#511
b1111 !
b1111 (
1#
