Report4/Ex1/mux2to1.v
module mux_2to1(in0, in1, sel, out);

	input  in0, in1, sel;
	output out;

	wire Not_Out0, And_Out0, And_Out1;//Not_Out0 is the ~sel, And_Out0 is ~sel*in0, And_Out1 is sel*in1

	not NOT0(Not_Out0, sel);
	and AND0(And_Out0, in0, Not_Out0);
	and AND1(And_Out1, in1, sel);
	or	OR0(out, And_Out0, And_Out1);

endmodule

Report4/Ex1/mux4to1.v
module mux_4to1(in, sel, out);
	
	input [3:0]in;
	input [1:0]sel;
	output out;
	
	wire M2T1_out[0:1];
	
	mux_2to1 M2T1_0(in[0], in[1], sel[0], M2T1_out[0]);
	mux_2to1 M2T1_1(in[2], in[3], sel[0], M2T1_out[1]);
	mux_2to1 M2T1_2(M2T1_out[0], M2T1_out[1], sel[1], out);
	

endmodule

Report4/Ex1/testM4T1.v
module test;
	reg [3:0]in;
	reg [1:0] sel;
	
	wire out;
	
	mux_4to1 M4T1(in, sel, out);
	
	initial begin
		for(in=4'd0; in<15; in=in+1)begin
			for(sel=2'd0; sel<3; sel=sel+1)begin
				#1;
			end
			#1 sel=sel+1;
		end
		
		for(sel=2'd0; sel<3; sel=sel+1)begin
			#1;
		end
		#1 sel=sel+1;
	end
	
	initial begin
		$monitor("in[3:0]= %b, sel=%b, out=%b", in, sel, out);
	end
	
	initial begin
		$dumpfile("testM4T1.vcd");
		$dumpvars;
	end
	
endmodule

Report4/Ex1/testM4T1.vcd
$date
	Sat Apr 14 21:51:29 2018
$end
$version
	Icarus Verilog
$end
$timescale
	1s
$end
$scope module test $end
$var wire 1 ! out $end
$var reg 4 " in [3:0] $end
$var reg 2 # sel [1:0] $end
$scope module M4T1 $end
$var wire 4 $ in [3:0] $end
$var wire 2 % sel [1:0] $end
$var wire 1 ! out $end
$scope module M2T1_0 $end
$var wire 1 & And_Out0 $end
$var wire 1 ' And_Out1 $end
$var wire 1 ( Not_Out0 $end
$var wire 1 ) in0 $end
$var wire 1 * in1 $end
$var wire 1 + out $end
$var wire 1 , sel $end
$upscope $end
$scope module M2T1_1 $end
$var wire 1 - And_Out0 $end
$var wire 1 . And_Out1 $end
$var wire 1 / Not_Out0 $end
$var wire 1 0 in0 $end
$var wire 1 1 in1 $end
$var wire 1 2 out $end
$var wire 1 3 sel $end
$upscope $end
$scope module M2T1_2 $end
$var wire 1 4 And_Out0 $end
$var wire 1 5 And_Out1 $end
$var wire 1 6 Not_Out0 $end
$var wire 1 + in0 $end
$var wire 1 2 in1 $end
$var wire 1 ! out $end
$var wire 1 7 sel $end
$upscope $end
$upscope $end
$upscope $end
$enddefinitions $end
#0
$dumpvars
07
16
05
04
03
02
01
00
1/
0.
0-
0,
0+
0*
0)
1(
0'
0&
b0 %
b0 $
b0 #
b0 "
0!
$end
#1
0(
0/
1,
13
b1 #
b1 %
#2
1(
1/
06
0,
03
17
b10 #
b10 %
#3
0(
0/
1,
13
b11 #
b11 %
#4
1!
14
1+
1&
1(
1/
16
1)
0,
03
07
b1 "
b1 $
b0 #
b0 %
#5
0!
04
0+
0&
0(
0/
1,
13
b1 #
b1 %
#6
1+
1&
1(
1/
06
0,
03
17
b10 #
b10 %
#7
0+
0&
0(
0/
1,
13
b11 #
b11 %
#8
1(
1/
16
0)
1*
0,
03
07
b10 "
b10 $
b0 #
b0 %
#9
1!
14
1+
0(
1'
0/
1,
13
b1 #
b1 %
#10
0!
0+
04
1(
0'
1/
06
0,
03
17
b10 #
b10 %
#11
1+
0(
1'
0/
1,
13
b11 #
b11 %
#12
1!
14
1&
1(
0'
1/
16
1)
0,
03
07
b11 "
b11 $
b0 #
b0 %
#13
0&
0(
1'
0/
1,
13
b1 #
b1 %
#14
0!
1&
1+
04
1(
0'
1/
06
0,
03
17
b10 #
b10 %
#15
0&
0(
1'
0/
1,
13
b11 #
b11 %
#16
0!
12
0+
04
1-
1(
0'
1/
16
0)
0*
10
0,
03
07
b100 "
b100 $
b0 #
b0 %
#17
02
0-
0(
0/
1,
13
b1 #
b1 %
#18
1!
15
12
1-
1(
1/
06
0,
03
17
b10 #
b10 %
#19
0!
05
02
0-
0(
0/
1,
13
b11 #
b11 %
#20
1!
14
12
1+
1-
1&
1(
1/
16
1)
0,
03
07
b101 "
b101 $
b0 #
b0 %
#21
0!
04
0+
02
0&
0-
0(
0/
1,
13
b1 #
b1 %
#22
1!
15
1+
12
1&
1-
1(
1/
06
0,
03
17
b10 #
b10 %
#23
0!
05
0+
02
0&
0-
0(
0/
1,
13
b11 #
b11 %
#24
12
1-
1(
1/
16
0)
1*
0,
03
07
b110 "
b110 $
b0 #
b0 %
#25
1!
14
02
1+
0-
0(
1'
0/
1,
13
b1 #
b1 %
#26
15
12
1!
0+
1-
04
1(
0'
1/
06
0,
03
17
b10 #
b10 %
#27
0!
05
02
1+
0-
0(
1'
0/
1,
13
b11 #
b11 %
#28
12
1!
1-
14
1&
1(
0'
1/
16
1)
0,
03
07
b111 "
b111 $
b0 #
b0 %
#29
02
0&
0-
0(
1'
0/
1,
13
b1 #
b1 %
#30
15
12
1!
1&
1+
1-
04
1(
0'
1/
06
0,
03
17
b10 #
b10 %
#31
0!
05
02
0&
0-
0(
1'
0/
1,
13
b11 #
b11 %
#32
0!
0+
04
1(
0'
1/
16
0)
0*
00
11
0,
03
07
b1000 "
b1000 $
b0 #
b0 %
#33
12
0(
0/
1.
1,
13
b1 #
b1 %
#34
02
0!
1(
1/
0.
06
05
0,
03
17
b10 #
b10 %
#35
1!
15
12
0(
0/
1.
1,
13
b11 #
b11 %
#36
14
1+
02
1!
1&
1(
1/
0.
16
05
1)
0,
03
07
b1001 "
b1001 $
b0 #
b0 %
#37
0!
04
0+
0&
12
0(
0/
1.
1,
13
b1 #
b1 %
#38
1+
1&
02
0!
1(
1/
0.
06
05
0,
03
17
b10 #
b10 %
#39
1!
0+
15
0&
12
0(
0/
1.
1,
13
b11 #
b11 %
#40
02
0!
1(
1/
0.
16
05
0)
1*
0,
03
07
b1010 "
b1010 $
b0 #
b0 %
#41
1!
14
1+
12
0(
1'
0/
1.
1,
13
b1 #
b1 %
#42
0!
0+
02
04
1(
0'
1/
0.
06
05
0,
03
17
b10 #
b10 %
#43
1!
15
1+
12
0(
1'
0/
1.
1,
13
b11 #
b11 %
#44
02
14
1!
1&
1(
0'
1/
0.
16
05
1)
0,
03
07
b1011 "
b1011 $
b0 #
b0 %
#45
0&
12
0(
1'
0/
1.
1,
13
b1 #
b1 %
#46
0!
1&
1+
02
04
1(
0'
1/
0.
06
05
0,
03
17
b10 #
b10 %
#47
1!
15
0&
12
0(
1'
0/
1.
1,
13
b11 #
b11 %
#48
0+
04
0!
1-
1(
0'
1/
0.
16
05
0)
0*
10
0,
03
07
b1100 "
b1100 $
b0 #
b0 %
#49
0-
0(
0/
1.
1,
13
b1 #
b1 %
#50
1-
12
1!
1(
1/
0.
06
15
0,
03
17
b10 #
b10 %
#51
0-
0(
0/
1.
1,
13
b11 #
b11 %
#52
14
1+
1-
12
1!
1&
1(
1/
0.
16
05
1)
0,
03
07
b1101 "
b1101 $
b0 #
b0 %
#53
0!
04
0+
0&
0-
0(
0/
1.
1,
13
b1 #
b1 %
#54
1+
1&
1-
12
1!
1(
1/
0.
06
15
0,
03
17
b10 #
b10 %
#55
0+
0&
0-
0(
0/
1.
1,
13
b11 #
b11 %
#56
1-
12
0!
1(
1/
0.
16
05
0)
1*
0,
03
07
b1110 "
b1110 $
b0 #
b0 %
#57
1!
14
1+
0-
0(
1'
0/
1.
1,
13
b1 #
b1 %
#58
1!
0+
1-
12
04
1(
0'
1/
0.
06
15
0,
03
17
b10 #
b10 %
#59
1+
0-
0(
1'
0/
1.
1,
13
b11 #
b11 %
#60
1-
12
14
1!
1&
1(
0'
1/
0.
16
05
1)
0,
03
07
b1111 "
b1111 $
b0 #
b0 %
#61
0&
0-
0(
1'
0/
1.
1,
13
b1 #
b1 %
#62
1!
1&
1+
1-
12
04
1(
0'
1/
0.
06
15
0,
03
17
b10 #
b10 %
#63
0&
0-
0(
1'
0/
1.
1,
13
b11 #
b11 %
#64
1&
1+
1-
12
14
1!
1(
0'
1/
0.
16
05
0,
03
07
b0 #
b0 %
