Report6/Ex1/fourBitALU.v
module fourBitALU(inA, inB, sel, out);
	input [3:0]inA;
	input [3:0]inB;
	input [2:0]sel;
	
	output [3:0]out;
	reg [3:0]out;
	
	parameter   ADD=3'b000,
				SUB=3'b001,
				AND=3'b010,
				OR =3'b011,
				XOR=3'b100,
				SHR=3'b101,
				SHL=3'b110,
				CMP=3'b111;
	
	always@(*)begin
		case(sel)
			ADD:out=inA+inB;
			SUB:out=inA-inB;
			AND:out=inA&inB;
			OR :out=inA|inB;
			XOR:out=inA^inB;
			SHR:out=inA>>inB;
			SHL:out=inA<<inB;
			CMP:out=inA>inB;
			default:out=4'b0;
		endcase
	end
	
	
endmodule

Report6/Ex1/sysFourBitALU.v
module system(clk, sel, inA, inB, out);
	input clk;
	input[2:0]sel;
	input[3:0]inA, inB;
	output[3:0]out;
	
	fourBitALU ALU0(.inA(inA), .inB(inB), .sel(sel), .out(out));
	
endmodule

Report6/Ex1/fourBitALUTest.v
module fourBitALUTest;
	reg [3:0]in0, in1;
	reg [2:0]sel;
	
	integer i;
	
	wire[3:0]out;
	
	system ALU0(.sel(sel), .inA(in0), .inB(in1), .out(out));
	
	initial begin
		in0=4'b1100;
		in1=4'b0001;
		sel=3'd0;
		for(i=5'd0; i<7; i=i+1)begin
			#1 sel=sel+1;
		end
		#1;
		in0=4'b0001;
		in1=4'b1101;
		sel=3'd0;
		for(i=5'd0; i<7; i=i+1)begin
			#1 sel=sel+1;
		end
	end
	
	initial begin
		$monitor("in0=%b, in1=%b, out=%b, sel=%b", in0, in1, out, sel);
	end
	
	initial begin
		$dumpfile("fourBitALUTest.vcd");
		$dumpvars;	
	end
	
endmodule

Report6/Ex1/fourBitALUTest.vcd
$date
	Wed Apr 25 11:44:01 2018
$end
$version
	Icarus Verilog
$end
$timescale
	1s
$end
$scope module fourBitALUTest $end
$var wire 4 ! out [3:0] $end
$var reg 4 " in0 [3:0] $end
$var reg 4 # in1 [3:0] $end
$var reg 3 $ sel [2:0] $end
$var integer 32 % i [31:0] $end
$scope module ALU0 $end
$var wire 1 & clk $end
$var wire 4 ' inA [3:0] $end
$var wire 4 ( inB [3:0] $end
$var wire 3 ) sel [2:0] $end
$var wire 4 * out [3:0] $end
$scope module ALU0 $end
$var wire 4 + inA [3:0] $end
$var wire 4 , inB [3:0] $end
$var wire 3 - sel [2:0] $end
$var reg 4 . out [3:0] $end
$upscope $end
$upscope $end
$upscope $end
$enddefinitions $end
#0
$dumpvars
b1101 .
b0 -
b1 ,
b1100 +
b1101 *
b0 )
b1 (
b1100 '
z&
b0 %
b0 $
b1 #
b1100 "
b1101 !
$end
#1
b1011 !
b1011 *
b1011 .
b1 %
b1 $
b1 )
b1 -
#2
b0 !
b0 *
b0 .
b10 %
b10 $
b10 )
b10 -
#3
b1101 !
b1101 *
b1101 .
b11 %
b11 $
b11 )
b11 -
#4
b100 %
b100 $
b100 )
b100 -
#5
b110 !
b110 *
b110 .
b101 %
b101 $
b101 )
b101 -
#6
b1000 !
b1000 *
b1000 .
b110 %
b110 $
b110 )
b110 -
#7
b1 !
b1 *
b1 .
b111 %
b111 $
b111 )
b111 -
#8
b1110 !
b1110 *
b1110 .
b0 %
b0 $
b0 )
b0 -
b1101 #
b1101 (
b1101 ,
b1 "
b1 '
b1 +
#9
b100 !
b100 *
b100 .
b1 %
b1 $
b1 )
b1 -
#10
b1 !
b1 *
b1 .
b10 %
b10 $
b10 )
b10 -
#11
b1101 !
b1101 *
b1101 .
b11 %
b11 $
b11 )
b11 -
#12
b1100 !
b1100 *
b1100 .
b100 %
b100 $
b100 )
b100 -
#13
b0 !
b0 *
b0 .
b101 %
b101 $
b101 )
b101 -
#14
b110 %
b110 $
b110 )
b110 -
#15
b111 %
b111 $
b111 )
b111 -
