Report5/Ex1/fourBitFA.v
module fourBitFA(inA, inB, carryIn, sum, carryOut);
	input [3:0]inA, inB;
	input carryIn;
	output [3:0]sum;
	output carryOut;
	
	assign {carryOut, sum}=inA+inB+carryIn;

endmodule

Report5/Ex1/testFourBitFA.v
module testFourBitFA;

	reg [0:3] INa;
	reg [0:3] INb;
	reg CarryIn;

	wire [0:3] Sum;
	wire CarryOut;

	fourBitFA fourBitFA0 (INa, INb, CarryIn, Sum, CarryOut);

	initial begin
		for(INa=0; INa<15; INa=INa+1)begin
			for(INb=0; INb<15; INb=INb+1)begin
				CarryIn=0;
				#1 CarryIn=1;
				#1;
			end
			CarryIn=0;
			#1 CarryIn=1;
			#1;
		end
		for(INb=0; INb<15; INb=INb+1)begin
				CarryIn=0;
				#1 CarryIn=1;
				#1;
		end
		CarryIn=0;
		#1 CarryIn=1;
		#1;
	end
	
	initial begin
		$monitor(" CarryIn=%b, INa=%b, INb=%b, Sum=%b, CarryOut=%b", CarryIn, INa, INb, Sum, CarryOut);
	end
	
	initial begin
		$dumpfile("testFourBitFA.vcd");
		$dumpvars;
	end
      
endmodule

Report5/Ex1/testFourBitFA.vcd
$date
	Mon Apr 23 19:27:21 2018
$end
$version
	Icarus Verilog
$end
$timescale
	1s
$end
$scope module testFourBitFA $end
$var wire 4 ! Sum [0:3] $end
$var wire 1 " CarryOut $end
$var reg 1 # CarryIn $end
$var reg 4 $ INa [0:3] $end
$var reg 4 % INb [0:3] $end
$scope module fourBitFA0 $end
$var wire 1 # carryIn $end
$var wire 4 & inA [3:0] $end
$var wire 4 ' inB [3:0] $end
$var wire 4 ( sum [3:0] $end
$var wire 1 " carryOut $end
$upscope $end
$upscope $end
$enddefinitions $end
#0
$dumpvars
b0 (
b0 '
b0 &
b0 %
b0 $
0#
0"
b0 !
$end
#1
b1 !
b1 (
1#
#2
0#
b1 %
b1 '
#3
b10 !
b10 (
1#
#4
0#
b10 %
b10 '
#5
b11 !
b11 (
1#
#6
0#
b11 %
b11 '
#7
b100 !
b100 (
1#
#8
0#
b100 %
b100 '
#9
b101 !
b101 (
1#
#10
0#
b101 %
b101 '
#11
b110 !
b110 (
1#
#12
0#
b110 %
b110 '
#13
b111 !
b111 (
1#
#14
0#
b111 %
b111 '
#15
b1000 !
b1000 (
1#
#16
0#
b1000 %
b1000 '
#17
b1001 !
b1001 (
1#
#18
0#
b1001 %
b1001 '
#19
b1010 !
b1010 (
1#
#20
0#
b1010 %
b1010 '
#21
b1011 !
b1011 (
1#
#22
0#
b1011 %
b1011 '
#23
b1100 !
b1100 (
1#
#24
0#
b1100 %
b1100 '
#25
b1101 !
b1101 (
1#
#26
0#
b1101 %
b1101 '
#27
b1110 !
b1110 (
1#
#28
0#
b1110 %
b1110 '
#29
b1111 !
b1111 (
1#
#30
0#
b1111 %
b1111 '
#31
b0 !
b0 (
1"
1#
#32
0"
b1 !
b1 (
0#
b0 %
b0 '
b1 $
b1 &
#33
b10 !
b10 (
1#
#34
0#
b1 %
b1 '
#35
b11 !
b11 (
1#
#36
0#
b10 %
b10 '
#37
b100 !
b100 (
1#
#38
0#
b11 %
b11 '
#39
b101 !
b101 (
1#
#40
0#
b100 %
b100 '
#41
b110 !
b110 (
1#
#42
0#
b101 %
b101 '
#43
b111 !
b111 (
1#
#44
0#
b110 %
b110 '
#45
b1000 !
b1000 (
1#
#46
0#
b111 %
b111 '
#47
b1001 !
b1001 (
1#
#48
0#
b1000 %
b1000 '
#49
b1010 !
b1010 (
1#
#50
0#
b1001 %
b1001 '
#51
b1011 !
b1011 (
1#
#52
0#
b1010 %
b1010 '
#53
b1100 !
b1100 (
1#
#54
0#
b1011 %
b1011 '
#55
b1101 !
b1101 (
1#
#56
0#
b1100 %
b1100 '
#57
b1110 !
b1110 (
1#
#58
0#
b1101 %
b1101 '
#59
b1111 !
b1111 (
1#
#60
0#
b1110 %
b1110 '
#61
b0 !
b0 (
1"
1#
#62
0#
b1111 %
b1111 '
#63
b1 !
b1 (
1#
#64
0"
b10 !
b10 (
0#
b0 %
b0 '
b10 $
b10 &
#65
b11 !
b11 (
1#
#66
0#
b1 %
b1 '
#67
b100 !
b100 (
1#
#68
0#
b10 %
b10 '
#69
b101 !
b101 (
1#
#70
0#
b11 %
b11 '
#71
b110 !
b110 (
1#
#72
0#
b100 %
b100 '
#73
b111 !
b111 (
1#
#74
0#
b101 %
b101 '
#75
b1000 !
b1000 (
1#
#76
0#
b110 %
b110 '
#77
b1001 !
b1001 (
1#
#78
0#
b111 %
b111 '
#79
b1010 !
b1010 (
1#
#80
0#
b1000 %
b1000 '
#81
b1011 !
b1011 (
1#
#82
0#
b1001 %
b1001 '
#83
b1100 !
b1100 (
1#
#84
0#
b1010 %
b1010 '
#85
b1101 !
b1101 (
1#
#86
0#
b1011 %
b1011 '
#87
b1110 !
b1110 (
1#
#88
0#
b1100 %
b1100 '
#89
b1111 !
b1111 (
1#
#90
0#
b1101 %
b1101 '
#91
b0 !
b0 (
1"
1#
#92
0#
b1110 %
b1110 '
#93
b1 !
b1 (
1#
#94
0#
b1111 %
b1111 '
#95
b10 !
b10 (
1#
#96
0"
b11 !
b11 (
0#
b0 %
b0 '
b11 $
b11 &
#97
b100 !
b100 (
1#
#98
0#
b1 %
b1 '
#99
b101 !
b101 (
1#
#100
0#
b10 %
b10 '
#101
b110 !
b110 (
1#
#102
0#
b11 %
b11 '
#103
b111 !
b111 (
1#
#104
0#
b100 %
b100 '
#105
b1000 !
b1000 (
1#
#106
0#
b101 %
b101 '
#107
b1001 !
b1001 (
1#
#108
0#
b110 %
b110 '
#109
b1010 !
b1010 (
1#
#110
0#
b111 %
b111 '
#111
b1011 !
b1011 (
1#
#112
0#
b1000 %
b1000 '
#113
b1100 !
b1100 (
1#
#114
0#
b1001 %
b1001 '
#115
b1101 !
b1101 (
1#
#116
0#
b1010 %
b1010 '
#117
b1110 !
b1110 (
1#
#118
0#
b1011 %
b1011 '
#119
b1111 !
b1111 (
1#
#120
0#
b1100 %
b1100 '
#121
b0 !
b0 (
1"
1#
#122
0#
b1101 %
b1101 '
#123
b1 !
b1 (
1#
#124
0#
b1110 %
b1110 '
#125
b10 !
b10 (
1#
#126
0#
b1111 %
b1111 '
#127
b11 !
b11 (
1#
#128
0"
b100 !
b100 (
0#
b0 %
b0 '
b100 $
b100 &
#129
b101 !
b101 (
1#
#130
0#
b1 %
b1 '
#131
b110 !
b110 (
1#
#132
0#
b10 %
b10 '
#133
b111 !
b111 (
1#
#134
0#
b11 %
b11 '
#135
b1000 !
b1000 (
1#
#136
0#
b100 %
b100 '
#137
b1001 !
b1001 (
1#
#138
0#
b101 %
b101 '
#139
b1010 !
b1010 (
1#
#140
0#
b110 %
b110 '
#141
b1011 !
b1011 (
1#
#142
0#
b111 %
b111 '
#143
b1100 !
b1100 (
1#
#144
0#
b1000 %
b1000 '
#145
b1101 !
b1101 (
1#
#146
0#
b1001 %
b1001 '
#147
b1110 !
b1110 (
1#
#148
0#
b1010 %
b1010 '
#149
b1111 !
b1111 (
1#
#150
0#
b1011 %
b1011 '
#151
b0 !
b0 (
1"
1#
#152
0#
b1100 %
b1100 '
#153
b1 !
b1 (
1#
#154
0#
b1101 %
b1101 '
#155
b10 !
b10 (
1#
#156
0#
b1110 %
b1110 '
#157
b11 !
b11 (
1#
#158
0#
b1111 %
b1111 '
#159
b100 !
b100 (
1#
#160
0"
b101 !
b101 (
0#
b0 %
b0 '
b101 $
b101 &
#161
b110 !
b110 (
1#
#162
0#
b1 %
b1 '
#163
b111 !
b111 (
1#
#164
0#
b10 %
b10 '
#165
b1000 !
b1000 (
1#
#166
0#
b11 %
b11 '
#167
b1001 !
b1001 (
1#
#168
0#
b100 %
b100 '
#169
b1010 !
b1010 (
1#
#170
0#
b101 %
b101 '
#171
b1011 !
b1011 (
1#
#172
0#
b110 %
b110 '
#173
b1100 !
b1100 (
1#
#174
0#
b111 %
b111 '
#175
b1101 !
b1101 (
1#
#176
0#
b1000 %
b1000 '
#177
b1110 !
b1110 (
1#
#178
0#
b1001 %
b1001 '
#179
b1111 !
b1111 (
1#
#180
0#
b1010 %
b1010 '
#181
b0 !
b0 (
1"
1#
#182
0#
b1011 %
b1011 '
#183
b1 !
b1 (
1#
#184
0#
b1100 %
b1100 '
#185
b10 !
b10 (
1#
#186
0#
b1101 %
b1101 '
#187
b11 !
b11 (
1#
#188
0#
b1110 %
b1110 '
#189
b100 !
b100 (
1#
#190
0#
b1111 %
b1111 '
#191
b101 !
b101 (
1#
#192
0"
b110 !
b110 (
0#
b0 %
b0 '
b110 $
b110 &
#193
b111 !
b111 (
1#
#194
0#
b1 %
b1 '
#195
b1000 !
b1000 (
1#
#196
0#
b10 %
b10 '
#197
b1001 !
b1001 (
1#
#198
0#
b11 %
b11 '
#199
b1010 !
b1010 (
1#
#200
0#
b100 %
b100 '
#201
b1011 !
b1011 (
1#
#202
0#
b101 %
b101 '
#203
b1100 !
b1100 (
1#
#204
0#
b110 %
b110 '
#205
b1101 !
b1101 (
1#
#206
0#
b111 %
b111 '
#207
b1110 !
b1110 (
1#
#208
0#
b1000 %
b1000 '
#209
b1111 !
b1111 (
1#
#210
0#
b1001 %
b1001 '
#211
b0 !
b0 (
1"
1#
#212
0#
b1010 %
b1010 '
#213
b1 !
b1 (
1#
#214
0#
b1011 %
b1011 '
#215
b10 !
b10 (
1#
#216
0#
b1100 %
b1100 '
#217
b11 !
b11 (
1#
#218
0#
b1101 %
b1101 '
#219
b100 !
b100 (
1#
#220
0#
b1110 %
b1110 '
#221
b101 !
b101 (
1#
#222
0#
b1111 %
b1111 '
#223
b110 !
b110 (
1#
#224
0"
b111 !
b111 (
0#
b0 %
b0 '
b111 $
b111 &
#225
b1000 !
b1000 (
1#
#226
0#
b1 %
b1 '
#227
b1001 !
b1001 (
1#
#228
0#
b10 %
b10 '
#229
b1010 !
b1010 (
1#
#230
0#
b11 %
b11 '
#231
b1011 !
b1011 (
1#
#232
0#
b100 %
b100 '
#233
b1100 !
b1100 (
1#
#234
0#
b101 %
b101 '
#235
b1101 !
b1101 (
1#
#236
0#
b110 %
b110 '
#237
b1110 !
b1110 (
1#
#238
0#
b111 %
b111 '
#239
b1111 !
b1111 (
1#
#240
0#
b1000 %
b1000 '
#241
b0 !
b0 (
1"
1#
#242
0#
b1001 %
b1001 '
#243
b1 !
b1 (
1#
#244
0#
b1010 %
b1010 '
#245
b10 !
b10 (
1#
#246
0#
b1011 %
b1011 '
#247
b11 !
b11 (
1#
#248
0#
b1100 %
b1100 '
#249
b100 !
b100 (
1#
#250
0#
b1101 %
b1101 '
#251
b101 !
b101 (
1#
#252
0#
b1110 %
b1110 '
#253
b110 !
b110 (
1#
#254
0#
b1111 %
b1111 '
#255
b111 !
b111 (
1#
#256
0"
b1000 !
b1000 (
0#
b0 %
b0 '
b1000 $
b1000 &
#257
b1001 !
b1001 (
1#
#258
0#
b1 %
b1 '
#259
b1010 !
b1010 (
1#
#260
0#
b10 %
b10 '
#261
b1011 !
b1011 (
1#
#262
0#
b11 %
b11 '
#263
b1100 !
b1100 (
1#
#264
0#
b100 %
b100 '
#265
b1101 !
b1101 (
1#
#266
0#
b101 %
b101 '
#267
b1110 !
b1110 (
1#
#268
0#
b110 %
b110 '
#269
b1111 !
b1111 (
1#
#270
0#
b111 %
b111 '
#271
b0 !
b0 (
1"
1#
#272
0#
b1000 %
b1000 '
#273
b1 !
b1 (
1#
#274
0#
b1001 %
b1001 '
#275
b10 !
b10 (
1#
#276
0#
b1010 %
b1010 '
#277
b11 !
b11 (
1#
#278
0#
b1011 %
b1011 '
#279
b100 !
b100 (
1#
#280
0#
b1100 %
b1100 '
#281
b101 !
b101 (
1#
#282
0#
b1101 %
b1101 '
#283
b110 !
b110 (
1#
#284
0#
b1110 %
b1110 '
#285
b111 !
b111 (
1#
#286
0#
b1111 %
b1111 '
#287
b1000 !
b1000 (
1#
#288
0"
b1001 !
b1001 (
0#
b0 %
b0 '
b1001 $
b1001 &
#289
b1010 !
b1010 (
1#
#290
0#
b1 %
b1 '
#291
b1011 !
b1011 (
1#
#292
0#
b10 %
b10 '
#293
b1100 !
b1100 (
1#
#294
0#
b11 %
b11 '
#295
b1101 !
b1101 (
1#
#296
0#
b100 %
b100 '
#297
b1110 !
b1110 (
1#
#298
0#
b101 %
b101 '
#299
b1111 !
b1111 (
1#
#300
0#
b110 %
b110 '
#301
b0 !
b0 (
1"
1#
#302
0#
b111 %
b111 '
#303
b1 !
b1 (
1#
#304
0#
b1000 %
b1000 '
#305
b10 !
b10 (
1#
#306
0#
b1001 %
b1001 '
#307
b11 !
b11 (
1#
#308
0#
b1010 %
b1010 '
#309
b100 !
b100 (
1#
#310
0#
b1011 %
b1011 '
#311
b101 !
b101 (
1#
#312
0#
b1100 %
b1100 '
#313
b110 !
b110 (
1#
#314
0#
b1101 %
b1101 '
#315
b111 !
b111 (
1#
#316
0#
b1110 %
b1110 '
#317
b1000 !
b1000 (
1#
#318
0#
b1111 %
b1111 '
#319
b1001 !
b1001 (
1#
#320
0"
b1010 !
b1010 (
0#
b0 %
b0 '
b1010 $
b1010 &
#321
b1011 !
b1011 (
1#
#322
0#
b1 %
b1 '
#323
b1100 !
b1100 (
1#
#324
0#
b10 %
b10 '
#325
b1101 !
b1101 (
1#
#326
0#
b11 %
b11 '
#327
b1110 !
b1110 (
1#
#328
0#
b100 %
b100 '
#329
b1111 !
b1111 (
1#
#330
0#
b101 %
b101 '
#331
b0 !
b0 (
1"
1#
#332
0#
b110 %
b110 '
#333
b1 !
b1 (
1#
#334
0#
b111 %
b111 '
#335
b10 !
b10 (
1#
#336
0#
b1000 %
b1000 '
#337
b11 !
b11 (
1#
#338
0#
b1001 %
b1001 '
#339
b100 !
b100 (
1#
#340
0#
b1010 %
b1010 '
#341
b101 !
b101 (
1#
#342
0#
b1011 %
b1011 '
#343
b110 !
b110 (
1#
#344
0#
b1100 %
b1100 '
#345
b111 !
b111 (
1#
#346
0#
b1101 %
b1101 '
#347
b1000 !
b1000 (
1#
#348
0#
b1110 %
b1110 '
#349
b1001 !
b1001 (
1#
#350
0#
b1111 %
b1111 '
#351
b1010 !
b1010 (
1#
#352
0"
b1011 !
b1011 (
0#
b0 %
b0 '
b1011 $
b1011 &
#353
b1100 !
b1100 (
1#
#354
0#
b1 %
b1 '
#355
b1101 !
b1101 (
1#
#356
0#
b10 %
b10 '
#357
b1110 !
b1110 (
1#
#358
0#
b11 %
b11 '
#359
b1111 !
b1111 (
1#
#360
0#
b100 %
b100 '
#361
b0 !
b0 (
1"
1#
#362
0#
b101 %
b101 '
#363
b1 !
b1 (
1#
#364
0#
b110 %
b110 '
#365
b10 !
b10 (
1#
#366
0#
b111 %
b111 '
#367
b11 !
b11 (
1#
#368
0#
b1000 %
b1000 '
#369
b100 !
b100 (
1#
#370
0#
b1001 %
b1001 '
#371
b101 !
b101 (
1#
#372
0#
b1010 %
b1010 '
#373
b110 !
b110 (
1#
#374
0#
b1011 %
b1011 '
#375
b111 !
b111 (
1#
#376
0#
b1100 %
b1100 '
#377
b1000 !
b1000 (
1#
#378
0#
b1101 %
b1101 '
#379
b1001 !
b1001 (
1#
#380
0#
b1110 %
b1110 '
#381
b1010 !
b1010 (
1#
#382
0#
b1111 %
b1111 '
#383
b1011 !
b1011 (
1#
#384
0"
b1100 !
b1100 (
0#
b0 %
b0 '
b1100 $
b1100 &
#385
b1101 !
b1101 (
1#
#386
0#
b1 %
b1 '
#387
b1110 !
b1110 (
1#
#388
0#
b10 %
b10 '
#389
b1111 !
b1111 (
1#
#390
0#
b11 %
b11 '
#391
b0 !
b0 (
1"
1#
#392
0#
b100 %
b100 '
#393
b1 !
b1 (
1#
#394
0#
b101 %
b101 '
#395
b10 !
b10 (
1#
#396
0#
b110 %
b110 '
#397
b11 !
b11 (
1#
#398
0#
b111 %
b111 '
#399
b100 !
b100 (
1#
#400
0#
b1000 %
b1000 '
#401
b101 !
b101 (
1#
#402
0#
b1001 %
b1001 '
#403
b110 !
b110 (
1#
#404
0#
b1010 %
b1010 '
#405
b111 !
b111 (
1#
#406
0#
b1011 %
b1011 '
#407
b1000 !
b1000 (
1#
#408
0#
b1100 %
b1100 '
#409
b1001 !
b1001 (
1#
#410
0#
b1101 %
b1101 '
#411
b1010 !
b1010 (
1#
#412
0#
b1110 %
b1110 '
#413
b1011 !
b1011 (
1#
#414
0#
b1111 %
b1111 '
#415
b1100 !
b1100 (
1#
#416
0"
b1101 !
b1101 (
0#
b0 %
b0 '
b1101 $
b1101 &
#417
b1110 !
b1110 (
1#
#418
0#
b1 %
b1 '
#419
b1111 !
b1111 (
1#
#420
0#
b10 %
b10 '
#421
b0 !
b0 (
1"
1#
#422
0#
b11 %
b11 '
#423
b1 !
b1 (
1#
#424
0#
b100 %
b100 '
#425
b10 !
b10 (
1#
#426
0#
b101 %
b101 '
#427
b11 !
b11 (
1#
#428
0#
b110 %
b110 '
#429
b100 !
b100 (
1#
#430
0#
b111 %
b111 '
#431
b101 !
b101 (
1#
#432
0#
b1000 %
b1000 '
#433
b110 !
b110 (
1#
#434
0#
b1001 %
b1001 '
#435
b111 !
b111 (
1#
#436
0#
b1010 %
b1010 '
#437
b1000 !
b1000 (
1#
#438
0#
b1011 %
b1011 '
#439
b1001 !
b1001 (
1#
#440
0#
b1100 %
b1100 '
#441
b1010 !
b1010 (
1#
#442
0#
b1101 %
b1101 '
#443
b1011 !
b1011 (
1#
#444
0#
b1110 %
b1110 '
#445
b1100 !
b1100 (
1#
#446
0#
b1111 %
b1111 '
#447
b1101 !
b1101 (
1#
#448
0"
b1110 !
b1110 (
0#
b0 %
b0 '
b1110 $
b1110 &
#449
b1111 !
b1111 (
1#
#450
0#
b1 %
b1 '
#451
b0 !
b0 (
1"
1#
#452
0#
b10 %
b10 '
#453
b1 !
b1 (
1#
#454
0#
b11 %
b11 '
#455
b10 !
b10 (
1#
#456
0#
b100 %
b100 '
#457
b11 !
b11 (
1#
#458
0#
b101 %
b101 '
#459
b100 !
b100 (
1#
#460
0#
b110 %
b110 '
#461
b101 !
b101 (
1#
#462
0#
b111 %
b111 '
#463
b110 !
b110 (
1#
#464
0#
b1000 %
b1000 '
#465
b111 !
b111 (
1#
#466
0#
b1001 %
b1001 '
#467
b1000 !
b1000 (
1#
#468
0#
b1010 %
b1010 '
#469
b1001 !
b1001 (
1#
#470
0#
b1011 %
b1011 '
#471
b1010 !
b1010 (
1#
#472
0#
b1100 %
b1100 '
#473
b1011 !
b1011 (
1#
#474
0#
b1101 %
b1101 '
#475
b1100 !
b1100 (
1#
#476
0#
b1110 %
b1110 '
#477
b1101 !
b1101 (
1#
#478
0#
b1111 %
b1111 '
#479
b1110 !
b1110 (
1#
#480
0"
b1111 !
b1111 (
0#
b0 %
b0 '
b1111 $
b1111 &
#481
b0 !
b0 (
1"
1#
#482
0#
b1 %
b1 '
#483
b1 !
b1 (
1#
#484
0#
b10 %
b10 '
#485
b10 !
b10 (
1#
#486
0#
b11 %
b11 '
#487
b11 !
b11 (
1#
#488
0#
b100 %
b100 '
#489
b100 !
b100 (
1#
#490
0#
b101 %
b101 '
#491
b101 !
b101 (
1#
#492
0#
b110 %
b110 '
#493
b110 !
b110 (
1#
#494
0#
b111 %
b111 '
#495
b111 !
b111 (
1#
#496
0#
b1000 %
b1000 '
#497
b1000 !
b1000 (
1#
#498
0#
b1001 %
b1001 '
#499
b1001 !
b1001 (
1#
#500
0#
b1010 %
b1010 '
#501
b1010 !
b1010 (
1#
#502
0#
b1011 %
b1011 '
#503
b1011 !
b1011 (
1#
#504
0#
b1100 %
b1100 '
#505
b1100 !
b1100 (
1#
#506
0#
b1101 %
b1101 '
#507
b1101 !
b1101 (
1#
#508
0#
b1110 %
b1110 '
#509
b1110 !
b1110 (
1#
#510
0#
b1111 %
b1111 '
#511
b1111 !
b1111 (
1#
