Report4/Ex3/semiAdder.v
module semiAdder(in0, in1, sum, carry);
	input in0, in1;
	output sum, carry;
	
	xor XOR0(sum, in0, in1);
	and AND0(carry, in0, in1);

endmodule

Report4/Ex2/fullAdder.v
module fullAdder(in0, in1, in2, sum, carry);
	
	input in0, in1, in2;
	output sum, carry;
	
	wire carry0, carry1, sum0;
	
	semiAdder SA0(in0, in1, sum0, carry0);
	semiAdder SA1(in2, sum0, sum, carry1);
	or OR0(carry, carry0, carry1);
	
endmodule

Report4/Ex2/testFullAdder.v
module testFullAdder;

	reg [2:0] in;

	wire sum;
	wire carry;

	fullAdder FA0 (.in0(in[0]),.in1(in[1]),.in2(in[2]),.sum(sum),.carry(carry));

	initial begin
		for(in=3'd0; in<7; in=in+1)begin
			#1;
		end
		#1;
	end
      
	initial begin
		$monitor("in0=%b, in1=%b, in2=%b, sum=%b, carry=%b", in[0], in[1], in[2], sum, carry);
	end
	
	initial begin
		$dumpfile("testFullAdder.vcd");
		$dumpvars;
	end
		
endmodule

Report4/Ex2/testFullAdder.vcd
$date
	Sat Apr 14 22:10:47 2018
$end
$version
	Icarus Verilog
$end
$timescale
	1s
$end
$scope module testFullAdder $end
$var wire 1 ! sum $end
$var wire 1 " carry $end
$var reg 3 # in [2:0] $end
$scope module FA0 $end
$var wire 1 " carry $end
$var wire 1 $ in0 $end
$var wire 1 % in1 $end
$var wire 1 & in2 $end
$var wire 1 ' sum0 $end
$var wire 1 ! sum $end
$var wire 1 ( carry1 $end
$var wire 1 ) carry0 $end
$scope module SA0 $end
$var wire 1 ) carry $end
$var wire 1 $ in0 $end
$var wire 1 % in1 $end
$var wire 1 ' sum $end
$upscope $end
$scope module SA1 $end
$var wire 1 ( carry $end
$var wire 1 & in0 $end
$var wire 1 ' in1 $end
$var wire 1 ! sum $end
$upscope $end
$upscope $end
$upscope $end
$enddefinitions $end
#0
$dumpvars
0)
0(
0'
0&
0%
0$
b0 #
0"
0!
$end
#1
1!
1'
1$
b1 #
#2
0$
1%
b10 #
#3
0!
1"
0'
1)
1$
b11 #
#4
0"
0)
1!
0$
0%
1&
b100 #
#5
1"
0!
1(
1'
1$
b101 #
#6
0$
1%
b110 #
#7
1!
0(
0'
1)
1$
b111 #
