Report9/Ex3/LEDMatrix.v
module LEDMatrix(clk, rst, sel, row, col);
	input clk, rst;
	input [1:0]sel;
	
	output reg[7:0]row, col;
	
	always@(posedge clk or posedge rst)begin
		if(rst) row<=8'b00000001;
		else if(row==8'b10000000) row<=8'b00000001;
		else row<=row<<1'b1;
	end
	
	always@(*)begin
		case(sel)
			2'b00:begin
				case(row)
					8'b00000001:col=8'b00111000;
					8'b00000010:col=8'b00111000;
					8'b00000100:col=8'b10010000;
					8'b00001000:col=8'b01111110;
					8'b00010000:col=8'b00010000;
					8'b00100000:col=8'b00110100;
					8'b01000000:col=8'b01001000;
					8'b10000000:col=8'b10000000;
				endcase
			end
			2'b01:begin
				case(row)
					8'b00000001:col=8'b00111000;
					8'b00000010:col=8'b00111000;
					8'b00000100:col=8'b01010000;
					8'b00001000:col=8'b00111100;
					8'b00010000:col=8'b00010010;
					8'b00100000:col=8'b00110000;
					8'b01000000:col=8'b01001100;
					8'b10000000:col=8'b01000000;
				endcase
			end
			2'b10:begin
				case(row)
					8'b00000001:col=8'b00111000;
					8'b00000010:col=8'b00111000;
					8'b00000100:col=8'b00010000;
					8'b00001000:col=8'b01011000;
					8'b00010000:col=8'b00110100;
					8'b00100000:col=8'b00010000;
					8'b01000000:col=8'b00101000;
					8'b10000000:col=8'b00100100;
				endcase
			end
			2'b11:begin
				case(row)
					8'b00000001:col=8'b00111000;
					8'b00000010:col=8'b00111000;
					8'b00000100:col=8'b01010000;
					8'b00001000:col=8'b00111100;
					8'b00010000:col=8'b00010010;
					8'b00100000:col=8'b00110000;
					8'b01000000:col=8'b01001100;
					8'b10000000:col=8'b01000000;
				endcase
			end
		endcase
	end
	
endmodule

Report9/Ex3/counter.v
module counter(clk, rst, out);
	input clk, rst;
	
	output [1:0]out;
	assign out=cnt[9:8];
	
	reg [9:0]cnt;
	
	always@(posedge clk or posedge rst)begin
		if(rst) cnt<=10'd0;
		else cnt<=cnt+10'd1;
	end
endmodule

Report9/Ex3/freqDevider.v
module freqDevider(clk, rst, dclk);
	input clk, rst;
	
	output reg dclk;
	
	reg[24:0]count;
	
	always@(posedge clk, posedge rst)begin
		if(rst)begin
			dclk<=1'b0;
			count<=25'd0;
		end
		
		else if(count==25'd24000)begin
			dclk<=~dclk;
			count<=25'd0;
		end
		
		else count<=count+25'd1;
		
	end

endmodule

Report9/Ex3/system.v
module system(clk, rst, row, col);
	input clk, rst;
	
	output[7:0]row, col;
	
	wire dclk;
	wire[1:0]sel;
	
	freqDevider FD(.clk(clk), .dclk(dclk));
	counter CNT(.clk(clk), .rst(rst), .out(sel));
	LEDMatrix LM(.clk(clk), .rst(rst), .row(row), .col(col), .sel(sel));
	
endmodule

Report9/Ex3/test.v
module test;
	reg clk, rst;	
	
	wire[7:0]row, col;
	wire[1:0]sel;
	
	integer cnt=0;
	
	system S(.clk(clk), .rst(rst), .row(row), .col(col));
	
	initial begin
		rst=1'b1;#1 rst=1'b0;
		clk=1'd0;
		for(cnt=0; cnt<32'd1100; cnt=cnt+1)begin
			clk=~clk;
			#1;
		end
	end
	
	initial begin
		$monitor("row:%b, col:%b, cnt:%d", row, col, cnt);
	end
	
	initial begin
		$dumpfile("test.vcd");
		$dumpvars;
	end	
endmodule

Report9/Ex3/test.vcd
$date
	Sun Jun 03 11:32:32 2018
$end
$version
	Icarus Verilog
$end
$timescale
	1s
$end
$scope module test $end
$var wire 8 ! row [7:0] $end
$var wire 8 " col [7:0] $end
$var reg 1 # clk $end
$var reg 1 $ rst $end
$var integer 32 % cnt [31:0] $end
$scope module S $end
$var wire 1 # clk $end
$var wire 1 $ rst $end
$var wire 2 & sel [1:0] $end
$var wire 8 ' row [7:0] $end
$var wire 1 ( dclk $end
$var wire 8 ) col [7:0] $end
$scope module CNT $end
$var wire 1 # clk $end
$var wire 1 $ rst $end
$var wire 2 * out [1:0] $end
$var reg 10 + cnt [9:0] $end
$upscope $end
$scope module FD $end
$var wire 1 # clk $end
$var wire 1 , rst $end
$var reg 25 - count [24:0] $end
$var reg 1 ( dclk $end
$upscope $end
$scope module LM $end
$var wire 1 # clk $end
$var wire 1 $ rst $end
$var wire 2 . sel [1:0] $end
$var reg 8 / col [7:0] $end
$var reg 8 0 row [7:0] $end
$upscope $end
$upscope $end
$upscope $end
$enddefinitions $end
#0
$dumpvars
b1 0
b111000 /
b0 .
bx -
z,
b0 +
b0 *
b111000 )
x(
b1 '
b0 &
b0 %
1$
x#
b111000 "
b1 !
$end
#1
b10 !
b10 '
b10 0
b1 +
1#
0$
#2
0#
b1 %
#3
b10010000 "
b10010000 )
b10010000 /
b10 +
b100 !
b100 '
b100 0
1#
b10 %
#4
0#
b11 %
#5
b1111110 "
b1111110 )
b1111110 /
b1000 !
b1000 '
b1000 0
b11 +
1#
b100 %
#6
0#
b101 %
#7
b10000 "
b10000 )
b10000 /
b100 +
b10000 !
b10000 '
b10000 0
1#
b110 %
#8
0#
b111 %
#9
b110100 "
b110100 )
b110100 /
b100000 !
b100000 '
b100000 0
b101 +
1#
b1000 %
#10
0#
b1001 %
#11
b1001000 "
b1001000 )
b1001000 /
b110 +
b1000000 !
b1000000 '
b1000000 0
1#
b1010 %
#12
0#
b1011 %
#13
b10000000 "
b10000000 )
b10000000 /
b10000000 !
b10000000 '
b10000000 0
b111 +
1#
b1100 %
#14
0#
b1101 %
#15
b111000 "
b111000 )
b111000 /
b1000 +
b1 !
b1 '
b1 0
1#
b1110 %
#16
0#
b1111 %
#17
b10 !
b10 '
b10 0
b1001 +
1#
b10000 %
#18
0#
b10001 %
#19
b10010000 "
b10010000 )
b10010000 /
b1010 +
b100 !
b100 '
b100 0
1#
b10010 %
#20
0#
b10011 %
#21
b1111110 "
b1111110 )
b1111110 /
b1000 !
b1000 '
b1000 0
b1011 +
1#
b10100 %
#22
0#
b10101 %
#23
b10000 "
b10000 )
b10000 /
b1100 +
b10000 !
b10000 '
b10000 0
1#
b10110 %
#24
0#
b10111 %
#25
b110100 "
b110100 )
b110100 /
b100000 !
b100000 '
b100000 0
b1101 +
1#
b11000 %
#26
0#
b11001 %
#27
b1001000 "
b1001000 )
b1001000 /
b1110 +
b1000000 !
b1000000 '
b1000000 0
1#
b11010 %
#28
0#
b11011 %
#29
b10000000 "
b10000000 )
b10000000 /
b10000000 !
b10000000 '
b10000000 0
b1111 +
1#
b11100 %
#30
0#
b11101 %
#31
b111000 "
b111000 )
b111000 /
b10000 +
b1 !
b1 '
b1 0
1#
b11110 %
#32
0#
b11111 %
#33
b10 !
b10 '
b10 0
b10001 +
1#
b100000 %
#34
0#
b100001 %
#35
b10010000 "
b10010000 )
b10010000 /
b10010 +
b100 !
b100 '
b100 0
1#
b100010 %
#36
0#
b100011 %
#37
b1111110 "
b1111110 )
b1111110 /
b1000 !
b1000 '
b1000 0
b10011 +
1#
b100100 %
#38
0#
b100101 %
#39
b10000 "
b10000 )
b10000 /
b10100 +
b10000 !
b10000 '
b10000 0
1#
b100110 %
#40
0#
b100111 %
#41
b110100 "
b110100 )
b110100 /
b100000 !
b100000 '
b100000 0
b10101 +
1#
b101000 %
#42
0#
b101001 %
#43
b1001000 "
b1001000 )
b1001000 /
b10110 +
b1000000 !
b1000000 '
b1000000 0
1#
b101010 %
#44
0#
b101011 %
#45
b10000000 "
b10000000 )
b10000000 /
b10000000 !
b10000000 '
b10000000 0
b10111 +
1#
b101100 %
#46
0#
b101101 %
#47
b111000 "
b111000 )
b111000 /
b11000 +
b1 !
b1 '
b1 0
1#
b101110 %
#48
0#
b101111 %
#49
b10 !
b10 '
b10 0
b11001 +
1#
b110000 %
#50
0#
b110001 %
#51
b10010000 "
b10010000 )
b10010000 /
b11010 +
b100 !
b100 '
b100 0
1#
b110010 %
#52
0#
b110011 %
#53
b1111110 "
b1111110 )
b1111110 /
b1000 !
b1000 '
b1000 0
b11011 +
1#
b110100 %
#54
0#
b110101 %
#55
b10000 "
b10000 )
b10000 /
b11100 +
b10000 !
b10000 '
b10000 0
1#
b110110 %
#56
0#
b110111 %
#57
b110100 "
b110100 )
b110100 /
b100000 !
b100000 '
b100000 0
b11101 +
1#
b111000 %
#58
0#
b111001 %
#59
b1001000 "
b1001000 )
b1001000 /
b11110 +
b1000000 !
b1000000 '
b1000000 0
1#
b111010 %
#60
0#
b111011 %
#61
b10000000 "
b10000000 )
b10000000 /
b10000000 !
b10000000 '
b10000000 0
b11111 +
1#
b111100 %
#62
0#
b111101 %
#63
b111000 "
b111000 )
b111000 /
b100000 +
b1 !
b1 '
b1 0
1#
b111110 %
#64
0#
b111111 %
#65
b10 !
b10 '
b10 0
b100001 +
1#
b1000000 %
#66
0#
b1000001 %
#67
b10010000 "
b10010000 )
b10010000 /
b100010 +
b100 !
b100 '
b100 0
1#
b1000010 %
#68
0#
b1000011 %
#69
b1111110 "
b1111110 )
b1111110 /
b1000 !
b1000 '
b1000 0
b100011 +
1#
b1000100 %
#70
0#
b1000101 %
#71
b10000 "
b10000 )
b10000 /
b100100 +
b10000 !
b10000 '
b10000 0
1#
b1000110 %
#72
0#
b1000111 %
#73
b110100 "
b110100 )
b110100 /
b100000 !
b100000 '
b100000 0
b100101 +
1#
b1001000 %
#74
0#
b1001001 %
#75
b1001000 "
b1001000 )
b1001000 /
b100110 +
b1000000 !
b1000000 '
b1000000 0
1#
b1001010 %
#76
0#
b1001011 %
#77
b10000000 "
b10000000 )
b10000000 /
b10000000 !
b10000000 '
b10000000 0
b100111 +
1#
b1001100 %
#78
0#
b1001101 %
#79
b111000 "
b111000 )
b111000 /
b101000 +
b1 !
b1 '
b1 0
1#
b1001110 %
#80
0#
b1001111 %
#81
b10 !
b10 '
b10 0
b101001 +
1#
b1010000 %
#82
0#
b1010001 %
#83
b10010000 "
b10010000 )
b10010000 /
b101010 +
b100 !
b100 '
b100 0
1#
b1010010 %
#84
0#
b1010011 %
#85
b1111110 "
b1111110 )
b1111110 /
b1000 !
b1000 '
b1000 0
b101011 +
1#
b1010100 %
#86
0#
b1010101 %
#87
b10000 "
b10000 )
b10000 /
b101100 +
b10000 !
b10000 '
b10000 0
1#
b1010110 %
#88
0#
b1010111 %
#89
b110100 "
b110100 )
b110100 /
b100000 !
b100000 '
b100000 0
b101101 +
1#
b1011000 %
#90
0#
b1011001 %
#91
b1001000 "
b1001000 )
b1001000 /
b101110 +
b1000000 !
b1000000 '
b1000000 0
1#
b1011010 %
#92
0#
b1011011 %
#93
b10000000 "
b10000000 )
b10000000 /
b10000000 !
b10000000 '
b10000000 0
b101111 +
1#
b1011100 %
#94
0#
b1011101 %
#95
b111000 "
b111000 )
b111000 /
b110000 +
b1 !
b1 '
b1 0
1#
b1011110 %
#96
0#
b1011111 %
#97
b10 !
b10 '
b10 0
b110001 +
1#
b1100000 %
#98
0#
b1100001 %
#99
b10010000 "
b10010000 )
b10010000 /
b110010 +
b100 !
b100 '
b100 0
1#
b1100010 %
#100
0#
b1100011 %
#101
b1111110 "
b1111110 )
b1111110 /
b1000 !
b1000 '
b1000 0
b110011 +
1#
b1100100 %
#102
0#
b1100101 %
#103
b10000 "
b10000 )
b10000 /
b110100 +
b10000 !
b10000 '
b10000 0
1#
b1100110 %
#104
0#
b1100111 %
#105
b110100 "
b110100 )
b110100 /
b100000 !
b100000 '
b100000 0
b110101 +
1#
b1101000 %
#106
0#
b1101001 %
#107
b1001000 "
b1001000 )
b1001000 /
b110110 +
b1000000 !
b1000000 '
b1000000 0
1#
b1101010 %
#108
0#
b1101011 %
#109
b10000000 "
b10000000 )
b10000000 /
b10000000 !
b10000000 '
b10000000 0
b110111 +
1#
b1101100 %
#110
0#
b1101101 %
#111
b111000 "
b111000 )
b111000 /
b111000 +
b1 !
b1 '
b1 0
1#
b1101110 %
#112
0#
b1101111 %
#113
b10 !
b10 '
b10 0
b111001 +
1#
b1110000 %
#114
0#
b1110001 %
#115
b10010000 "
b10010000 )
b10010000 /
b111010 +
b100 !
b100 '
b100 0
1#
b1110010 %
#116
0#
b1110011 %
#117
b1111110 "
b1111110 )
b1111110 /
b1000 !
b1000 '
b1000 0
b111011 +
1#
b1110100 %
#118
0#
b1110101 %
#119
b10000 "
b10000 )
b10000 /
b111100 +
b10000 !
b10000 '
b10000 0
1#
b1110110 %
#120
0#
b1110111 %
#121
b110100 "
b110100 )
b110100 /
b100000 !
b100000 '
b100000 0
b111101 +
1#
b1111000 %
#122
0#
b1111001 %
#123
b1001000 "
b1001000 )
b1001000 /
b111110 +
b1000000 !
b1000000 '
b1000000 0
1#
b1111010 %
#124
0#
b1111011 %
#125
b10000000 "
b10000000 )
b10000000 /
b10000000 !
b10000000 '
b10000000 0
b111111 +
1#
b1111100 %
#126
0#
b1111101 %
#127
b111000 "
b111000 )
b111000 /
b1000000 +
b1 !
b1 '
b1 0
1#
b1111110 %
#128
0#
b1111111 %
#129
b10 !
b10 '
b10 0
b1000001 +
1#
b10000000 %
#130
0#
b10000001 %
#131
b10010000 "
b10010000 )
b10010000 /
b1000010 +
b100 !
b100 '
b100 0
1#
b10000010 %
#132
0#
b10000011 %
#133
b1111110 "
b1111110 )
b1111110 /
b1000 !
b1000 '
b1000 0
b1000011 +
1#
b10000100 %
#134
0#
b10000101 %
#135
b10000 "
b10000 )
b10000 /
b1000100 +
b10000 !
b10000 '
b10000 0
1#
b10000110 %
#136
0#
b10000111 %
#137
b110100 "
b110100 )
b110100 /
b100000 !
b100000 '
b100000 0
b1000101 +
1#
b10001000 %
#138
0#
b10001001 %
#139
b1001000 "
b1001000 )
b1001000 /
b1000110 +
b1000000 !
b1000000 '
b1000000 0
1#
b10001010 %
#140
0#
b10001011 %
#141
b10000000 "
b10000000 )
b10000000 /
b10000000 !
b10000000 '
b10000000 0
b1000111 +
1#
b10001100 %
#142
0#
b10001101 %
#143
b111000 "
b111000 )
b111000 /
b1001000 +
b1 !
b1 '
b1 0
1#
b10001110 %
#144
0#
b10001111 %
#145
b10 !
b10 '
b10 0
b1001001 +
1#
b10010000 %
#146
0#
b10010001 %
#147
b10010000 "
b10010000 )
b10010000 /
b1001010 +
b100 !
b100 '
b100 0
1#
b10010010 %
#148
0#
b10010011 %
#149
b1111110 "
b1111110 )
b1111110 /
b1000 !
b1000 '
b1000 0
b1001011 +
1#
b10010100 %
#150
0#
b10010101 %
#151
b10000 "
b10000 )
b10000 /
b1001100 +
b10000 !
b10000 '
b10000 0
1#
b10010110 %
#152
0#
b10010111 %
#153
b110100 "
b110100 )
b110100 /
b100000 !
b100000 '
b100000 0
b1001101 +
1#
b10011000 %
#154
0#
b10011001 %
#155
b1001000 "
b1001000 )
b1001000 /
b1001110 +
b1000000 !
b1000000 '
b1000000 0
1#
b10011010 %
#156
0#
b10011011 %
#157
b10000000 "
b10000000 )
b10000000 /
b10000000 !
b10000000 '
b10000000 0
b1001111 +
1#
b10011100 %
#158
0#
b10011101 %
#159
b111000 "
b111000 )
b111000 /
b1010000 +
b1 !
b1 '
b1 0
1#
b10011110 %
#160
0#
b10011111 %
#161
b10 !
b10 '
b10 0
b1010001 +
1#
b10100000 %
#162
0#
b10100001 %
#163
b10010000 "
b10010000 )
b10010000 /
b1010010 +
b100 !
b100 '
b100 0
1#
b10100010 %
#164
0#
b10100011 %
#165
b1111110 "
b1111110 )
b1111110 /
b1000 !
b1000 '
b1000 0
b1010011 +
1#
b10100100 %
#166
0#
b10100101 %
#167
b10000 "
b10000 )
b10000 /
b1010100 +
b10000 !
b10000 '
b10000 0
1#
b10100110 %
#168
0#
b10100111 %
#169
b110100 "
b110100 )
b110100 /
b100000 !
b100000 '
b100000 0
b1010101 +
1#
b10101000 %
#170
0#
b10101001 %
#171
b1001000 "
b1001000 )
b1001000 /
b1010110 +
b1000000 !
b1000000 '
b1000000 0
1#
b10101010 %
#172
0#
b10101011 %
#173
b10000000 "
b10000000 )
b10000000 /
b10000000 !
b10000000 '
b10000000 0
b1010111 +
1#
b10101100 %
#174
0#
b10101101 %
#175
b111000 "
b111000 )
b111000 /
b1011000 +
b1 !
b1 '
b1 0
1#
b10101110 %
#176
0#
b10101111 %
#177
b10 !
b10 '
b10 0
b1011001 +
1#
b10110000 %
#178
0#
b10110001 %
#179
b10010000 "
b10010000 )
b10010000 /
b1011010 +
b100 !
b100 '
b100 0
1#
b10110010 %
#180
0#
b10110011 %
#181
b1111110 "
b1111110 )
b1111110 /
b1000 !
b1000 '
b1000 0
b1011011 +
1#
b10110100 %
#182
0#
b10110101 %
#183
b10000 "
b10000 )
b10000 /
b1011100 +
b10000 !
b10000 '
b10000 0
1#
b10110110 %
#184
0#
b10110111 %
#185
b110100 "
b110100 )
b110100 /
b100000 !
b100000 '
b100000 0
b1011101 +
1#
b10111000 %
#186
0#
b10111001 %
#187
b1001000 "
b1001000 )
b1001000 /
b1011110 +
b1000000 !
b1000000 '
b1000000 0
1#
b10111010 %
#188
0#
b10111011 %
#189
b10000000 "
b10000000 )
b10000000 /
b10000000 !
b10000000 '
b10000000 0
b1011111 +
1#
b10111100 %
#190
0#
b10111101 %
#191
b111000 "
b111000 )
b111000 /
b1100000 +
b1 !
b1 '
b1 0
1#
b10111110 %
#192
0#
b10111111 %
#193
b10 !
b10 '
b10 0
b1100001 +
1#
b11000000 %
#194
0#
b11000001 %
#195
b10010000 "
b10010000 )
b10010000 /
b1100010 +
b100 !
b100 '
b100 0
1#
b11000010 %
#196
0#
b11000011 %
#197
b1111110 "
b1111110 )
b1111110 /
b1000 !
b1000 '
b1000 0
b1100011 +
1#
b11000100 %
#198
0#
b11000101 %
#199
b10000 "
b10000 )
b10000 /
b1100100 +
b10000 !
b10000 '
b10000 0
1#
b11000110 %
#200
0#
b11000111 %
#201
b110100 "
b110100 )
b110100 /
b100000 !
b100000 '
b100000 0
b1100101 +
1#
b11001000 %
#202
0#
b11001001 %
#203
b1001000 "
b1001000 )
b1001000 /
b1100110 +
b1000000 !
b1000000 '
b1000000 0
1#
b11001010 %
#204
0#
b11001011 %
#205
b10000000 "
b10000000 )
b10000000 /
b10000000 !
b10000000 '
b10000000 0
b1100111 +
1#
b11001100 %
#206
0#
b11001101 %
#207
b111000 "
b111000 )
b111000 /
b1101000 +
b1 !
b1 '
b1 0
1#
b11001110 %
#208
0#
b11001111 %
#209
b10 !
b10 '
b10 0
b1101001 +
1#
b11010000 %
#210
0#
b11010001 %
#211
b10010000 "
b10010000 )
b10010000 /
b1101010 +
b100 !
b100 '
b100 0
1#
b11010010 %
#212
0#
b11010011 %
#213
b1111110 "
b1111110 )
b1111110 /
b1000 !
b1000 '
b1000 0
b1101011 +
1#
b11010100 %
#214
0#
b11010101 %
#215
b10000 "
b10000 )
b10000 /
b1101100 +
b10000 !
b10000 '
b10000 0
1#
b11010110 %
#216
0#
b11010111 %
#217
b110100 "
b110100 )
b110100 /
b100000 !
b100000 '
b100000 0
b1101101 +
1#
b11011000 %
#218
0#
b11011001 %
#219
b1001000 "
b1001000 )
b1001000 /
b1101110 +
b1000000 !
b1000000 '
b1000000 0
1#
b11011010 %
#220
0#
b11011011 %
#221
b10000000 "
b10000000 )
b10000000 /
b10000000 !
b10000000 '
b10000000 0
b1101111 +
1#
b11011100 %
#222
0#
b11011101 %
#223
b111000 "
b111000 )
b111000 /
b1110000 +
b1 !
b1 '
b1 0
1#
b11011110 %
#224
0#
b11011111 %
#225
b10 !
b10 '
b10 0
b1110001 +
1#
b11100000 %
#226
0#
b11100001 %
#227
b10010000 "
b10010000 )
b10010000 /
b1110010 +
b100 !
b100 '
b100 0
1#
b11100010 %
#228
0#
b11100011 %
#229
b1111110 "
b1111110 )
b1111110 /
b1000 !
b1000 '
b1000 0
b1110011 +
1#
b11100100 %
#230
0#
b11100101 %
#231
b10000 "
b10000 )
b10000 /
b1110100 +
b10000 !
b10000 '
b10000 0
1#
b11100110 %
#232
0#
b11100111 %
#233
b110100 "
b110100 )
b110100 /
b100000 !
b100000 '
b100000 0
b1110101 +
1#
b11101000 %
#234
0#
b11101001 %
#235
b1001000 "
b1001000 )
b1001000 /
b1110110 +
b1000000 !
b1000000 '
b1000000 0
1#
b11101010 %
#236
0#
b11101011 %
#237
b10000000 "
b10000000 )
b10000000 /
b10000000 !
b10000000 '
b10000000 0
b1110111 +
1#
b11101100 %
#238
0#
b11101101 %
#239
b111000 "
b111000 )
b111000 /
b1111000 +
b1 !
b1 '
b1 0
1#
b11101110 %
#240
0#
b11101111 %
#241
b10 !
b10 '
b10 0
b1111001 +
1#
b11110000 %
#242
0#
b11110001 %
#243
b10010000 "
b10010000 )
b10010000 /
b1111010 +
b100 !
b100 '
b100 0
1#
b11110010 %
#244
0#
b11110011 %
#245
b1111110 "
b1111110 )
b1111110 /
b1000 !
b1000 '
b1000 0
b1111011 +
1#
b11110100 %
#246
0#
b11110101 %
#247
b10000 "
b10000 )
b10000 /
b1111100 +
b10000 !
b10000 '
b10000 0
1#
b11110110 %
#248
0#
b11110111 %
#249
b110100 "
b110100 )
b110100 /
b100000 !
b100000 '
b100000 0
b1111101 +
1#
b11111000 %
#250
0#
b11111001 %
#251
b1001000 "
b1001000 )
b1001000 /
b1111110 +
b1000000 !
b1000000 '
b1000000 0
1#
b11111010 %
#252
0#
b11111011 %
#253
b10000000 "
b10000000 )
b10000000 /
b10000000 !
b10000000 '
b10000000 0
b1111111 +
1#
b11111100 %
#254
0#
b11111101 %
#255
b111000 "
b111000 )
b111000 /
b10000000 +
b1 !
b1 '
b1 0
1#
b11111110 %
#256
0#
b11111111 %
#257
b10 !
b10 '
b10 0
b10000001 +
1#
b100000000 %
#258
0#
b100000001 %
#259
b10010000 "
b10010000 )
b10010000 /
b10000010 +
b100 !
b100 '
b100 0
1#
b100000010 %
#260
0#
b100000011 %
#261
b1111110 "
b1111110 )
b1111110 /
b1000 !
b1000 '
b1000 0
b10000011 +
1#
b100000100 %
#262
0#
b100000101 %
#263
b10000 "
b10000 )
b10000 /
b10000100 +
b10000 !
b10000 '
b10000 0
1#
b100000110 %
#264
0#
b100000111 %
#265
b110100 "
b110100 )
b110100 /
b100000 !
b100000 '
b100000 0
b10000101 +
1#
b100001000 %
#266
0#
b100001001 %
#267
b1001000 "
b1001000 )
b1001000 /
b10000110 +
b1000000 !
b1000000 '
b1000000 0
1#
b100001010 %
#268
0#
b100001011 %
#269
b10000000 "
b10000000 )
b10000000 /
b10000000 !
b10000000 '
b10000000 0
b10000111 +
1#
b100001100 %
#270
0#
b100001101 %
#271
b111000 "
b111000 )
b111000 /
b10001000 +
b1 !
b1 '
b1 0
1#
b100001110 %
#272
0#
b100001111 %
#273
b10 !
b10 '
b10 0
b10001001 +
1#
b100010000 %
#274
0#
b100010001 %
#275
b10010000 "
b10010000 )
b10010000 /
b10001010 +
b100 !
b100 '
b100 0
1#
b100010010 %
#276
0#
b100010011 %
#277
b1111110 "
b1111110 )
b1111110 /
b1000 !
b1000 '
b1000 0
b10001011 +
1#
b100010100 %
#278
0#
b100010101 %
#279
b10000 "
b10000 )
b10000 /
b10001100 +
b10000 !
b10000 '
b10000 0
1#
b100010110 %
#280
0#
b100010111 %
#281
b110100 "
b110100 )
b110100 /
b100000 !
b100000 '
b100000 0
b10001101 +
1#
b100011000 %
#282
0#
b100011001 %
#283
b1001000 "
b1001000 )
b1001000 /
b10001110 +
b1000000 !
b1000000 '
b1000000 0
1#
b100011010 %
#284
0#
b100011011 %
#285
b10000000 "
b10000000 )
b10000000 /
b10000000 !
b10000000 '
b10000000 0
b10001111 +
1#
b100011100 %
#286
0#
b100011101 %
#287
b111000 "
b111000 )
b111000 /
b10010000 +
b1 !
b1 '
b1 0
1#
b100011110 %
#288
0#
b100011111 %
#289
b10 !
b10 '
b10 0
b10010001 +
1#
b100100000 %
#290
0#
b100100001 %
#291
b10010000 "
b10010000 )
b10010000 /
b10010010 +
b100 !
b100 '
b100 0
1#
b100100010 %
#292
0#
b100100011 %
#293
b1111110 "
b1111110 )
b1111110 /
b1000 !
b1000 '
b1000 0
b10010011 +
1#
b100100100 %
#294
0#
b100100101 %
#295
b10000 "
b10000 )
b10000 /
b10010100 +
b10000 !
b10000 '
b10000 0
1#
b100100110 %
#296
0#
b100100111 %
#297
b110100 "
b110100 )
b110100 /
b100000 !
b100000 '
b100000 0
b10010101 +
1#
b100101000 %
#298
0#
b100101001 %
#299
b1001000 "
b1001000 )
b1001000 /
b10010110 +
b1000000 !
b1000000 '
b1000000 0
1#
b100101010 %
#300
0#
b100101011 %
#301
b10000000 "
b10000000 )
b10000000 /
b10000000 !
b10000000 '
b10000000 0
b10010111 +
1#
b100101100 %
#302
0#
b100101101 %
#303
b111000 "
b111000 )
b111000 /
b10011000 +
b1 !
b1 '
b1 0
1#
b100101110 %
#304
0#
b100101111 %
#305
b10 !
b10 '
b10 0
b10011001 +
1#
b100110000 %
#306
0#
b100110001 %
#307
b10010000 "
b10010000 )
b10010000 /
b10011010 +
b100 !
b100 '
b100 0
1#
b100110010 %
#308
0#
b100110011 %
#309
b1111110 "
b1111110 )
b1111110 /
b1000 !
b1000 '
b1000 0
b10011011 +
1#
b100110100 %
#310
0#
b100110101 %
#311
b10000 "
b10000 )
b10000 /
b10011100 +
b10000 !
b10000 '
b10000 0
1#
b100110110 %
#312
0#
b100110111 %
#313
b110100 "
b110100 )
b110100 /
b100000 !
b100000 '
b100000 0
b10011101 +
1#
b100111000 %
#314
0#
b100111001 %
#315
b1001000 "
b1001000 )
b1001000 /
b10011110 +
b1000000 !
b1000000 '
b1000000 0
1#
b100111010 %
#316
0#
b100111011 %
#317
b10000000 "
b10000000 )
b10000000 /
b10000000 !
b10000000 '
b10000000 0
b10011111 +
1#
b100111100 %
#318
0#
b100111101 %
#319
b111000 "
b111000 )
b111000 /
b10100000 +
b1 !
b1 '
b1 0
1#
b100111110 %
#320
0#
b100111111 %
#321
b10 !
b10 '
b10 0
b10100001 +
1#
b101000000 %
#322
0#
b101000001 %
#323
b10010000 "
b10010000 )
b10010000 /
b10100010 +
b100 !
b100 '
b100 0
1#
b101000010 %
#324
0#
b101000011 %
#325
b1111110 "
b1111110 )
b1111110 /
b1000 !
b1000 '
b1000 0
b10100011 +
1#
b101000100 %
#326
0#
b101000101 %
#327
b10000 "
b10000 )
b10000 /
b10100100 +
b10000 !
b10000 '
b10000 0
1#
b101000110 %
#328
0#
b101000111 %
#329
b110100 "
b110100 )
b110100 /
b100000 !
b100000 '
b100000 0
b10100101 +
1#
b101001000 %
#330
0#
b101001001 %
#331
b1001000 "
b1001000 )
b1001000 /
b10100110 +
b1000000 !
b1000000 '
b1000000 0
1#
b101001010 %
#332
0#
b101001011 %
#333
b10000000 "
b10000000 )
b10000000 /
b10000000 !
b10000000 '
b10000000 0
b10100111 +
1#
b101001100 %
#334
0#
b101001101 %
#335
b111000 "
b111000 )
b111000 /
b10101000 +
b1 !
b1 '
b1 0
1#
b101001110 %
#336
0#
b101001111 %
#337
b10 !
b10 '
b10 0
b10101001 +
1#
b101010000 %
#338
0#
b101010001 %
#339
b10010000 "
b10010000 )
b10010000 /
b10101010 +
b100 !
b100 '
b100 0
1#
b101010010 %
#340
0#
b101010011 %
#341
b1111110 "
b1111110 )
b1111110 /
b1000 !
b1000 '
b1000 0
b10101011 +
1#
b101010100 %
#342
0#
b101010101 %
#343
b10000 "
b10000 )
b10000 /
b10101100 +
b10000 !
b10000 '
b10000 0
1#
b101010110 %
#344
0#
b101010111 %
#345
b110100 "
b110100 )
b110100 /
b100000 !
b100000 '
b100000 0
b10101101 +
1#
b101011000 %
#346
0#
b101011001 %
#347
b1001000 "
b1001000 )
b1001000 /
b10101110 +
b1000000 !
b1000000 '
b1000000 0
1#
b101011010 %
#348
0#
b101011011 %
#349
b10000000 "
b10000000 )
b10000000 /
b10000000 !
b10000000 '
b10000000 0
b10101111 +
1#
b101011100 %
#350
0#
b101011101 %
#351
b111000 "
b111000 )
b111000 /
b10110000 +
b1 !
b1 '
b1 0
1#
b101011110 %
#352
0#
b101011111 %
#353
b10 !
b10 '
b10 0
b10110001 +
1#
b101100000 %
#354
0#
b101100001 %
#355
b10010000 "
b10010000 )
b10010000 /
b10110010 +
b100 !
b100 '
b100 0
1#
b101100010 %
#356
0#
b101100011 %
#357
b1111110 "
b1111110 )
b1111110 /
b1000 !
b1000 '
b1000 0
b10110011 +
1#
b101100100 %
#358
0#
b101100101 %
#359
b10000 "
b10000 )
b10000 /
b10110100 +
b10000 !
b10000 '
b10000 0
1#
b101100110 %
#360
0#
b101100111 %
#361
b110100 "
b110100 )
b110100 /
b100000 !
b100000 '
b100000 0
b10110101 +
1#
b101101000 %
#362
0#
b101101001 %
#363
b1001000 "
b1001000 )
b1001000 /
b10110110 +
b1000000 !
b1000000 '
b1000000 0
1#
b101101010 %
#364
0#
b101101011 %
#365
b10000000 "
b10000000 )
b10000000 /
b10000000 !
b10000000 '
b10000000 0
b10110111 +
1#
b101101100 %
#366
0#
b101101101 %
#367
b111000 "
b111000 )
b111000 /
b10111000 +
b1 !
b1 '
b1 0
1#
b101101110 %
#368
0#
b101101111 %
#369
b10 !
b10 '
b10 0
b10111001 +
1#
b101110000 %
#370
0#
b101110001 %
#371
b10010000 "
b10010000 )
b10010000 /
b10111010 +
b100 !
b100 '
b100 0
1#
b101110010 %
#372
0#
b101110011 %
#373
b1111110 "
b1111110 )
b1111110 /
b1000 !
b1000 '
b1000 0
b10111011 +
1#
b101110100 %
#374
0#
b101110101 %
#375
b10000 "
b10000 )
b10000 /
b10111100 +
b10000 !
b10000 '
b10000 0
1#
b101110110 %
#376
0#
b101110111 %
#377
b110100 "
b110100 )
b110100 /
b100000 !
b100000 '
b100000 0
b10111101 +
1#
b101111000 %
#378
0#
b101111001 %
#379
b1001000 "
b1001000 )
b1001000 /
b10111110 +
b1000000 !
b1000000 '
b1000000 0
1#
b101111010 %
