Report9/Ex3/LEDMatrix.v
module LEDMatrix(clk, rst, sel, row, col);
	input clk, rst;
	input [1:0]sel;
	
	output reg[7:0]row, col;
	
	always@(posedge clk or posedge rst)begin
		if(rst) row<=8'b00000001;
		else if(row==8'b10000000) row<=8'b00000001;
		else row<=row<<1'b1;
	end
	
	always@(*)begin
		case(sel)
			2'b00:begin
				case(row)
					8'b00000001:col=8'b00111000;
					8'b00000010:col=8'b00111000;
					8'b00000100:col=8'b10010000;
					8'b00001000:col=8'b01111110;
					8'b00010000:col=8'b00010000;
					8'b00100000:col=8'b00110100;
					8'b01000000:col=8'b01001000;
					8'b10000000:col=8'b10000000;
				endcase
			end
			2'b01:begin
				case(row)
					8'b00000001:col=8'b00111000;
					8'b00000010:col=8'b00111000;
					8'b00000100:col=8'b01010000;
					8'b00001000:col=8'b00111100;
					8'b00010000:col=8'b00010010;
					8'b00100000:col=8'b00110000;
					8'b01000000:col=8'b01001100;
					8'b10000000:col=8'b01000000;
				endcase
			end
			2'b10:begin
				case(row)
					8'b00000001:col=8'b00111000;
					8'b00000010:col=8'b00111000;
					8'b00000100:col=8'b00010000;
					8'b00001000:col=8'b01011000;
					8'b00010000:col=8'b00110100;
					8'b00100000:col=8'b00010000;
					8'b01000000:col=8'b00101000;
					8'b10000000:col=8'b00100100;
				endcase
			end
			2'b11:begin
				case(row)
					8'b00000001:col=8'b00111000;
					8'b00000010:col=8'b00111000;
					8'b00000100:col=8'b01010000;
					8'b00001000:col=8'b00111100;
					8'b00010000:col=8'b00010010;
					8'b00100000:col=8'b00110000;
					8'b01000000:col=8'b01001100;
					8'b10000000:col=8'b01000000;
				endcase
			end
		endcase
	end
	
endmodule

Report9/Ex3/counter.v
module counter(clk, rst, out);
	input clk, rst;
	
	output reg [1:0]out;
	
	reg [7:0]cnt;
	
	always@(posedge clk or posedge rst)begin
		if(rst)begin
			out<=2'b00;
			cnt<=8'd0;
		end
		else if(cnt==8'b10000000)begin
			cnt<=8'd0;
			out<=out+1'b1;
		end
		else cnt<=cnt+1'b1;
	end
endmodule

Report9/Ex3/system.v
module system(clk, rst, row, col);
	input clk, rst;
	
	output[7:0]row, col;
	
	wire dclk;
	wire[1:0]sel;
	
	//freqDevider FD(.clk(clk), .dclk(dclk));
	counter CNT(.clk(clk), .rst(rst), .out(sel));
	LEDMatrix LM(.clk(clk), .rst(rst), .row(row), .col(col), .sel(sel));
	
endmodule

Report9/Ex3/test.v
module test;
	reg clk, rst;	
	
	wire[7:0]row, col;
	wire[1:0]sel;
	
	integer cnt=0;
	
	system S(.clk(clk), .rst(rst), .row(row), .col(col));
	
	initial begin
		rst=1'b1;#1 rst=1'b0;
		clk=1'd0;
		for(cnt=0; cnt<32'd150; cnt=cnt+1)begin
			clk=~clk;
			#1;
		end
	end
	
	initial begin
		$monitor("row:%b, col:%b", row, col);
	end
	
	initial begin
		$dumpfile("test.vcd");
		$dumpvars;
	end	
endmodule

Report9/Ex3/freqDevider.v
module freqDevider(clk, rst, dclk);
	input clk, rst;
	
	output reg dclk;
	
	reg[24:0]count;
	
	always@(posedge clk, posedge rst)begin
		if(rst)begin
			dclk<=1'b0;
			count<=25'd0;
		end
		
		else if(count==25'd24000)begin
			dclk<=~dclk;
			count<=25'd0;
		end
		
		else count<=count+25'd1;
		
	end

endmodule

Report9/Ex3/test.vcd
$date
	Wed May 23 12:17:44 2018
$end
$version
	Icarus Verilog
$end
$timescale
	1s
$end
$scope module freqDevider $end
$var wire 1 ! clk $end
$var wire 1 " rst $end
$var reg 25 # count [24:0] $end
$var reg 1 $ dclk $end
$upscope $end
$scope module test $end
$var wire 8 % row [7:0] $end
$var wire 8 & col [7:0] $end
$var reg 1 ' clk $end
$var reg 1 ( rst $end
$var integer 32 ) cnt [31:0] $end
$scope module S $end
$var wire 1 ' clk $end
$var wire 1 ( rst $end
$var wire 2 * sel [1:0] $end
$var wire 8 + row [7:0] $end
$var wire 8 , col [7:0] $end
$scope module CNT $end
$var wire 1 ' clk $end
$var wire 1 ( rst $end
$var reg 8 - cnt [7:0] $end
$var reg 2 . out [1:0] $end
$upscope $end
$scope module LM $end
$var wire 1 ' clk $end
$var wire 1 ( rst $end
$var wire 2 / sel [1:0] $end
$var reg 8 0 col [7:0] $end
$var reg 8 1 row [7:0] $end
$upscope $end
$upscope $end
$upscope $end
$enddefinitions $end
#0
$dumpvars
b1 1
b111000 0
b0 /
b0 .
b0 -
b111000 ,
b1 +
b0 *
b0 )
1(
x'
b111000 &
b1 %
x$
bx #
z"
z!
$end
#1
b1 -
b10 %
b10 +
b10 1
1'
0(
#2
0'
b1 )
#3
b10 -
b10010000 &
b10010000 ,
b10010000 0
b100 %
b100 +
b100 1
1'
b10 )
#4
0'
b11 )
#5
b11 -
b1111110 &
b1111110 ,
b1111110 0
b1000 %
b1000 +
b1000 1
1'
b100 )
#6
0'
b101 )
#7
b100 -
b10000 &
b10000 ,
b10000 0
b10000 %
b10000 +
b10000 1
1'
b110 )
#8
0'
b111 )
#9
b101 -
b110100 &
b110100 ,
b110100 0
b100000 %
b100000 +
b100000 1
1'
b1000 )
#10
0'
b1001 )
#11
b110 -
b1001000 &
b1001000 ,
b1001000 0
b1000000 %
b1000000 +
b1000000 1
1'
b1010 )
#12
0'
b1011 )
#13
b111 -
b10000000 &
b10000000 ,
b10000000 0
b10000000 %
b10000000 +
b10000000 1
1'
b1100 )
#14
0'
b1101 )
#15
b111000 &
b111000 ,
b111000 0
b1000 -
b1 %
b1 +
b1 1
1'
b1110 )
#16
0'
b1111 )
#17
b1001 -
b10 %
b10 +
b10 1
1'
b10000 )
#18
0'
b10001 )
#19
b1010 -
b10010000 &
b10010000 ,
b10010000 0
b100 %
b100 +
b100 1
1'
b10010 )
#20
0'
b10011 )
#21
b1011 -
b1111110 &
b1111110 ,
b1111110 0
b1000 %
b1000 +
b1000 1
1'
b10100 )
#22
0'
b10101 )
#23
b1100 -
b10000 &
b10000 ,
b10000 0
b10000 %
b10000 +
b10000 1
1'
b10110 )
#24
0'
b10111 )
#25
b1101 -
b110100 &
b110100 ,
b110100 0
b100000 %
b100000 +
b100000 1
1'
b11000 )
#26
0'
b11001 )
#27
b1110 -
b1001000 &
b1001000 ,
b1001000 0
b1000000 %
b1000000 +
b1000000 1
1'
b11010 )
#28
0'
b11011 )
#29
b1111 -
b10000000 &
b10000000 ,
b10000000 0
b10000000 %
b10000000 +
b10000000 1
1'
b11100 )
#30
0'
b11101 )
#31
b111000 &
b111000 ,
b111000 0
b10000 -
b1 %
b1 +
b1 1
1'
b11110 )
#32
0'
b11111 )
#33
b10001 -
b10 %
b10 +
b10 1
1'
b100000 )
#34
0'
b100001 )
#35
b10010 -
b10010000 &
b10010000 ,
b10010000 0
b100 %
b100 +
b100 1
1'
b100010 )
#36
0'
b100011 )
#37
b10011 -
b1111110 &
b1111110 ,
b1111110 0
b1000 %
b1000 +
b1000 1
1'
b100100 )
#38
0'
b100101 )
#39
b10100 -
b10000 &
b10000 ,
b10000 0
b10000 %
b10000 +
b10000 1
1'
b100110 )
#40
0'
b100111 )
#41
b10101 -
b110100 &
b110100 ,
b110100 0
b100000 %
b100000 +
b100000 1
1'
b101000 )
#42
0'
b101001 )
#43
b10110 -
b1001000 &
b1001000 ,
b1001000 0
b1000000 %
b1000000 +
b1000000 1
1'
b101010 )
#44
0'
b101011 )
#45
b10111 -
b10000000 &
b10000000 ,
b10000000 0
b10000000 %
b10000000 +
b10000000 1
1'
b101100 )
#46
0'
b101101 )
#47
b111000 &
b111000 ,
b111000 0
b11000 -
b1 %
b1 +
b1 1
1'
b101110 )
#48
0'
b101111 )
#49
b11001 -
b10 %
b10 +
b10 1
1'
b110000 )
#50
0'
b110001 )
#51
b11010 -
b10010000 &
b10010000 ,
b10010000 0
b100 %
b100 +
b100 1
1'
b110010 )
#52
0'
b110011 )
#53
b11011 -
b1111110 &
b1111110 ,
b1111110 0
b1000 %
b1000 +
b1000 1
1'
b110100 )
#54
0'
b110101 )
#55
b11100 -
b10000 &
b10000 ,
b10000 0
b10000 %
b10000 +
b10000 1
1'
b110110 )
#56
0'
b110111 )
#57
b11101 -
b110100 &
b110100 ,
b110100 0
b100000 %
b100000 +
b100000 1
1'
b111000 )
#58
0'
b111001 )
#59
b11110 -
b1001000 &
b1001000 ,
b1001000 0
b1000000 %
b1000000 +
b1000000 1
1'
b111010 )
#60
0'
b111011 )
#61
b11111 -
b10000000 &
b10000000 ,
b10000000 0
b10000000 %
b10000000 +
b10000000 1
1'
b111100 )
#62
0'
b111101 )
#63
b111000 &
b111000 ,
b111000 0
b100000 -
b1 %
b1 +
b1 1
1'
b111110 )
#64
0'
b111111 )
#65
b100001 -
b10 %
b10 +
b10 1
1'
b1000000 )
#66
0'
b1000001 )
#67
b100010 -
b10010000 &
b10010000 ,
b10010000 0
b100 %
b100 +
b100 1
1'
b1000010 )
#68
0'
b1000011 )
#69
b100011 -
b1111110 &
b1111110 ,
b1111110 0
b1000 %
b1000 +
b1000 1
1'
b1000100 )
#70
0'
b1000101 )
#71
b100100 -
b10000 &
b10000 ,
b10000 0
b10000 %
b10000 +
b10000 1
1'
b1000110 )
#72
0'
b1000111 )
#73
b100101 -
b110100 &
b110100 ,
b110100 0
b100000 %
b100000 +
b100000 1
1'
b1001000 )
#74
0'
b1001001 )
#75
b100110 -
b1001000 &
b1001000 ,
b1001000 0
b1000000 %
b1000000 +
b1000000 1
1'
b1001010 )
#76
0'
b1001011 )
#77
b100111 -
b10000000 &
b10000000 ,
b10000000 0
b10000000 %
b10000000 +
b10000000 1
1'
b1001100 )
#78
0'
b1001101 )
#79
b111000 &
b111000 ,
b111000 0
b101000 -
b1 %
b1 +
b1 1
1'
b1001110 )
#80
0'
b1001111 )
#81
b101001 -
b10 %
b10 +
b10 1
1'
b1010000 )
#82
0'
b1010001 )
#83
b101010 -
b10010000 &
b10010000 ,
b10010000 0
b100 %
b100 +
b100 1
1'
b1010010 )
#84
0'
b1010011 )
#85
b101011 -
b1111110 &
b1111110 ,
b1111110 0
b1000 %
b1000 +
b1000 1
1'
b1010100 )
#86
0'
b1010101 )
#87
b101100 -
b10000 &
b10000 ,
b10000 0
b10000 %
b10000 +
b10000 1
1'
b1010110 )
#88
0'
b1010111 )
#89
b101101 -
b110100 &
b110100 ,
b110100 0
b100000 %
b100000 +
b100000 1
1'
b1011000 )
#90
0'
b1011001 )
#91
b101110 -
b1001000 &
b1001000 ,
b1001000 0
b1000000 %
b1000000 +
b1000000 1
1'
b1011010 )
#92
0'
b1011011 )
#93
b101111 -
b10000000 &
b10000000 ,
b10000000 0
b10000000 %
b10000000 +
b10000000 1
1'
b1011100 )
#94
0'
b1011101 )
#95
b111000 &
b111000 ,
b111000 0
b110000 -
b1 %
b1 +
b1 1
1'
b1011110 )
#96
0'
b1011111 )
#97
b110001 -
b10 %
b10 +
b10 1
1'
b1100000 )
#98
0'
b1100001 )
#99
b110010 -
b10010000 &
b10010000 ,
b10010000 0
b100 %
b100 +
b100 1
1'
b1100010 )
#100
0'
b1100011 )
#101
b110011 -
b1111110 &
b1111110 ,
b1111110 0
b1000 %
b1000 +
b1000 1
1'
b1100100 )
#102
0'
b1100101 )
#103
b110100 -
b10000 &
b10000 ,
b10000 0
b10000 %
b10000 +
b10000 1
1'
b1100110 )
#104
0'
b1100111 )
#105
b110101 -
b110100 &
b110100 ,
b110100 0
b100000 %
b100000 +
b100000 1
1'
b1101000 )
#106
0'
b1101001 )
#107
b110110 -
b1001000 &
b1001000 ,
b1001000 0
b1000000 %
b1000000 +
b1000000 1
1'
b1101010 )
#108
0'
b1101011 )
#109
b110111 -
b10000000 &
b10000000 ,
b10000000 0
b10000000 %
b10000000 +
b10000000 1
1'
b1101100 )
#110
0'
b1101101 )
#111
b111000 &
b111000 ,
b111000 0
b111000 -
b1 %
b1 +
b1 1
1'
b1101110 )
#112
0'
b1101111 )
#113
b111001 -
b10 %
b10 +
b10 1
1'
b1110000 )
#114
0'
b1110001 )
#115
b111010 -
b10010000 &
b10010000 ,
b10010000 0
b100 %
b100 +
b100 1
1'
b1110010 )
#116
0'
b1110011 )
#117
b111011 -
b1111110 &
b1111110 ,
b1111110 0
b1000 %
b1000 +
b1000 1
1'
b1110100 )
#118
0'
b1110101 )
#119
b111100 -
b10000 &
b10000 ,
b10000 0
b10000 %
b10000 +
b10000 1
1'
b1110110 )
#120
0'
b1110111 )
#121
b111101 -
b110100 &
b110100 ,
b110100 0
b100000 %
b100000 +
b100000 1
1'
b1111000 )
#122
0'
b1111001 )
#123
b111110 -
b1001000 &
b1001000 ,
b1001000 0
b1000000 %
b1000000 +
b1000000 1
1'
b1111010 )
#124
0'
b1111011 )
#125
b111111 -
b10000000 &
b10000000 ,
b10000000 0
b10000000 %
b10000000 +
b10000000 1
1'
b1111100 )
#126
0'
b1111101 )
#127
b111000 &
b111000 ,
b111000 0
b1000000 -
b1 %
b1 +
b1 1
1'
b1111110 )
#128
0'
b1111111 )
#129
b1000001 -
b10 %
b10 +
b10 1
1'
b10000000 )
#130
0'
b10000001 )
#131
b1000010 -
b10010000 &
b10010000 ,
b10010000 0
b100 %
b100 +
b100 1
1'
b10000010 )
#132
0'
b10000011 )
#133
b1000011 -
b1111110 &
b1111110 ,
b1111110 0
b1000 %
b1000 +
b1000 1
1'
b10000100 )
#134
0'
b10000101 )
#135
b1000100 -
b10000 &
b10000 ,
b10000 0
b10000 %
b10000 +
b10000 1
1'
b10000110 )
#136
0'
b10000111 )
#137
b1000101 -
b110100 &
b110100 ,
b110100 0
b100000 %
b100000 +
b100000 1
1'
b10001000 )
#138
0'
b10001001 )
#139
b1000110 -
b1001000 &
b1001000 ,
b1001000 0
b1000000 %
b1000000 +
b1000000 1
1'
b10001010 )
#140
0'
b10001011 )
#141
b1000111 -
b10000000 &
b10000000 ,
b10000000 0
b10000000 %
b10000000 +
b10000000 1
1'
b10001100 )
#142
0'
b10001101 )
#143
b111000 &
b111000 ,
b111000 0
b1001000 -
b1 %
b1 +
b1 1
1'
b10001110 )
#144
0'
b10001111 )
#145
b1001001 -
b10 %
b10 +
b10 1
1'
b10010000 )
#146
0'
b10010001 )
#147
b1001010 -
b10010000 &
b10010000 ,
b10010000 0
b100 %
b100 +
b100 1
1'
b10010010 )
#148
0'
b10010011 )
#149
b1001011 -
b1111110 &
b1111110 ,
b1111110 0
b1000 %
b1000 +
b1000 1
1'
b10010100 )
#150
0'
b10010101 )
#151
b10010110 )
