Report4/Ex3/semiAdder.v
module semiAdder(in0, in1, sum, carry);
	input in0, in1;
	output sum, carry;
	
	xor XOR0(sum, in0, in1);
	and AND0(carry, in0, in1);

endmodule

Report4/Ex2/fullAdder.v
module fullAdder(in0, in1, in2, sum, carry);
	
	input in0, in1, in2;
	output sum, carry;
	
	wire carry0, carry1, sum0;
	
	semiAdder SA0(in0, in1, sum0, carry0);
	semiAdder SA1(in2, sum0, sum, carry1);
	or OR0(carry, carry0, carry1);
	
endmodule

Report4/Ex3/fourBitFA.v
module fourBitFA(INa, INb, CarryIn, Sum, CarryOut);
	
	input [3:0]INa;
	input [3:0]INb;
	input CarryIn;
	output [3:0]Sum;
	output CarryOut;
	
	wire FA_out[0:2];
	
	fullAdder FA0(CarryIn, INa[0], INb[0], Sum[0], FA_out[0]);
	fullAdder FA1(FA_out[0], INa[1], INb[1], Sum[1], FA_out[1]);
	fullAdder FA2(FA_out[1], INa[2], INb[2], Sum[2], FA_out[2]);
	fullAdder FA3(FA_out[2], INa[3], INb[3], Sum[3], CarryOut);
	
endmodule

Report4/Ex3/testFourBitFA.v
module testFourBitFA;

	reg [0:3] INa;
	reg [0:3] INb;
	reg CarryIn;

	wire [0:3] Sum;
	wire CarryOut;

	fourBitFA fourBitFA0 (.INa(INa),.INb(INb),.CarryIn(CarryIn),.Sum(Sum),.CarryOut(CarryOut));

	initial begin
		for(INa=0; INa<15; INa=INa+1)begin
			for(INb=0; INb<15; INb=INb+1)begin
				CarryIn=0;
				#1 CarryIn=1;
				#1;
			end
			CarryIn=0;
			#1 CarryIn=1;
			#1;
		end
		for(INb=0; INb<15; INb=INb+1)begin
				CarryIn=0;
				#1 CarryIn=1;
				#1;
		end
		CarryIn=0;
		#1 CarryIn=1;
		#1;
	end
	
	initial begin
		$monitor(" CarryIn=%b, INa=%b, INb=%b, Sum=%b, CarryOut=%b", CarryIn, INa, INb, Sum, CarryOut);
	end
	
	initial begin
		$dumpfile("testFourBitFA.vcd");
		$dumpvars;
	end
      
endmodule

Report4/Ex3/testFourBitFA.vcd
$date
	Sat Apr 14 23:08:40 2018
$end
$version
	Icarus Verilog
$end
$timescale
	1s
$end
$scope module testFourBitFA $end
$var wire 4 ! Sum [0:3] $end
$var wire 1 " CarryOut $end
$var reg 1 # CarryIn $end
$var reg 4 $ INa [0:3] $end
$var reg 4 % INb [0:3] $end
$scope module fourBitFA0 $end
$var wire 1 # CarryIn $end
$var wire 4 & INa [3:0] $end
$var wire 4 ' INb [3:0] $end
$var wire 4 ( Sum [3:0] $end
$var wire 1 " CarryOut $end
$scope module FA0 $end
$var wire 1 ) carry $end
$var wire 1 # in0 $end
$var wire 1 * in1 $end
$var wire 1 + in2 $end
$var wire 1 , sum0 $end
$var wire 1 - sum $end
$var wire 1 . carry1 $end
$var wire 1 / carry0 $end
$scope module SA0 $end
$var wire 1 / carry $end
$var wire 1 # in0 $end
$var wire 1 * in1 $end
$var wire 1 , sum $end
$upscope $end
$scope module SA1 $end
$var wire 1 . carry $end
$var wire 1 + in0 $end
$var wire 1 , in1 $end
$var wire 1 - sum $end
$upscope $end
$upscope $end
$scope module FA1 $end
$var wire 1 0 carry $end
$var wire 1 ) in0 $end
$var wire 1 1 in1 $end
$var wire 1 2 in2 $end
$var wire 1 3 sum0 $end
$var wire 1 4 sum $end
$var wire 1 5 carry1 $end
$var wire 1 6 carry0 $end
$scope module SA0 $end
$var wire 1 6 carry $end
$var wire 1 ) in0 $end
$var wire 1 1 in1 $end
$var wire 1 3 sum $end
$upscope $end
$scope module SA1 $end
$var wire 1 5 carry $end
$var wire 1 2 in0 $end
$var wire 1 3 in1 $end
$var wire 1 4 sum $end
$upscope $end
$upscope $end
$scope module FA2 $end
$var wire 1 7 carry $end
$var wire 1 0 in0 $end
$var wire 1 8 in1 $end
$var wire 1 9 in2 $end
$var wire 1 : sum0 $end
$var wire 1 ; sum $end
$var wire 1 < carry1 $end
$var wire 1 = carry0 $end
$scope module SA0 $end
$var wire 1 = carry $end
$var wire 1 0 in0 $end
$var wire 1 8 in1 $end
$var wire 1 : sum $end
$upscope $end
$scope module SA1 $end
$var wire 1 < carry $end
$var wire 1 9 in0 $end
$var wire 1 : in1 $end
$var wire 1 ; sum $end
$upscope $end
$upscope $end
$scope module FA3 $end
$var wire 1 " carry $end
$var wire 1 7 in0 $end
$var wire 1 > in1 $end
$var wire 1 ? in2 $end
$var wire 1 @ sum0 $end
$var wire 1 A sum $end
$var wire 1 B carry1 $end
$var wire 1 C carry0 $end
$scope module SA0 $end
$var wire 1 C carry $end
$var wire 1 7 in0 $end
$var wire 1 > in1 $end
$var wire 1 @ sum $end
$upscope $end
$scope module SA1 $end
$var wire 1 B carry $end
$var wire 1 ? in0 $end
$var wire 1 @ in1 $end
$var wire 1 A sum $end
$upscope $end
$upscope $end
$upscope $end
$upscope $end
$enddefinitions $end
#0
$dumpvars
0C
0B
0A
0@
0?
0>
0=
0<
0;
0:
09
08
07
06
05
04
03
02
01
00
0/
0.
0-
0,
0+
0*
0)
b0 (
b0 '
b0 &
b0 %
b0 $
0#
0"
b0 !
$end
#1
b1 !
b1 (
1-
1,
1#
#2
0,
1+
0#
b1 %
b1 '
#3
14
13
1)
b10 !
b10 (
0-
1.
1,
1#
#4
0;
03
0:
0)
00
0.
b10 !
b10 (
14
05
0,
0+
12
0#
b10 %
b10 '
#5
b11 !
b11 (
1-
1,
1#
#6
0,
1+
0#
b11 %
b11 '
#7
1;
1:
10
04
15
13
1)
b100 !
b100 (
0-
1.
1,
1#
#8
0A
03
0:
0@
0)
00
07
0.
04
05
b100 !
b100 (
1;
0<
0,
0+
02
19
0#
b100 %
b100 '
#9
b101 !
b101 (
1-
1,
1#
#10
0,
1+
0#
b101 %
b101 '
#11
14
13
1)
b110 !
b110 (
0-
1.
1,
1#
#12
0A
0@
07
1;
0<
03
0:
0)
00
0.
b110 !
b110 (
14
05
0,
0+
12
0#
b110 %
b110 '
#13
b111 !
b111 (
1-
1,
1#
#14
0,
1+
0#
b111 %
b111 '
#15
1A
1@
17
0;
1<
1:
10
04
15
13
1)
b1000 !
b1000 (
0-
1.
1,
1#
#16
03
0:
0@
0)
00
07
0"
0.
04
05
0;
0<
b1000 !
b1000 (
1A
0B
0,
0+
02
09
1?
0#
b1000 %
b1000 '
#17
b1001 !
b1001 (
1-
1,
1#
#18
0,
1+
0#
b1001 %
b1001 '
#19
14
13
1)
b1010 !
b1010 (
0-
1.
1,
1#
#20
0;
03
0:
0)
00
0.
b1010 !
b1010 (
14
05
0,
0+
12
0#
b1010 %
b1010 '
#21
b1011 !
b1011 (
1-
1,
1#
#22
0,
1+
0#
b1011 %
b1011 '
#23
1;
1:
10
04
15
13
1)
b1100 !
b1100 (
0-
1.
1,
1#
#24
0"
1A
0B
03
0:
0@
0)
00
07
0.
04
05
b1100 !
b1100 (
1;
0<
0,
0+
02
19
0#
b1100 %
b1100 '
#25
b1101 !
b1101 (
1-
1,
1#
#26
0,
1+
0#
b1101 %
b1101 '
#27
14
13
1)
b1110 !
b1110 (
0-
1.
1,
1#
#28
0"
1A
0B
0@
07
1;
0<
03
0:
0)
00
0.
b1110 !
b1110 (
14
05
0,
0+
12
0#
b1110 %
b1110 '
#29
b1111 !
b1111 (
1-
1,
1#
#30
0,
1+
0#
b1111 %
b1111 '
#31
1"
0A
1B
1@
17
0;
1<
1:
10
04
15
13
1)
b0 !
b0 (
0-
1.
1,
1#
#32
03
0:
0@
0)
00
07
0"
1-
0.
04
05
0;
0<
b1 !
b1 (
0A
0B
0+
02
09
0?
1*
0#
b0 %
b0 '
b1 $
b1 &
#33
14
13
b10 !
b10 (
0-
1)
0,
1/
1#
#34
1.
1,
0/
1+
0#
b1 %
b1 '
#35
b11 !
b11 (
1-
0.
0,
1/
1#
#36
0;
0:
03
00
0)
b11 !
b11 (
14
05
1,
0/
0+
12
0#
b10 %
b10 '
#37
1;
1:
10
04
15
13
b100 !
b100 (
0-
1)
0,
1/
1#
#38
1.
1,
0/
1+
0#
b11 %
b11 '
#39
b101 !
b101 (
1-
0.
0,
1/
1#
#40
0A
0:
0@
03
00
07
0)
04
05
b101 !
b101 (
1;
0<
1,
0/
0+
02
19
0#
b100 %
b100 '
#41
14
13
b110 !
b110 (
0-
1)
0,
1/
1#
#42
1.
1,
0/
1+
0#
b101 %
b101 '
#43
b111 !
b111 (
1-
0.
0,
1/
1#
#44
0A
0@
07
1;
0<
0:
03
00
0)
b111 !
b111 (
14
05
1,
0/
0+
12
0#
b110 %
b110 '
#45
1A
1@
17
0;
1<
1:
10
04
15
13
b1000 !
b1000 (
0-
1)
0,
1/
1#
#46
1.
1,
0/
1+
0#
b111 %
b111 '
#47
b1001 !
b1001 (
1-
0.
0,
1/
1#
#48
0:
0@
03
00
07
0"
0)
04
05
0;
0<
b1001 !
b1001 (
1A
0B
1,
0/
0+
02
09
1?
0#
b1000 %
b1000 '
#49
14
13
b1010 !
b1010 (
0-
1)
0,
1/
1#
#50
1.
1,
0/
1+
0#
b1001 %
b1001 '
#51
b1011 !
b1011 (
1-
0.
0,
1/
1#
#52
0;
0:
03
00
0)
b1011 !
b1011 (
14
05
1,
0/
0+
12
0#
b1010 %
b1010 '
#53
1;
1:
10
04
15
13
b1100 !
b1100 (
0-
1)
0,
1/
1#
#54
1.
1,
0/
1+
0#
b1011 %
b1011 '
#55
b1101 !
b1101 (
1-
0.
0,
1/
1#
#56
0"
1A
0B
0:
0@
03
00
07
0)
04
05
b1101 !
b1101 (
1;
0<
1,
0/
0+
02
19
0#
b1100 %
b1100 '
#57
14
13
b1110 !
b1110 (
0-
1)
0,
1/
1#
#58
1.
1,
0/
1+
0#
b1101 %
b1101 '
#59
b1111 !
b1111 (
1-
0.
0,
1/
1#
#60
0"
1A
0B
0@
07
1;
0<
0:
03
00
0)
b1111 !
b1111 (
14
05
1,
0/
0+
12
0#
b1110 %
b1110 '
#61
1"
0A
1B
1@
17
0;
1<
1:
10
04
15
13
b0 !
b0 (
0-
1)
0,
1/
1#
#62
1.
1,
0/
1+
0#
b1111 %
b1111 '
#63
b1 !
b1 (
1-
0.
0,
1/
1#
#64
0:
14
00
0@
07
0"
0)
0-
05
0;
0<
b10 !
b10 (
0A
0B
13
06
0/
0+
02
09
0?
0*
11
0#
b0 %
b0 '
b10 $
b10 &
#65
b11 !
b11 (
1-
1,
1#
#66
0,
1+
0#
b1 %
b1 '
#67
1;
1:
04
10
03
16
1)
b100 !
b100 (
0-
1.
1,
1#
#68
1;
1:
15
10
13
06
0)
0.
b100 !
b100 (
04
0,
0+
12
0#
b10 %
b10 '
#69
b101 !
b101 (
1-
1,
1#
#70
0,
1+
0#
b11 %
b11 '
#71
14
05
03
16
1)
b110 !
b110 (
0-
1.
1,
1#
#72
0:
00
0A
13
06
0@
0)
07
0.
14
b110 !
b110 (
1;
0<
0,
0+
02
19
0#
b100 %
b100 '
#73
b111 !
b111 (
1-
1,
1#
#74
0,
1+
0#
b101 %
b101 '
#75
1A
1@
17
0;
1<
1:
04
10
03
16
1)
b1000 !
b1000 (
0-
1.
1,
1#
#76
1A
1@
17
0;
1<
1:
15
10
13
06
0)
0.
b1000 !
b1000 (
04
0,
0+
12
0#
b110 %
b110 '
#77
b1001 !
b1001 (
1-
1,
1#
#78
0,
1+
0#
b111 %
b111 '
#79
14
05
03
16
1)
b1010 !
b1010 (
0-
1.
1,
1#
#80
0:
00
13
06
0@
0)
07
0"
0.
14
0;
0<
b1010 !
b1010 (
1A
0B
0,
0+
02
09
1?
0#
b1000 %
b1000 '
#81
b1011 !
b1011 (
1-
1,
1#
#82
0,
1+
0#
b1001 %
b1001 '
#83
1;
1:
04
10
03
16
1)
b1100 !
b1100 (
0-
1.
1,
1#
#84
1;
1:
15
10
13
06
0)
0.
b1100 !
b1100 (
04
0,
0+
12
0#
b1010 %
b1010 '
#85
b1101 !
b1101 (
1-
1,
1#
#86
0,
1+
0#
b1011 %
b1011 '
#87
14
05
03
16
1)
b1110 !
b1110 (
0-
1.
1,
1#
#88
0:
0"
00
1A
0B
13
06
0@
0)
07
0.
14
b1110 !
b1110 (
1;
0<
0,
0+
02
19
0#
b1100 %
b1100 '
#89
b1111 !
b1111 (
1-
1,
1#
#90
0,
1+
0#
b1101 %
b1101 '
#91
1"
0A
1B
1@
17
0;
1<
1:
04
10
03
16
1)
b0 !
b0 (
0-
1.
1,
1#
#92
1"
0A
1B
1@
17
0;
1<
1:
15
10
13
06
0)
0.
b0 !
b0 (
04
0,
0+
12
0#
b1110 %
b1110 '
#93
b1 !
b1 (
1-
1,
1#
#94
0,
1+
0#
b1111 %
b1111 '
#95
14
05
03
16
1)
b10 !
b10 (
0-
1.
1,
1#
#96
0:
00
13
06
0@
0)
07
0"
1-
0.
14
0;
0<
b11 !
b11 (
0A
0B
0+
02
09
0?
1*
0#
b0 %
b0 '
b11 $
b11 &
#97
1;
1:
04
10
03
16
b100 !
b100 (
0-
1)
0,
1/
1#
#98
1.
1,
0/
1+
0#
b1 %
b1 '
#99
b101 !
b101 (
1-
0.
0,
1/
1#
#100
1;
1:
15
10
13
06
0)
b101 !
b101 (
04
1,
0/
0+
12
0#
b10 %
b10 '
#101
14
05
03
16
b110 !
b110 (
0-
1)
0,
1/
1#
#102
1.
1,
0/
1+
0#
b11 %
b11 '
#103
b111 !
b111 (
1-
0.
0,
1/
1#
#104
0:
0A
00
0@
13
06
07
0)
14
b111 !
b111 (
1;
0<
1,
0/
0+
02
19
0#
b100 %
b100 '
#105
1A
1@
17
0;
1<
1:
04
10
03
16
b1000 !
b1000 (
0-
1)
0,
1/
1#
#106
1.
1,
0/
1+
0#
b101 %
b101 '
#107
b1001 !
b1001 (
1-
0.
0,
1/
1#
#108
1A
1@
17
0;
1<
1:
15
10
13
06
0)
b1001 !
b1001 (
04
1,
0/
0+
12
0#
b110 %
b110 '
#109
14
05
03
16
b1010 !
b1010 (
0-
1)
0,
1/
1#
#110
1.
1,
0/
1+
0#
b111 %
b111 '
#111
b1011 !
b1011 (
1-
0.
0,
1/
1#
#112
0:
00
0@
13
06
07
0"
0)
14
0;
0<
b1011 !
b1011 (
1A
0B
1,
0/
0+
02
09
1?
0#
b1000 %
b1000 '
#113
1;
1:
04
10
03
16
b1100 !
b1100 (
0-
1)
0,
1/
1#
#114
1.
1,
0/
1+
0#
b1001 %
b1001 '
#115
b1101 !
b1101 (
1-
0.
0,
1/
1#
#116
1;
1:
15
10
13
06
0)
b1101 !
b1101 (
04
1,
0/
0+
12
0#
b1010 %
b1010 '
#117
14
05
03
16
b1110 !
b1110 (
0-
1)
0,
1/
1#
#118
1.
1,
0/
1+
0#
b1011 %
b1011 '
#119
b1111 !
b1111 (
1-
0.
0,
1/
1#
#120
0"
0:
1A
0B
00
0@
13
06
07
0)
14
b1111 !
b1111 (
1;
0<
1,
0/
0+
02
19
0#
b1100 %
b1100 '
#121
1"
0A
1B
1@
17
0;
1<
1:
04
10
03
16
b0 !
b0 (
0-
1)
0,
1/
1#
#122
1.
1,
0/
1+
0#
b1101 %
b1101 '
#123
b1 !
b1 (
1-
0.
0,
1/
1#
#124
1"
0A
1B
1@
17
0;
1<
1:
15
10
13
06
0)
b1 !
b1 (
04
1,
0/
0+
12
0#
b1110 %
b1110 '
#125
14
05
03
16
b10 !
b10 (
0-
1)
0,
1/
1#
#126
1.
1,
0/
1+
0#
b1111 %
b1111 '
#127
b11 !
b11 (
1-
0.
0,
1/
1#
#128
0@
1;
07
04
0"
00
0)
0-
0<
b100 !
b100 (
0A
0B
03
06
1:
0=
0/
0+
02
09
0?
0*
01
18
0#
b0 %
b0 '
b100 $
b100 &
#129
b101 !
b101 (
1-
1,
1#
#130
0,
1+
0#
b1 %
b1 '
#131
14
13
1)
b110 !
b110 (
0-
1.
1,
1#
#132
0A
0@
1;
07
03
1:
0=
0)
00
0.
b110 !
b110 (
14
05
0,
0+
12
0#
b10 %
b10 '
#133
b111 !
b111 (
1-
1,
1#
#134
0,
1+
0#
b11 %
b11 '
#135
1A
1@
0;
17
0:
1=
10
04
15
13
1)
b1000 !
b1000 (
0-
1.
1,
1#
#136
1A
1@
1<
17
03
1:
0=
0)
00
0.
04
05
b1000 !
b1000 (
0;
0,
0+
02
19
0#
b100 %
b100 '
#137
b1001 !
b1001 (
1-
1,
1#
#138
0,
1+
0#
b101 %
b101 '
#139
14
13
1)
b1010 !
b1010 (
0-
1.
1,
1#
#140
1A
1@
17
0;
1<
03
1:
0=
0)
00
0.
b1010 !
b1010 (
14
05
0,
0+
12
0#
b110 %
b110 '
#141
b1011 !
b1011 (
1-
1,
1#
#142
0,
1+
0#
b111 %
b111 '
#143
1;
0<
0:
1=
10
04
15
13
1)
b1100 !
b1100 (
0-
1.
1,
1#
#144
0@
07
03
1:
0=
0)
00
0"
0.
04
05
1;
b1100 !
b1100 (
1A
0B
0,
0+
02
09
1?
0#
b1000 %
b1000 '
#145
b1101 !
b1101 (
1-
1,
1#
#146
0,
1+
0#
b1001 %
b1001 '
#147
14
13
1)
b1110 !
b1110 (
0-
1.
1,
1#
#148
0"
1A
0B
0@
1;
07
03
1:
0=
0)
00
0.
b1110 !
b1110 (
14
05
0,
0+
12
0#
b1010 %
b1010 '
#149
b1111 !
b1111 (
1-
1,
1#
#150
0,
1+
0#
b1011 %
b1011 '
#151
1"
0A
1B
1@
0;
17
0:
1=
10
04
15
13
1)
b0 !
b0 (
0-
1.
1,
1#
#152
1"
0A
1B
1@
1<
17
03
1:
0=
0)
00
0.
04
05
b0 !
b0 (
0;
0,
0+
02
19
0#
b1100 %
b1100 '
#153
b1 !
b1 (
1-
1,
1#
#154
0,
1+
0#
b1101 %
b1101 '
#155
14
13
1)
b10 !
b10 (
0-
1.
1,
1#
#156
1"
0A
1B
1@
17
0;
1<
03
1:
0=
0)
00
0.
b10 !
b10 (
14
05
0,
0+
12
0#
b1110 %
b1110 '
#157
b11 !
b11 (
1-
1,
1#
#158
0,
1+
0#
b1111 %
b1111 '
#159
1;
0<
0:
1=
10
04
15
13
1)
b100 !
b100 (
0-
1.
1,
1#
#160
0@
07
03
1:
0=
0)
00
0"
1-
0.
04
05
1;
b101 !
b101 (
0A
0B
0+
02
09
0?
1*
0#
b0 %
b0 '
b101 $
b101 &
#161
14
13
b110 !
b110 (
0-
1)
0,
1/
1#
#162
1.
1,
0/
1+
0#
b1 %
b1 '
#163
b111 !
b111 (
1-
0.
0,
1/
1#
#164
0A
0@
1;
07
1:
0=
03
00
0)
b111 !
b111 (
14
05
1,
0/
0+
12
0#
b10 %
b10 '
#165
1A
1@
0;
17
0:
1=
10
04
15
13
b1000 !
b1000 (
0-
1)
0,
1/
1#
#166
1.
1,
0/
1+
0#
b11 %
b11 '
#167
b1001 !
b1001 (
1-
0.
0,
1/
1#
#168
1A
1@
1<
17
1:
0=
03
00
0)
04
05
b1001 !
b1001 (
0;
1,
0/
0+
02
19
0#
b100 %
b100 '
#169
14
13
b1010 !
b1010 (
0-
1)
0,
1/
1#
#170
1.
1,
0/
1+
0#
b101 %
b101 '
#171
b1011 !
b1011 (
1-
0.
0,
1/
1#
#172
1A
1@
17
0;
1<
1:
0=
03
00
0)
b1011 !
b1011 (
14
05
1,
0/
0+
12
0#
b110 %
b110 '
#173
1;
0<
0:
1=
10
04
15
13
b1100 !
b1100 (
0-
1)
0,
1/
1#
#174
1.
1,
0/
1+
0#
b111 %
b111 '
#175
b1101 !
b1101 (
1-
0.
0,
1/
1#
#176
0@
07
1:
0=
03
00
0"
0)
04
05
1;
b1101 !
b1101 (
1A
0B
1,
0/
0+
02
09
1?
0#
b1000 %
b1000 '
#177
14
13
b1110 !
b1110 (
0-
1)
0,
1/
1#
#178
1.
1,
0/
1+
0#
b1001 %
b1001 '
#179
b1111 !
b1111 (
1-
0.
0,
1/
1#
#180
0"
1A
0B
0@
1;
07
1:
0=
03
00
0)
b1111 !
b1111 (
14
05
1,
0/
0+
12
0#
b1010 %
b1010 '
#181
1"
0A
1B
1@
0;
17
0:
1=
10
04
15
13
b0 !
b0 (
0-
1)
0,
1/
1#
#182
1.
1,
0/
1+
0#
b1011 %
b1011 '
#183
b1 !
b1 (
1-
0.
0,
1/
1#
#184
1"
0A
1B
1@
1<
17
1:
0=
03
00
0)
04
05
b1 !
b1 (
0;
1,
0/
0+
02
19
0#
b1100 %
b1100 '
#185
14
13
b10 !
b10 (
0-
1)
0,
1/
1#
#186
1.
1,
0/
1+
0#
b1101 %
b1101 '
#187
b11 !
b11 (
1-
0.
0,
1/
1#
#188
1"
0A
1B
1@
17
0;
1<
1:
0=
03
00
0)
b11 !
b11 (
14
05
1,
0/
0+
12
0#
b1110 %
b1110 '
#189
1;
0<
0:
1=
10
04
15
13
b100 !
b100 (
0-
1)
0,
1/
1#
#190
1.
1,
0/
1+
0#
b1111 %
b1111 '
#191
b101 !
b101 (
1-
0.
0,
1/
1#
#192
0@
07
1:
0=
14
00
0"
0)
0-
05
1;
b110 !
b110 (
0A
0B
13
06
0/
0+
02
09
0?
0*
11
0#
b0 %
b0 '
b110 $
b110 &
#193
b111 !
b111 (
1-
1,
1#
#194
0,
1+
0#
b1 %
b1 '
#195
1A
1@
0;
17
0:
1=
04
10
03
16
1)
b1000 !
b1000 (
0-
1.
1,
1#
#196
1A
1@
0;
17
0:
1=
15
10
13
06
0)
0.
b1000 !
b1000 (
04
0,
0+
12
0#
b10 %
b10 '
#197
b1001 !
b1001 (
1-
1,
1#
#198
0,
1+
0#
b11 %
b11 '
#199
14
05
03
16
1)
b1010 !
b1010 (
0-
1.
1,
1#
#200
1A
1@
1<
17
1:
0=
00
13
06
0)
0.
14
b1010 !
b1010 (
0;
0,
0+
02
19
0#
b100 %
b100 '
#201
b1011 !
b1011 (
1-
1,
1#
#202
0,
1+
0#
b101 %
b101 '
#203
1;
0<
0:
1=
04
10
03
16
1)
b1100 !
b1100 (
0-
1.
1,
1#
#204
1A
1@
1;
0<
17
0:
1=
15
10
13
06
0)
0.
b1100 !
b1100 (
04
0,
0+
12
0#
b110 %
b110 '
#205
b1101 !
b1101 (
1-
1,
1#
#206
0,
1+
0#
b111 %
b111 '
#207
14
05
03
16
1)
b1110 !
b1110 (
0-
1.
1,
1#
#208
0@
07
1:
0=
00
13
06
0)
0"
0.
14
1;
b1110 !
b1110 (
1A
0B
0,
0+
02
09
1?
0#
b1000 %
b1000 '
#209
b1111 !
b1111 (
1-
1,
1#
#210
0,
1+
0#
b1001 %
b1001 '
#211
1"
0A
1B
1@
0;
17
0:
1=
04
10
03
16
1)
b0 !
b0 (
0-
1.
1,
1#
#212
1"
0A
1B
1@
0;
17
0:
1=
15
10
13
06
0)
0.
b0 !
b0 (
04
0,
0+
12
0#
b1010 %
b1010 '
#213
b1 !
b1 (
1-
1,
1#
#214
0,
1+
0#
b1011 %
b1011 '
#215
14
05
03
16
1)
b10 !
b10 (
0-
1.
1,
1#
#216
1"
0A
1B
1@
1<
17
1:
0=
00
13
06
0)
0.
14
b10 !
b10 (
0;
0,
0+
02
19
0#
b1100 %
b1100 '
#217
b11 !
b11 (
1-
1,
1#
#218
0,
1+
0#
b1101 %
b1101 '
#219
1;
0<
0:
1=
04
10
03
16
1)
b100 !
b100 (
0-
1.
1,
1#
#220
1"
0A
1B
1@
1;
0<
17
0:
1=
15
10
13
06
0)
0.
b100 !
b100 (
04
0,
0+
12
0#
b1110 %
b1110 '
#221
b101 !
b101 (
1-
1,
1#
#222
0,
1+
0#
b1111 %
b1111 '
#223
14
05
03
16
1)
b110 !
b110 (
0-
1.
1,
1#
#224
0@
07
1:
0=
00
13
06
0)
0"
1-
0.
14
1;
b111 !
b111 (
0A
0B
0+
02
09
0?
1*
0#
b0 %
b0 '
b111 $
b111 &
#225
1A
1@
0;
17
0:
1=
04
10
03
16
b1000 !
b1000 (
0-
1)
0,
1/
1#
#226
1.
1,
0/
1+
0#
b1 %
b1 '
#227
b1001 !
b1001 (
1-
0.
0,
1/
1#
#228
1A
1@
0;
17
0:
1=
15
10
13
06
0)
b1001 !
b1001 (
04
1,
0/
0+
12
0#
b10 %
b10 '
#229
14
05
03
16
b1010 !
b1010 (
0-
1)
0,
1/
1#
#230
1.
1,
0/
1+
0#
b11 %
b11 '
#231
b1011 !
b1011 (
1-
0.
0,
1/
1#
#232
1A
1@
1<
17
1:
0=
00
13
06
0)
14
b1011 !
b1011 (
0;
1,
0/
0+
02
19
0#
b100 %
b100 '
#233
1;
0<
0:
1=
04
10
03
16
b1100 !
b1100 (
0-
1)
0,
1/
1#
#234
1.
1,
0/
1+
0#
b101 %
b101 '
#235
b1101 !
b1101 (
1-
0.
0,
1/
1#
#236
1A
1@
1;
0<
17
0:
1=
15
10
13
06
0)
b1101 !
b1101 (
04
1,
0/
0+
12
0#
b110 %
b110 '
#237
14
05
03
16
b1110 !
b1110 (
0-
1)
0,
1/
1#
#238
1.
1,
0/
1+
0#
b111 %
b111 '
#239
b1111 !
b1111 (
1-
0.
0,
1/
1#
#240
0@
07
1:
0=
00
13
06
0"
0)
14
1;
b1111 !
b1111 (
1A
0B
1,
0/
0+
02
09
1?
0#
b1000 %
b1000 '
#241
1"
0A
1B
1@
0;
17
0:
1=
04
10
03
16
b0 !
b0 (
0-
1)
0,
1/
1#
#242
1.
1,
0/
1+
0#
b1001 %
b1001 '
#243
b1 !
b1 (
1-
0.
0,
1/
1#
#244
1"
0A
1B
1@
0;
17
0:
1=
15
10
13
06
0)
b1 !
b1 (
04
1,
0/
0+
12
0#
b1010 %
b1010 '
#245
14
05
03
16
b10 !
b10 (
0-
1)
0,
1/
1#
#246
1.
1,
0/
1+
0#
b1011 %
b1011 '
#247
b11 !
b11 (
1-
0.
0,
1/
1#
#248
1"
0A
1B
1@
1<
17
1:
0=
00
13
06
0)
14
b11 !
b11 (
0;
1,
0/
0+
02
19
0#
b1100 %
b1100 '
#249
1;
0<
0:
1=
04
10
03
16
b100 !
b100 (
0-
1)
0,
1/
1#
#250
1.
1,
0/
1+
0#
b1101 %
b1101 '
#251
b101 !
b101 (
1-
0.
0,
1/
1#
#252
1"
0A
1B
1@
1;
0<
17
0:
1=
15
10
13
06
0)
b101 !
b101 (
04
1,
0/
0+
12
0#
b1110 %
b1110 '
#253
14
05
03
16
b110 !
b110 (
0-
1)
0,
1/
1#
#254
1.
1,
0/
1+
0#
b1111 %
b1111 '
#255
b111 !
b111 (
1-
0.
0,
1/
1#
#256
0;
1A
0"
04
00
07
0)
b1000 !
b1000 (
0-
0B
03
06
0:
0=
1@
0C
0/
0+
02
09
0?
0*
01
08
1>
0#
b0 %
b0 '
b1000 $
b1000 &
#257
b1001 !
b1001 (
1-
1,
1#
#258
0,
1+
0#
b1 %
b1 '
#259
14
13
1)
b1010 !
b1010 (
0-
1.
1,
1#
#260
0;
03
0:
0)
00
0.
b1010 !
b1010 (
14
05
0,
0+
12
0#
b10 %
b10 '
#261
b1011 !
b1011 (
1-
1,
1#
#262
0,
1+
0#
b11 %
b11 '
#263
1;
1:
10
04
15
13
1)
b1100 !
b1100 (
0-
1.
1,
1#
#264
1A
0"
03
0:
1@
0C
0)
00
07
0.
04
05
b1100 !
b1100 (
1;
0<
0,
0+
02
19
0#
b100 %
b100 '
#265
b1101 !
b1101 (
1-
1,
1#
#266
0,
1+
0#
b101 %
b101 '
#267
14
13
1)
b1110 !
b1110 (
0-
1.
1,
1#
#268
1A
0"
1@
0C
07
1;
0<
03
0:
0)
00
0.
b1110 !
b1110 (
14
05
0,
0+
12
0#
b110 %
b110 '
#269
b1111 !
b1111 (
1-
1,
1#
#270
0,
1+
0#
b111 %
b111 '
#271
0A
1"
0@
1C
17
0;
1<
1:
10
04
15
13
1)
b0 !
b0 (
0-
1.
1,
1#
#272
1B
1"
03
0:
1@
0C
0)
00
07
0.
04
05
0;
0<
b0 !
b0 (
0A
0,
0+
02
09
1?
0#
b1000 %
b1000 '
#273
b1 !
b1 (
1-
1,
1#
#274
0,
1+
0#
b1001 %
b1001 '
#275
14
13
1)
b10 !
b10 (
0-
1.
1,
1#
#276
0;
03
0:
0)
00
0.
b10 !
b10 (
14
05
0,
0+
12
0#
b1010 %
b1010 '
#277
b11 !
b11 (
1-
1,
1#
#278
0,
1+
0#
b1011 %
b1011 '
#279
1;
1:
10
04
15
13
1)
b100 !
b100 (
0-
1.
1,
1#
#280
1"
0A
1B
03
0:
1@
0C
0)
00
07
0.
04
05
b100 !
b100 (
1;
0<
0,
0+
02
19
0#
b1100 %
b1100 '
#281
b101 !
b101 (
1-
1,
1#
#282
0,
1+
0#
b1101 %
b1101 '
#283
14
13
1)
b110 !
b110 (
0-
1.
1,
1#
#284
1"
0A
1B
1@
0C
07
1;
0<
03
0:
0)
00
0.
b110 !
b110 (
14
05
0,
0+
12
0#
b1110 %
b1110 '
#285
b111 !
b111 (
1-
1,
1#
#286
0,
1+
0#
b1111 %
b1111 '
#287
1A
0B
0@
1C
17
0;
1<
1:
10
04
15
13
1)
b1000 !
b1000 (
0-
1.
1,
1#
#288
0"
03
0:
1@
0C
0)
00
07
1-
0.
04
05
0;
0<
b1001 !
b1001 (
1A
0+
02
09
0?
1*
0#
b0 %
b0 '
b1001 $
b1001 &
#289
14
13
b1010 !
b1010 (
0-
1)
0,
1/
1#
#290
1.
1,
0/
1+
0#
b1 %
b1 '
#291
b1011 !
b1011 (
1-
0.
0,
1/
1#
#292
0;
0:
03
00
0)
b1011 !
b1011 (
14
05
1,
0/
0+
12
0#
b10 %
b10 '
#293
1;
1:
10
04
15
13
b1100 !
b1100 (
0-
1)
0,
1/
1#
#294
1.
1,
0/
1+
0#
b11 %
b11 '
#295
b1101 !
b1101 (
1-
0.
0,
1/
1#
