Report7/Ex2/7seg.v
module sevenSeg(in, out);
	input [3:0]in;
	
	output[6:0]out;
	reg[6:0]out;
	
	always@(*)begin
		case(in)
			4'b0000:out=7'b0111111;
			4'b0001:out=7'b0000110;
			4'b0010:out=7'b1011011;
			4'b0011:out=7'b1001111;
			4'b0100:out=7'b1100110;
			4'b0101:out=7'b1101101;
			4'b0110:out=7'b1111101;
			4'b0111:out=7'b0000111;
			4'b1000:out=7'b1111111;
			4'b1001:out=7'b1101111;
			4'b1010:out=7'b1110111;
			4'b1011:out=7'b1111100;
			4'b1100:out=7'b0111001;
			4'b1101:out=7'b1011110;
			4'b1110:out=7'b1110001;
			4'b1111:out=7'b0000000;
			default:out=7'b0000000;
		endcase		
	end
endmodule

Report8/Ex2/counter.v
module counter(clk, rst, stateNow, stateNext, count);
	input clk, rst;
	input [1:0]stateNow, stateNext;
	
	output reg [2:0]count;
	
	reg[2:0] countNext;
				
	//combinatorial component to determine the next state
	always@(*)begin
		if(stateNow==stateNext) countNext=count+1;
		else countNext=1;
	end
	
	//memory component to remember the current state
	always@(posedge clk or posedge rst)begin
		if(rst) count<=1;
		else	count<=countNext;
	end
	
endmodule

Report8/Ex2/trafficLight.v
module trafficLight(clk, rst, count, stateNow, stateNext, out);
	input clk, rst;
	input [2:0] count;
	
	output reg [1:0]stateNow, stateNext;
	output reg [2:0]out;
	
	parameter	greenOut =3'd1,
				yellowOut=3'd2,
				redOut   =3'd4,
				green    =2'd0,
				yellow   =2'd1,
				red      =2'd2;
	
	//combinatorial component to determine the next state
	always@(*)begin
		case(stateNow)
			green:	stateNext=(count==3'd4)?yellow:green;
			yellow:	stateNext=(count==3'd1)?red:yellow;
			red:	stateNext=(count==3'd5)?green:red;
		endcase
	end
	
	//memory component to remember the current state
	always@(posedge clk or posedge rst)begin
		if(rst) stateNow<=red;
		else	stateNow<=stateNext;
	end
	
	//combinatorial component to determine the output
	always@(*)begin
		case(stateNow)
			green:out=greenOut;
			yellow:out=yellowOut;
			red:out=redOut;
		endcase
	end
	
endmodule

Report9/Ex3/freqDevider.v
module freqDevider(clk, rst, dclk);
	input clk, rst;
	
	output reg dclk;
	
	reg[24:0]count;
	
	always@(posedge clk, posedge rst)begin
		if(rst)begin
			dclk<=1'b0;
			count<=25'd0;
		end
		
		else if(count==25'd24000)begin
			dclk<=~dclk;
			count<=25'd0;
		end
		
		else count<=count+25'd1;
		
	end

endmodule

Report8/Ex2/system.v
module system(clk, rst, outLED, outSS);
	input clk, rst;
	output [2:0]outLED;
	output [6:0]outSS;
	
	wire dclk;
	wire [1:0]stateNow, stateNext;
	wire [2:0]count;
	
	freqDevider FD(.clk(clk), .rst(rst), .dclk(dclk));
	trafficLight TL(.clk(clk), .rst(rst), .count(count), .stateNow(stateNow), .stateNext(stateNext), .out(outLED));
	counter CNT(.clk(clk), .rst(rst),.count(count), .stateNow(stateNow), .stateNext(stateNext));
	sevenSeg SS(.in({1'b0, count}), .out(outSS));
	
endmodule

Report8/Ex2/test.v
module test;
	reg clk=1'b0, rst;
	wire [2:0]outLED;
	wire [6:0]outSS;
	
	integer cnt=0;
	
	system S(.clk(clk), .rst(rst), .outLED(outLED), .outSS(outSS));
	
	initial begin
		rst=1'b1; #1 rst=1'b0;
		for(cnt=0; cnt<1000; cnt=cnt+1)begin
			#1 clk=~clk;
		end
	end
	
	initial $monitor("LED: %b, SS: %b", outLED, outSS);
	
	initial begin
		$dumpfile("test.vcd");
		$dumpvars;
	end

endmodule

Report8/Ex2/test.vcd
$date
	Tue May 08 21:50:29 2018
$end
$version
	Icarus Verilog
$end
$timescale
	1s
$end
$scope module test $end
$var wire 7 ! outSS [6:0] $end
$var wire 3 " outLED [2:0] $end
$var reg 1 # clk $end
$var reg 1 $ rst $end
$var integer 32 % cnt [31:0] $end
$scope module S $end
$var wire 1 # clk $end
$var wire 1 $ rst $end
$var wire 2 & stateNow [1:0] $end
$var wire 2 ' stateNext [1:0] $end
$var wire 7 ( outSS [6:0] $end
$var wire 3 ) outLED [2:0] $end
$var wire 1 * dclk $end
$var wire 3 + count [2:0] $end
$scope module CNT $end
$var wire 1 # clk $end
$var wire 1 $ rst $end
$var wire 2 , stateNow [1:0] $end
$var wire 2 - stateNext [1:0] $end
$var reg 3 . count [2:0] $end
$var reg 3 / countNext [2:0] $end
$upscope $end
$scope module FD $end
$var wire 1 # clk $end
$var wire 1 $ rst $end
$var reg 25 0 count [24:0] $end
$var reg 1 * dclk $end
$upscope $end
$scope module SS $end
$var wire 4 1 in [3:0] $end
$var reg 7 2 out [6:0] $end
$upscope $end
$scope module TL $end
$var wire 1 # clk $end
$var wire 3 3 count [2:0] $end
$var wire 1 $ rst $end
$var reg 3 4 out [2:0] $end
$var reg 2 5 stateNext [1:0] $end
$var reg 2 6 stateNow [1:0] $end
$upscope $end
$upscope $end
$upscope $end
$enddefinitions $end
#0
$dumpvars
b10 6
b10 5
b100 4
b1 3
b110 2
b1 1
b0 0
b10 /
b1 .
b10 -
b10 ,
b1 +
0*
b100 )
b110 (
b10 '
b10 &
b0 %
1$
0#
b100 "
b110 !
$end
#1
0$
#2
b11 /
b1011011 !
b1011011 (
b1011011 2
b10 1
b10 +
b10 .
b10 3
b1 0
b1 %
1#
#3
b10 %
0#
#4
b100 /
b1001111 !
b1001111 (
b1001111 2
b10 0
b11 1
b11 +
b11 .
b11 3
b11 %
1#
#5
b100 %
0#
#6
b101 /
b1100110 !
b1100110 (
b1100110 2
b100 1
b100 +
b100 .
b100 3
b11 0
b101 %
1#
#7
b110 %
0#
#8
b1 /
b0 '
b0 -
b0 5
b1101101 !
b1101101 (
b1101101 2
b100 0
b101 1
b101 +
b101 .
b101 3
b111 %
1#
#9
b1000 %
0#
#10
b110 !
b110 (
b110 2
b10 /
b1 "
b1 )
b1 4
b1 1
b1 +
b1 .
b1 3
b0 &
b0 ,
b0 6
b101 0
b1001 %
1#
#11
b1010 %
0#
#12
b11 /
b1011011 !
b1011011 (
b1011011 2
b110 0
b10 1
b10 +
b10 .
b10 3
b1011 %
1#
#13
b1100 %
0#
#14
b100 /
b1001111 !
b1001111 (
b1001111 2
b11 1
b11 +
b11 .
b11 3
b111 0
b1101 %
1#
#15
b1110 %
0#
#16
b1 /
b1 '
b1 -
b1 5
b1100110 !
b1100110 (
b1100110 2
b1000 0
b100 1
b100 +
b100 .
b100 3
b1111 %
1#
#17
b10000 %
0#
#18
b110 !
b110 (
b110 2
b10 "
b10 )
b10 4
b10 '
b10 -
b10 5
b1 1
b1 +
b1 .
b1 3
b1 &
b1 ,
b1 6
b1001 0
b10001 %
1#
#19
b10010 %
0#
#20
b10 /
b100 "
b100 )
b100 4
b1010 0
b10 &
b10 ,
b10 6
b10011 %
1#
#21
b10100 %
0#
#22
b11 /
b1011011 !
b1011011 (
b1011011 2
b10 1
b10 +
b10 .
b10 3
b1011 0
b10101 %
1#
#23
b10110 %
0#
#24
b100 /
b1001111 !
b1001111 (
b1001111 2
b1100 0
b11 1
b11 +
b11 .
b11 3
b10111 %
1#
#25
b11000 %
0#
#26
b101 /
b1100110 !
b1100110 (
b1100110 2
b100 1
b100 +
b100 .
b100 3
b1101 0
b11001 %
1#
#27
b11010 %
0#
#28
b1 /
b0 '
b0 -
b0 5
b1101101 !
b1101101 (
b1101101 2
b1110 0
b101 1
b101 +
b101 .
b101 3
b11011 %
1#
#29
b11100 %
0#
#30
b110 !
b110 (
b110 2
b10 /
b1 "
b1 )
b1 4
b1 1
b1 +
b1 .
b1 3
b0 &
b0 ,
b0 6
b1111 0
b11101 %
1#
#31
b11110 %
0#
#32
b11 /
b1011011 !
b1011011 (
b1011011 2
b10000 0
b10 1
b10 +
b10 .
b10 3
b11111 %
1#
#33
b100000 %
0#
#34
b100 /
b1001111 !
b1001111 (
b1001111 2
b11 1
b11 +
b11 .
b11 3
b10001 0
b100001 %
1#
#35
b100010 %
0#
#36
b1 /
b1 '
b1 -
b1 5
b1100110 !
b1100110 (
b1100110 2
b10010 0
b100 1
b100 +
b100 .
b100 3
b100011 %
1#
#37
b100100 %
0#
#38
b110 !
b110 (
b110 2
b10 "
b10 )
b10 4
b10 '
b10 -
b10 5
b1 1
b1 +
b1 .
b1 3
b1 &
b1 ,
b1 6
b10011 0
b100101 %
1#
#39
b100110 %
0#
#40
b10 /
b100 "
b100 )
b100 4
b10100 0
b10 &
b10 ,
b10 6
b100111 %
1#
#41
b101000 %
0#
#42
b11 /
b1011011 !
b1011011 (
b1011011 2
b10 1
b10 +
b10 .
b10 3
b10101 0
b101001 %
1#
#43
b101010 %
0#
#44
b100 /
b1001111 !
b1001111 (
b1001111 2
b10110 0
b11 1
b11 +
b11 .
b11 3
b101011 %
1#
#45
b101100 %
0#
#46
b101 /
b1100110 !
b1100110 (
b1100110 2
b100 1
b100 +
b100 .
b100 3
b10111 0
b101101 %
1#
#47
b101110 %
0#
#48
b1 /
b0 '
b0 -
b0 5
b1101101 !
b1101101 (
b1101101 2
b11000 0
b101 1
b101 +
b101 .
b101 3
b101111 %
1#
#49
b110000 %
0#
#50
b110 !
b110 (
b110 2
b10 /
b1 "
b1 )
b1 4
b1 1
b1 +
b1 .
b1 3
b0 &
b0 ,
b0 6
b11001 0
b110001 %
1#
#51
b110010 %
0#
#52
b11 /
b1011011 !
b1011011 (
b1011011 2
b11010 0
b10 1
b10 +
b10 .
b10 3
b110011 %
1#
#53
b110100 %
0#
#54
b100 /
b1001111 !
b1001111 (
b1001111 2
b11 1
b11 +
b11 .
b11 3
b11011 0
b110101 %
1#
#55
b110110 %
0#
#56
b1 /
b1 '
b1 -
b1 5
b1100110 !
b1100110 (
b1100110 2
b11100 0
b100 1
b100 +
b100 .
b100 3
b110111 %
1#
#57
b111000 %
0#
#58
b110 !
b110 (
b110 2
b10 "
b10 )
b10 4
b10 '
b10 -
b10 5
b1 1
b1 +
b1 .
b1 3
b1 &
b1 ,
b1 6
b11101 0
b111001 %
1#
#59
b111010 %
0#
#60
b10 /
b100 "
b100 )
b100 4
b11110 0
b10 &
b10 ,
b10 6
b111011 %
1#
#61
b111100 %
0#
#62
b11 /
b1011011 !
b1011011 (
b1011011 2
b10 1
b10 +
b10 .
b10 3
b11111 0
b111101 %
1#
#63
b111110 %
0#
#64
b100 /
b1001111 !
b1001111 (
b1001111 2
b100000 0
b11 1
b11 +
b11 .
b11 3
b111111 %
1#
#65
b1000000 %
0#
#66
b101 /
b1100110 !
b1100110 (
b1100110 2
b100 1
b100 +
b100 .
b100 3
b100001 0
b1000001 %
1#
#67
b1000010 %
0#
#68
b1 /
b0 '
b0 -
b0 5
b1101101 !
b1101101 (
b1101101 2
b100010 0
b101 1
b101 +
b101 .
b101 3
b1000011 %
1#
#69
b1000100 %
0#
#70
b110 !
b110 (
b110 2
b10 /
b1 "
b1 )
b1 4
b1 1
b1 +
b1 .
b1 3
b0 &
b0 ,
b0 6
b100011 0
b1000101 %
1#
#71
b1000110 %
0#
#72
b11 /
b1011011 !
b1011011 (
b1011011 2
b100100 0
b10 1
b10 +
b10 .
b10 3
b1000111 %
1#
#73
b1001000 %
0#
#74
b100 /
b1001111 !
b1001111 (
b1001111 2
b11 1
b11 +
b11 .
b11 3
b100101 0
b1001001 %
1#
#75
b1001010 %
0#
#76
b1 /
b1 '
b1 -
b1 5
b1100110 !
b1100110 (
b1100110 2
b100110 0
b100 1
b100 +
b100 .
b100 3
b1001011 %
1#
#77
b1001100 %
0#
#78
b110 !
b110 (
b110 2
b10 "
b10 )
b10 4
b10 '
b10 -
b10 5
b1 1
b1 +
b1 .
b1 3
b1 &
b1 ,
b1 6
b100111 0
b1001101 %
1#
#79
b1001110 %
0#
#80
b10 /
b100 "
b100 )
b100 4
b101000 0
b10 &
b10 ,
b10 6
b1001111 %
1#
#81
b1010000 %
0#
#82
b11 /
b1011011 !
b1011011 (
b1011011 2
b10 1
b10 +
b10 .
b10 3
b101001 0
b1010001 %
1#
#83
b1010010 %
0#
#84
b100 /
b1001111 !
b1001111 (
b1001111 2
b101010 0
b11 1
b11 +
b11 .
b11 3
b1010011 %
1#
#85
b1010100 %
0#
#86
b101 /
b1100110 !
b1100110 (
b1100110 2
b100 1
b100 +
b100 .
b100 3
b101011 0
b1010101 %
1#
#87
b1010110 %
0#
#88
b1 /
b0 '
b0 -
b0 5
b1101101 !
b1101101 (
b1101101 2
b101100 0
b101 1
b101 +
b101 .
b101 3
b1010111 %
1#
#89
b1011000 %
0#
#90
b110 !
b110 (
b110 2
b10 /
b1 "
b1 )
b1 4
b1 1
b1 +
b1 .
b1 3
b0 &
b0 ,
b0 6
b101101 0
b1011001 %
1#
#91
b1011010 %
0#
#92
b11 /
b1011011 !
b1011011 (
b1011011 2
b101110 0
b10 1
b10 +
b10 .
b10 3
b1011011 %
1#
#93
b1011100 %
0#
#94
b100 /
b1001111 !
b1001111 (
b1001111 2
b11 1
b11 +
b11 .
b11 3
b101111 0
b1011101 %
1#
#95
b1011110 %
0#
#96
b1 /
b1 '
b1 -
b1 5
b1100110 !
b1100110 (
b1100110 2
b110000 0
b100 1
b100 +
b100 .
b100 3
b1011111 %
1#
#97
b1100000 %
0#
#98
b110 !
b110 (
b110 2
b10 "
b10 )
b10 4
b10 '
b10 -
b10 5
b1 1
b1 +
b1 .
b1 3
b1 &
b1 ,
b1 6
b110001 0
b1100001 %
1#
#99
b1100010 %
0#
#100
b10 /
b100 "
b100 )
b100 4
b110010 0
b10 &
b10 ,
b10 6
b1100011 %
1#
#101
b1100100 %
0#
#102
b11 /
b1011011 !
b1011011 (
b1011011 2
b10 1
b10 +
b10 .
b10 3
b110011 0
b1100101 %
1#
#103
b1100110 %
0#
#104
b100 /
b1001111 !
b1001111 (
b1001111 2
b110100 0
b11 1
b11 +
b11 .
b11 3
b1100111 %
1#
#105
b1101000 %
0#
#106
b101 /
b1100110 !
b1100110 (
b1100110 2
b100 1
b100 +
b100 .
b100 3
b110101 0
b1101001 %
1#
#107
b1101010 %
0#
#108
b1 /
b0 '
b0 -
b0 5
b1101101 !
b1101101 (
b1101101 2
b110110 0
b101 1
b101 +
b101 .
b101 3
b1101011 %
1#
#109
b1101100 %
0#
#110
b110 !
b110 (
b110 2
b10 /
b1 "
b1 )
b1 4
b1 1
b1 +
b1 .
b1 3
b0 &
b0 ,
b0 6
b110111 0
b1101101 %
1#
#111
b1101110 %
0#
#112
b11 /
b1011011 !
b1011011 (
b1011011 2
b111000 0
b10 1
b10 +
b10 .
b10 3
b1101111 %
1#
#113
b1110000 %
0#
#114
b100 /
b1001111 !
b1001111 (
b1001111 2
b11 1
b11 +
b11 .
b11 3
b111001 0
b1110001 %
1#
#115
b1110010 %
0#
#116
b1 /
b1 '
b1 -
b1 5
b1100110 !
b1100110 (
b1100110 2
b111010 0
b100 1
b100 +
b100 .
b100 3
b1110011 %
1#
#117
b1110100 %
0#
#118
b110 !
b110 (
b110 2
b10 "
b10 )
b10 4
b10 '
b10 -
b10 5
b1 1
b1 +
b1 .
b1 3
b1 &
b1 ,
b1 6
b111011 0
b1110101 %
1#
#119
b1110110 %
0#
#120
b10 /
b100 "
b100 )
b100 4
b111100 0
b10 &
b10 ,
b10 6
b1110111 %
1#
#121
b1111000 %
0#
#122
b11 /
b1011011 !
b1011011 (
b1011011 2
b10 1
b10 +
b10 .
b10 3
b111101 0
b1111001 %
1#
#123
b1111010 %
0#
#124
b100 /
b1001111 !
b1001111 (
b1001111 2
b111110 0
b11 1
b11 +
b11 .
b11 3
b1111011 %
1#
#125
b1111100 %
0#
#126
b101 /
b1100110 !
b1100110 (
b1100110 2
b100 1
b100 +
b100 .
b100 3
b111111 0
b1111101 %
1#
#127
b1111110 %
0#
#128
b1 /
b0 '
b0 -
b0 5
b1101101 !
b1101101 (
b1101101 2
b1000000 0
b101 1
b101 +
b101 .
b101 3
b1111111 %
1#
#129
b10000000 %
0#
#130
b110 !
b110 (
b110 2
b10 /
b1 "
b1 )
b1 4
b1 1
b1 +
b1 .
b1 3
b0 &
b0 ,
b0 6
b1000001 0
b10000001 %
1#
#131
b10000010 %
0#
#132
b11 /
b1011011 !
b1011011 (
b1011011 2
b1000010 0
b10 1
b10 +
b10 .
b10 3
b10000011 %
1#
#133
b10000100 %
0#
#134
b100 /
b1001111 !
b1001111 (
b1001111 2
b11 1
b11 +
b11 .
b11 3
b1000011 0
b10000101 %
1#
#135
b10000110 %
0#
#136
b1 /
b1 '
b1 -
b1 5
b1100110 !
b1100110 (
b1100110 2
b1000100 0
b100 1
b100 +
b100 .
b100 3
b10000111 %
1#
#137
b10001000 %
0#
#138
b110 !
b110 (
b110 2
b10 "
b10 )
b10 4
b10 '
b10 -
b10 5
b1 1
b1 +
b1 .
b1 3
b1 &
b1 ,
b1 6
b1000101 0
b10001001 %
1#
#139
b10001010 %
0#
#140
b10 /
b100 "
b100 )
b100 4
b1000110 0
b10 &
b10 ,
b10 6
b10001011 %
1#
#141
b10001100 %
0#
#142
b11 /
b1011011 !
b1011011 (
b1011011 2
b10 1
b10 +
b10 .
b10 3
b1000111 0
b10001101 %
1#
#143
b10001110 %
0#
#144
b100 /
b1001111 !
b1001111 (
b1001111 2
b1001000 0
b11 1
b11 +
b11 .
b11 3
b10001111 %
1#
#145
b10010000 %
0#
#146
b101 /
b1100110 !
b1100110 (
b1100110 2
b100 1
b100 +
b100 .
b100 3
b1001001 0
b10010001 %
1#
#147
b10010010 %
0#
#148
b1 /
b0 '
b0 -
b0 5
b1101101 !
b1101101 (
b1101101 2
b1001010 0
b101 1
b101 +
b101 .
b101 3
b10010011 %
1#
#149
b10010100 %
0#
#150
b110 !
b110 (
b110 2
b10 /
b1 "
b1 )
b1 4
b1 1
b1 +
b1 .
b1 3
b0 &
b0 ,
b0 6
b1001011 0
b10010101 %
1#
#151
b10010110 %
0#
#152
b11 /
b1011011 !
b1011011 (
b1011011 2
b1001100 0
b10 1
b10 +
b10 .
b10 3
b10010111 %
1#
#153
b10011000 %
0#
#154
b100 /
b1001111 !
b1001111 (
b1001111 2
b11 1
b11 +
b11 .
b11 3
b1001101 0
b10011001 %
1#
#155
b10011010 %
0#
#156
b1 /
b1 '
b1 -
b1 5
b1100110 !
b1100110 (
b1100110 2
b1001110 0
b100 1
b100 +
b100 .
b100 3
b10011011 %
1#
#157
b10011100 %
0#
#158
b110 !
b110 (
b110 2
b10 "
b10 )
b10 4
b10 '
b10 -
b10 5
b1 1
b1 +
b1 .
b1 3
b1 &
b1 ,
b1 6
b1001111 0
b10011101 %
1#
#159
b10011110 %
0#
#160
b10 /
b100 "
b100 )
b100 4
b1010000 0
b10 &
b10 ,
b10 6
b10011111 %
1#
#161
b10100000 %
0#
#162
b11 /
b1011011 !
b1011011 (
b1011011 2
b10 1
b10 +
b10 .
b10 3
b1010001 0
b10100001 %
1#
#163
b10100010 %
0#
#164
b100 /
b1001111 !
b1001111 (
b1001111 2
b1010010 0
b11 1
b11 +
b11 .
b11 3
b10100011 %
1#
#165
b10100100 %
0#
#166
b101 /
b1100110 !
b1100110 (
b1100110 2
b100 1
b100 +
b100 .
b100 3
b1010011 0
b10100101 %
1#
#167
b10100110 %
0#
#168
b1 /
b0 '
b0 -
b0 5
b1101101 !
b1101101 (
b1101101 2
b1010100 0
b101 1
b101 +
b101 .
b101 3
b10100111 %
1#
#169
b10101000 %
0#
#170
b110 !
b110 (
b110 2
b10 /
b1 "
b1 )
b1 4
b1 1
b1 +
b1 .
b1 3
b0 &
b0 ,
b0 6
b1010101 0
b10101001 %
1#
#171
b10101010 %
0#
#172
b11 /
b1011011 !
b1011011 (
b1011011 2
b1010110 0
b10 1
b10 +
b10 .
b10 3
b10101011 %
1#
#173
b10101100 %
0#
#174
b100 /
b1001111 !
b1001111 (
b1001111 2
b11 1
b11 +
b11 .
b11 3
b1010111 0
b10101101 %
1#
#175
b10101110 %
0#
#176
b1 /
b1 '
b1 -
b1 5
b1100110 !
b1100110 (
b1100110 2
b1011000 0
b100 1
b100 +
b100 .
b100 3
b10101111 %
1#
#177
b10110000 %
0#
#178
b110 !
b110 (
b110 2
b10 "
b10 )
b10 4
b10 '
b10 -
b10 5
b1 1
b1 +
b1 .
b1 3
b1 &
b1 ,
b1 6
b1011001 0
b10110001 %
1#
#179
b10110010 %
0#
#180
b10 /
b100 "
b100 )
b100 4
b1011010 0
b10 &
b10 ,
b10 6
b10110011 %
1#
#181
b10110100 %
0#
#182
b11 /
b1011011 !
b1011011 (
b1011011 2
b10 1
b10 +
b10 .
b10 3
b1011011 0
b10110101 %
1#
#183
b10110110 %
0#
#184
b100 /
b1001111 !
b1001111 (
b1001111 2
b1011100 0
b11 1
b11 +
b11 .
b11 3
b10110111 %
1#
#185
b10111000 %
0#
#186
b101 /
b1100110 !
b1100110 (
b1100110 2
b100 1
b100 +
b100 .
b100 3
b1011101 0
b10111001 %
1#
#187
b10111010 %
0#
#188
b1 /
b0 '
b0 -
b0 5
b1101101 !
b1101101 (
b1101101 2
b1011110 0
b101 1
b101 +
b101 .
b101 3
b10111011 %
1#
#189
b10111100 %
0#
#190
b110 !
b110 (
b110 2
b10 /
b1 "
b1 )
b1 4
b1 1
b1 +
b1 .
b1 3
b0 &
b0 ,
b0 6
b1011111 0
b10111101 %
1#
#191
b10111110 %
0#
#192
b11 /
b1011011 !
b1011011 (
b1011011 2
b1100000 0
b10 1
b10 +
b10 .
b10 3
b10111111 %
1#
#193
b11000000 %
0#
#194
b100 /
b1001111 !
b1001111 (
b1001111 2
b11 1
b11 +
b11 .
b11 3
b1100001 0
b11000001 %
1#
#195
b11000010 %
0#
#196
b1 /
b1 '
b1 -
b1 5
b1100110 !
b1100110 (
b1100110 2
b1100010 0
b100 1
b100 +
b100 .
b100 3
b11000011 %
1#
#197
b11000100 %
0#
#198
b110 !
b110 (
b110 2
b10 "
b10 )
b10 4
b10 '
b10 -
b10 5
b1 1
b1 +
b1 .
b1 3
b1 &
b1 ,
b1 6
b1100011 0
b11000101 %
1#
#199
b11000110 %
0#
#200
b10 /
b100 "
b100 )
b100 4
b1100100 0
b10 &
b10 ,
b10 6
b11000111 %
1#
#201
b11001000 %
0#
#202
b11 /
b1011011 !
b1011011 (
b1011011 2
b10 1
b10 +
b10 .
b10 3
b1100101 0
b11001001 %
1#
#203
b11001010 %
0#
#204
b100 /
b1001111 !
b1001111 (
b1001111 2
b1100110 0
b11 1
b11 +
b11 .
b11 3
b11001011 %
1#
#205
b11001100 %
0#
#206
b101 /
b1100110 !
b1100110 (
b1100110 2
b100 1
b100 +
b100 .
b100 3
b1100111 0
b11001101 %
1#
#207
b11001110 %
0#
#208
b1 /
b0 '
b0 -
b0 5
b1101101 !
b1101101 (
b1101101 2
b1101000 0
b101 1
b101 +
b101 .
b101 3
b11001111 %
1#
#209
b11010000 %
0#
#210
b110 !
b110 (
b110 2
b10 /
b1 "
b1 )
b1 4
b1 1
b1 +
b1 .
b1 3
b0 &
b0 ,
b0 6
b1101001 0
b11010001 %
1#
#211
b11010010 %
0#
#212
b11 /
b1011011 !
b1011011 (
b1011011 2
b1101010 0
b10 1
b10 +
b10 .
b10 3
b11010011 %
1#
#213
b11010100 %
0#
#214
b100 /
b1001111 !
b1001111 (
b1001111 2
b11 1
b11 +
b11 .
b11 3
b1101011 0
b11010101 %
1#
#215
b11010110 %
0#
#216
b1 /
b1 '
b1 -
b1 5
b1100110 !
b1100110 (
b1100110 2
b1101100 0
b100 1
b100 +
b100 .
b100 3
b11010111 %
1#
#217
b11011000 %
0#
#218
b110 !
b110 (
b110 2
b10 "
b10 )
b10 4
b10 '
b10 -
b10 5
b1 1
b1 +
b1 .
b1 3
b1 &
b1 ,
b1 6
b1101101 0
b11011001 %
1#
#219
b11011010 %
0#
#220
b10 /
b100 "
b100 )
b100 4
b1101110 0
b10 &
b10 ,
b10 6
b11011011 %
1#
#221
b11011100 %
0#
#222
b11 /
b1011011 !
b1011011 (
b1011011 2
b10 1
b10 +
b10 .
b10 3
b1101111 0
b11011101 %
1#
#223
b11011110 %
0#
#224
b100 /
b1001111 !
b1001111 (
b1001111 2
b1110000 0
b11 1
b11 +
b11 .
b11 3
b11011111 %
1#
#225
b11100000 %
0#
#226
b101 /
b1100110 !
b1100110 (
b1100110 2
b100 1
b100 +
b100 .
b100 3
b1110001 0
b11100001 %
1#
#227
b11100010 %
0#
#228
b1 /
b0 '
b0 -
b0 5
b1101101 !
b1101101 (
b1101101 2
b1110010 0
b101 1
b101 +
b101 .
b101 3
b11100011 %
1#
#229
b11100100 %
0#
#230
b110 !
b110 (
b110 2
b10 /
b1 "
b1 )
b1 4
b1 1
b1 +
b1 .
b1 3
b0 &
b0 ,
b0 6
b1110011 0
b11100101 %
1#
#231
b11100110 %
0#
#232
b11 /
b1011011 !
b1011011 (
b1011011 2
b1110100 0
b10 1
b10 +
b10 .
b10 3
b11100111 %
1#
#233
b11101000 %
0#
#234
b100 /
b1001111 !
b1001111 (
b1001111 2
b11 1
b11 +
b11 .
b11 3
b1110101 0
b11101001 %
1#
#235
b11101010 %
0#
#236
b1 /
b1 '
b1 -
b1 5
b1100110 !
b1100110 (
b1100110 2
b1110110 0
b100 1
b100 +
b100 .
b100 3
b11101011 %
1#
#237
b11101100 %
0#
#238
b110 !
b110 (
b110 2
b10 "
b10 )
b10 4
b10 '
b10 -
b10 5
b1 1
b1 +
b1 .
b1 3
b1 &
b1 ,
b1 6
b1110111 0
b11101101 %
1#
#239
b11101110 %
0#
#240
b10 /
b100 "
b100 )
b100 4
b1111000 0
b10 &
b10 ,
b10 6
b11101111 %
1#
#241
b11110000 %
0#
#242
b11 /
b1011011 !
b1011011 (
b1011011 2
b10 1
b10 +
b10 .
b10 3
b1111001 0
b11110001 %
1#
#243
b11110010 %
0#
#244
b100 /
b1001111 !
b1001111 (
b1001111 2
b1111010 0
b11 1
b11 +
b11 .
b11 3
b11110011 %
1#
#245
b11110100 %
0#
#246
b101 /
b1100110 !
b1100110 (
b1100110 2
b100 1
b100 +
b100 .
b100 3
b1111011 0
b11110101 %
1#
#247
b11110110 %
0#
#248
b1 /
b0 '
b0 -
b0 5
b1101101 !
b1101101 (
b1101101 2
b1111100 0
b101 1
b101 +
b101 .
b101 3
b11110111 %
1#
#249
b11111000 %
0#
#250
b110 !
b110 (
b110 2
b10 /
b1 "
b1 )
b1 4
b1 1
b1 +
b1 .
b1 3
b0 &
b0 ,
b0 6
b1111101 0
b11111001 %
1#
#251
b11111010 %
0#
#252
b11 /
b1011011 !
b1011011 (
b1011011 2
b1111110 0
b10 1
b10 +
b10 .
b10 3
b11111011 %
1#
#253
b11111100 %
0#
#254
b100 /
b1001111 !
b1001111 (
b1001111 2
b11 1
b11 +
b11 .
b11 3
b1111111 0
b11111101 %
1#
#255
b11111110 %
0#
#256
b1 /
b1 '
b1 -
b1 5
b1100110 !
b1100110 (
b1100110 2
b10000000 0
b100 1
b100 +
b100 .
b100 3
b11111111 %
1#
#257
b100000000 %
0#
#258
b110 !
b110 (
b110 2
b10 "
b10 )
b10 4
b10 '
b10 -
b10 5
b1 1
b1 +
b1 .
b1 3
b1 &
b1 ,
b1 6
b10000001 0
b100000001 %
1#
#259
b100000010 %
0#
#260
b10 /
b100 "
b100 )
b100 4
b10000010 0
b10 &
b10 ,
b10 6
b100000011 %
1#
#261
b100000100 %
0#
#262
b11 /
b1011011 !
b1011011 (
b1011011 2
b10 1
b10 +
b10 .
b10 3
b10000011 0
b100000101 %
1#
#263
b100000110 %
0#
#264
b100 /
b1001111 !
b1001111 (
b1001111 2
b10000100 0
b11 1
b11 +
b11 .
b11 3
b100000111 %
1#
#265
b100001000 %
0#
#266
b101 /
b1100110 !
b1100110 (
b1100110 2
b100 1
b100 +
b100 .
b100 3
b10000101 0
b100001001 %
1#
#267
b100001010 %
0#
#268
b1 /
b0 '
b0 -
b0 5
b1101101 !
b1101101 (
b1101101 2
b10000110 0
b101 1
b101 +
b101 .
b101 3
b100001011 %
1#
#269
b100001100 %
0#
#270
b110 !
b110 (
b110 2
b10 /
b1 "
b1 )
b1 4
b1 1
b1 +
b1 .
b1 3
b0 &
b0 ,
b0 6
b10000111 0
b100001101 %
1#
#271
b100001110 %
0#
#272
b11 /
b1011011 !
b1011011 (
b1011011 2
b10001000 0
b10 1
b10 +
b10 .
b10 3
b100001111 %
1#
#273
b100010000 %
0#
#274
b100 /
b1001111 !
b1001111 (
b1001111 2
b11 1
b11 +
b11 .
b11 3
b10001001 0
b100010001 %
1#
#275
b100010010 %
0#
#276
b1 /
b1 '
b1 -
b1 5
b1100110 !
b1100110 (
b1100110 2
b10001010 0
b100 1
b100 +
b100 .
b100 3
b100010011 %
1#
#277
b100010100 %
0#
#278
b110 !
b110 (
b110 2
b10 "
b10 )
b10 4
b10 '
b10 -
b10 5
b1 1
b1 +
b1 .
b1 3
b1 &
b1 ,
b1 6
b10001011 0
b100010101 %
1#
#279
b100010110 %
0#
#280
b10 /
b100 "
b100 )
b100 4
b10001100 0
b10 &
b10 ,
b10 6
b100010111 %
1#
#281
b100011000 %
0#
#282
b11 /
b1011011 !
b1011011 (
b1011011 2
b10 1
b10 +
b10 .
b10 3
b10001101 0
b100011001 %
1#
#283
b100011010 %
0#
#284
b100 /
b1001111 !
b1001111 (
b1001111 2
b10001110 0
b11 1
b11 +
b11 .
b11 3
b100011011 %
1#
#285
b100011100 %
0#
#286
b101 /
b1100110 !
b1100110 (
b1100110 2
b100 1
b100 +
b100 .
b100 3
b10001111 0
b100011101 %
1#
#287
b100011110 %
0#
#288
b1 /
b0 '
b0 -
b0 5
b1101101 !
b1101101 (
b1101101 2
b10010000 0
b101 1
b101 +
b101 .
b101 3
b100011111 %
1#
#289
b100100000 %
0#
