Report5/Ex2/fourBitALU.v
module fourBitALU(in0, in1, sel, out);
	input [3:0]in0, in1;
	input [2:0]sel;
	
	output[3:0]out;
	
	assign out = sel[2]?(sel[1]?(sel[0]?in0>in1:in0<<in1):(sel[0]?in0>>in1:in0^in1)):(sel[1]?(sel[0]?in0|in1:in0&in1):(sel[0]?in0-in1:in0+in1));

endmodule

Report5/Ex2/fourBitALUTest.v
module fourBitALUTest;
	reg [3:0]in0, in1;
	reg [2:0]sel;
	reg [4:0]i;
	
	wire[3:0]out;
	
	fourBitALU ALU0(in0, in1, sel, out);
	
	initial begin
		in0=4'b1100;
		in1=4'b0001;
		sel=3'd0;
		for(i=5'd0; i<7; i=i+1)begin
			#1 sel=sel+1;
		end
	end
	
	initial begin
		$monitor("in0=%b, in1=%b, out=%b, sel=%b", in0, in1, out, sel);
	end
	
endmodule

Report5/Ex2/fourBitALUTest.vcd
$date
	Mon Apr 23 20:15:40 2018
$end
$version
	Icarus Verilog
$end
$timescale
	1s
$end
$scope module fourBitALUTest $end
$var wire 4 ! out [3:0] $end
$var reg 5 " i [4:0] $end
$var reg 4 # in0 [3:0] $end
$var reg 4 $ in1 [3:0] $end
$var reg 3 % sel [2:0] $end
$scope module ALU0 $end
$var wire 4 & in0 [3:0] $end
$var wire 4 ' in1 [3:0] $end
$var wire 3 ( sel [2:0] $end
$var wire 4 ) out [3:0] $end
$upscope $end
$upscope $end
$enddefinitions $end
#0
$dumpvars
b1101 )
b0 (
b1 '
b1100 &
b0 %
b1 $
b1100 #
b0 "
b1101 !
$end
#1
b1011 !
b1011 )
b1 "
b1 %
b1 (
#2
b0 !
b0 )
b10 "
b10 %
b10 (
#3
b1101 !
b1101 )
b11 "
b11 %
b11 (
#4
b100 "
b100 %
b100 (
#5
b110 !
b110 )
b101 "
b101 %
b101 (
#6
b1000 !
b1000 )
b110 "
b110 %
b110 (
#7
b1 !
b1 )
b111 "
b111 %
b111 (
#8
b1110 !
b1110 )
b0 "
b0 %
b0 (
b1101 $
b1101 '
b1 #
b1 &
#9
b100 !
b100 )
b1 "
b1 %
b1 (
#10
b1 !
b1 )
b10 "
b10 %
b10 (
#11
b1101 !
b1101 )
b11 "
b11 %
b11 (
#12
b1100 !
b1100 )
b100 "
b100 %
b100 (
#13
b0 !
b0 )
b101 "
b101 %
b101 (
#14
b110 "
b110 %
b110 (
#15
b111 "
b111 %
b111 (
