Report7/Ex2/7seg.v
module sevenSeg(in, out);
	input [3:0]in;
	
	output[6:0]out;
	reg[6:0]out;
	
	always@(*)begin
		case(in)
			4'b0000:out=7'b0111111;
			4'b0001:out=7'b0000110;
			4'b0010:out=7'b1011011;
			4'b0011:out=7'b1001111;
			4'b0100:out=7'b1100110;
			4'b0101:out=7'b1101101;
			4'b0110:out=7'b1111101;
			4'b0111:out=7'b0000111;
			4'b1000:out=7'b1111111;
			4'b1001:out=7'b1101111;
			4'b1010:out=7'b1110111;
			4'b1011:out=7'b1111100;
			4'b1100:out=7'b0111001;
			4'b1101:out=7'b1011110;
			4'b1110:out=7'b1110001;
			4'b1111:out=7'b0000000;
			default:out=7'b0000000;
		endcase		
	end
endmodule

Report7/Ex2/binToBCD.v
module binToBCD(in, outOne, outTen);
	input [5:0]in;
	output reg [3:0]outTen, outOne;
	
	always@(*)begin
		outTen<=in/10;
		outOne<=in%10;
	end

endmodule

Report8/Ex3/coinCounter.v
module coinCounter(clk, rst, buy, insertCoin, coin);
	input clk, rst;
	input [2:0]buy;//snack, drink, candy
	input [3:0]insertCoin;//50, 10, 5, 1
	
	output reg [5:0]coin;
	
	reg [5:0]coinNext;
	
	//combinatorial component to determine the next state
	always@(*)begin
		if(buy[2]) coinNext=(coin>6'd60)?coin-6'd60:coin;
		else if(buy[1]) coinNext=(coin>6'd30)?coin-6'd30:coin;
		else if(buy[0]) coinNext=(coin>6'd15)?coin-6'd15:coin;
		else if(insertCoin[3])coinNext=(coin<=6'd13)?coin+6'd50:coin;
		else if(insertCoin[2])coinNext=(coin<=6'd53)?coin+6'd10:coin;
		else if(insertCoin[1])coinNext=(coin<=6'd58)?coin+6'd05:coin;
		else if(insertCoin[0])coinNext=(coin<=6'd62)?coin+6'd01:coin;
		else coinNext=coin;
	end
	
	
	//memory component to remember current state
	always@(posedge clk or posedge rst)begin
		if(rst)coin<=6'd0;
		else coin<=coinNext;
	end
	

endmodule

Report8/Ex3/vendingMachine.v
module vendingMachine(clk, rst, coin, LEDout);
	input clk, rst;
	input [5:0]coin;
	
	output reg[2:0]LEDout;
	
	reg [1:0]stateNow, stateNext;

	parameter	LEDinsert=3'd0,
				LEDcandy =3'd1,
				LEDdrink =3'd3, 
				LEDsnack =3'd7,
				insert   =2'd0,
				candy    =2'd1, 
				drink    =2'd2,
				snack    =2'd3;
				
	//combinatorial component to determine the next state
	always@(*)begin
		if(coin>=6'd0&&coin<6'd15) stateNext=insert;
		else if(coin>=6'd15&&coin<6'd30) stateNext=candy;
		else if(coin>=6'd30&&coin<6'd60) stateNext=drink;
		else if(coin>=6'd60&&coin<=6'd63) stateNext=snack;
		else stateNext=2'b00;
	end
	
	
	//memory component to remember the current state
	always@(posedge clk or posedge rst)begin
		if(rst) stateNow<=insert;
		else stateNow<=stateNext;
	end
	
	
	//combinatorial component to determine the output
	always@(*)begin
		case(stateNow)
			insert: LEDout=LEDinsert;
			candy:  LEDout=LEDcandy;
			drink:  LEDout=LEDdrink;
			snack:  LEDout=LEDsnack;
		endcase
	end	
				
endmodule

Report9/Ex3/freqDevider.v
module freqDevider(clk, rst, dclk);
	input clk, rst;
	
	output reg dclk;
	
	reg[24:0]count;
	
	always@(posedge clk, posedge rst)begin
		if(rst)begin
			dclk<=1'b0;
			count<=25'd0;
		end
		
		else if(count==25'd24000)begin
			dclk<=~dclk;
			count<=25'd0;
		end
		
		else count<=count+25'd1;
		
	end

endmodule

Report8/Ex3/system.v
module system(clk, rst, buy, insert, LEDout, Ten, One);
	input clk, rst;
	input [2:0]buy;
	input [3:0]insert;
	
	output [2:0]LEDout;
	output [6:0]Ten, One;
	
	wire dclk;
	wire [5:0]coin;
	wire [3:0]SStenIn, SSoneIn;
	
	freqDevider FD(.clk(clk), .rst(rst), .dclk(dclk));
	vendingMachine VM(.clk(clk), .rst(rst), .coin(coin), .LEDout(LEDout));
	coinCounter CC(.clk(clk), .rst(rst), .buy(buy), .insertCoin(insert), .coin(coin));
	binToBCD BTB(.in(coin), .outOne(SSoneIn), .outTen(SStenIn));
	sevenSeg SSTen(.in(SStenIn), .out(Ten));
	sevenSeg SSOne(.in(SSoneIn), .out(One));
	
endmodule

Report8/Ex3/test.v
module test;
	reg clk=1'b0, rst=1'b0;
	reg[2:0]buy;
	reg[3:0]insert;
	
	wire [2:0]LEDout;
	wire [6:0]SSTen, SSOne;
	
	integer count=32'd0;
	
	system S0(.clk(clk), .rst(rst), .buy(buy), .insert(insert), .LEDout(LEDout), .Ten(SSTen), .One(SSOne));
	
	initial begin
		rst=1'b1;#1 rst=1'b0;
		for(count=32'd0; count < 32'd1000; count=count+1)begin
			#1 clk=~clk;
			if(count==32'd10||count==32'd11) insert=4'b1000;
			else if(count==32'd12) insert=4'b0000;
			else if(count==32'd20||count==32'd21) buy=3'b010;
			else if(count==32'd22) buy=3'b000;
		end
	end
	
	initial $monitor("LED:%b, SSOne:%b, SSTen:%b, Cnt: %d", LEDout, SSOne, SSTen, count);
	
	initial begin
		$dumpfile("test.vcd");
		$dumpvars;
	end

endmodule

Report8/Ex3/test.vcd
$date
	Tue May 08 23:31:34 2018
$end
$version
	Icarus Verilog
$end
$timescale
	1s
$end
$scope module test $end
$var wire 7 ! SSTen [6:0] $end
$var wire 7 " SSOne [6:0] $end
$var wire 3 # LEDout [2:0] $end
$var reg 3 $ buy [2:0] $end
$var reg 1 % clk $end
$var reg 4 & insert [3:0] $end
$var reg 1 ' rst $end
$var integer 32 ( count [31:0] $end
$scope module S0 $end
$var wire 3 ) buy [2:0] $end
$var wire 1 % clk $end
$var wire 4 * insert [3:0] $end
$var wire 1 ' rst $end
$var wire 1 + dclk $end
$var wire 6 , coin [5:0] $end
$var wire 7 - Ten [6:0] $end
$var wire 4 . SStenIn [3:0] $end
$var wire 4 / SSoneIn [3:0] $end
$var wire 7 0 One [6:0] $end
$var wire 3 1 LEDout [2:0] $end
$scope module BTB $end
$var wire 6 2 in [5:0] $end
$var reg 4 3 outOne [3:0] $end
$var reg 4 4 outTen [3:0] $end
$upscope $end
$scope module CC $end
$var wire 3 5 buy [2:0] $end
$var wire 1 % clk $end
$var wire 4 6 insertCoin [3:0] $end
$var wire 1 ' rst $end
$var reg 6 7 coin [5:0] $end
$var reg 6 8 coinNext [5:0] $end
$upscope $end
$scope module FD $end
$var wire 1 % clk $end
$var wire 1 ' rst $end
$var reg 25 9 count [24:0] $end
$var reg 1 + dclk $end
$upscope $end
$scope module SSOne $end
$var wire 4 : in [3:0] $end
$var reg 7 ; out [6:0] $end
$upscope $end
$scope module SSTen $end
$var wire 4 < in [3:0] $end
$var reg 7 = out [6:0] $end
$upscope $end
$scope module VM $end
$var wire 1 % clk $end
$var wire 6 > coin [5:0] $end
$var wire 1 ' rst $end
$var reg 3 ? LEDout [2:0] $end
$var reg 2 @ stateNext [1:0] $end
$var reg 2 A stateNow [1:0] $end
$upscope $end
$upscope $end
$upscope $end
$enddefinitions $end
#0
$dumpvars
b0 A
b0 @
b0 ?
b0 >
b111111 =
b0 <
b111111 ;
b0 :
b0 9
b0 8
b0 7
bx 6
bx 5
b0 4
b0 3
b0 2
b0 1
b111111 0
b0 /
b0 .
b111111 -
b0 ,
0+
bx *
bx )
b0 (
1'
bx &
0%
bx $
b0 #
b111111 "
b111111 !
$end
#1
0'
#2
b1 9
b1 (
1%
#3
b10 (
0%
#4
b10 9
b11 (
1%
#5
b100 (
0%
#6
b11 9
b101 (
1%
#7
b110 (
0%
#8
b100 9
b111 (
1%
#9
b1000 (
0%
#10
b101 9
b1001 (
1%
#11
b1010 (
0%
#12
b110 9
b110010 8
b1011 (
b1000 &
b1000 *
b1000 6
1%
#13
b1100 (
0%
#14
b1101101 !
b1101101 -
b1101101 =
b101 .
b101 4
b101 <
b10 @
b110010 ,
b110010 2
b110010 7
b110010 >
b111 9
b110010 8
b1101 (
b0 &
b0 *
b0 6
1%
#15
b1110 (
0%
#16
b11 #
b11 1
b11 ?
b1000 9
b10 A
b1111 (
1%
#17
b10000 (
0%
#18
b1001 9
b10001 (
1%
#19
b10010 (
0%
#20
b1010 9
b10011 (
1%
#21
b10100 (
0%
#22
b1011 9
b10100 8
b10101 (
b10 $
b10 )
b10 5
1%
#23
b10110 (
0%
#24
b1011011 !
b1011011 -
b1011011 =
b10 .
b10 4
b10 <
b1 @
b1100 9
b10100 ,
b10100 2
b10100 7
b10100 >
b10100 8
b10111 (
b0 $
b0 )
b0 5
1%
#25
b11000 (
0%
#26
b1 #
b1 1
b1 ?
b1 A
b1101 9
b11001 (
1%
#27
b11010 (
0%
#28
b1110 9
b11011 (
1%
#29
b11100 (
0%
#30
b1111 9
b11101 (
1%
#31
b11110 (
0%
#32
b10000 9
b11111 (
1%
#33
b100000 (
0%
#34
b10001 9
b100001 (
1%
#35
b100010 (
0%
#36
b10010 9
b100011 (
1%
#37
b100100 (
0%
#38
b10011 9
b100101 (
1%
#39
b100110 (
0%
#40
b10100 9
b100111 (
1%
#41
b101000 (
0%
#42
b10101 9
b101001 (
1%
#43
b101010 (
0%
#44
b10110 9
b101011 (
1%
#45
b101100 (
0%
#46
b10111 9
b101101 (
1%
#47
b101110 (
0%
#48
b11000 9
b101111 (
1%
#49
b110000 (
0%
#50
b11001 9
b110001 (
1%
#51
b110010 (
0%
#52
b11010 9
b110011 (
1%
#53
b110100 (
0%
#54
b11011 9
b110101 (
1%
#55
b110110 (
0%
#56
b11100 9
b110111 (
1%
#57
b111000 (
0%
#58
b11101 9
b111001 (
1%
#59
b111010 (
0%
#60
b11110 9
b111011 (
1%
#61
b111100 (
0%
#62
b11111 9
b111101 (
1%
#63
b111110 (
0%
#64
b100000 9
b111111 (
1%
#65
b1000000 (
0%
#66
b100001 9
b1000001 (
1%
#67
b1000010 (
0%
#68
b100010 9
b1000011 (
1%
#69
b1000100 (
0%
#70
b100011 9
b1000101 (
1%
#71
b1000110 (
0%
#72
b100100 9
b1000111 (
1%
#73
b1001000 (
0%
#74
b100101 9
b1001001 (
1%
#75
b1001010 (
0%
#76
b100110 9
b1001011 (
1%
#77
b1001100 (
0%
#78
b100111 9
b1001101 (
1%
#79
b1001110 (
0%
#80
b101000 9
b1001111 (
1%
#81
b1010000 (
0%
#82
b101001 9
b1010001 (
1%
#83
b1010010 (
0%
#84
b101010 9
b1010011 (
1%
#85
b1010100 (
0%
#86
b101011 9
b1010101 (
1%
#87
b1010110 (
0%
#88
b101100 9
b1010111 (
1%
#89
b1011000 (
0%
#90
b101101 9
b1011001 (
1%
#91
b1011010 (
0%
#92
b101110 9
b1011011 (
1%
#93
b1011100 (
0%
#94
b101111 9
b1011101 (
1%
#95
b1011110 (
0%
#96
b110000 9
b1011111 (
1%
#97
b1100000 (
0%
#98
b110001 9
b1100001 (
1%
#99
b1100010 (
0%
#100
b110010 9
b1100011 (
1%
#101
b1100100 (
0%
#102
b110011 9
b1100101 (
1%
#103
b1100110 (
0%
#104
b110100 9
b1100111 (
1%
#105
b1101000 (
0%
#106
b110101 9
b1101001 (
1%
#107
b1101010 (
0%
#108
b110110 9
b1101011 (
1%
#109
b1101100 (
0%
#110
b110111 9
b1101101 (
1%
#111
b1101110 (
0%
#112
b111000 9
b1101111 (
1%
#113
b1110000 (
0%
#114
b111001 9
b1110001 (
1%
#115
b1110010 (
0%
#116
b111010 9
b1110011 (
1%
#117
b1110100 (
0%
#118
b111011 9
b1110101 (
1%
#119
b1110110 (
0%
#120
b111100 9
b1110111 (
1%
#121
b1111000 (
0%
#122
b111101 9
b1111001 (
1%
#123
b1111010 (
0%
#124
b111110 9
b1111011 (
1%
#125
b1111100 (
0%
#126
b111111 9
b1111101 (
1%
#127
b1111110 (
0%
#128
b1000000 9
b1111111 (
1%
#129
b10000000 (
0%
#130
b1000001 9
b10000001 (
1%
#131
b10000010 (
0%
#132
b1000010 9
b10000011 (
1%
#133
b10000100 (
0%
#134
b1000011 9
b10000101 (
1%
#135
b10000110 (
0%
#136
b1000100 9
b10000111 (
1%
#137
b10001000 (
0%
#138
b1000101 9
b10001001 (
1%
#139
b10001010 (
0%
#140
b1000110 9
b10001011 (
1%
#141
b10001100 (
0%
#142
b1000111 9
b10001101 (
1%
#143
b10001110 (
0%
#144
b1001000 9
b10001111 (
1%
#145
b10010000 (
0%
#146
b1001001 9
b10010001 (
1%
#147
b10010010 (
0%
#148
b1001010 9
b10010011 (
1%
#149
b10010100 (
0%
#150
b1001011 9
b10010101 (
1%
#151
b10010110 (
0%
#152
b1001100 9
b10010111 (
1%
#153
b10011000 (
0%
#154
b1001101 9
b10011001 (
1%
#155
b10011010 (
0%
#156
b1001110 9
b10011011 (
1%
#157
b10011100 (
0%
#158
b1001111 9
b10011101 (
1%
#159
b10011110 (
0%
#160
b1010000 9
b10011111 (
1%
#161
b10100000 (
0%
#162
b1010001 9
b10100001 (
1%
#163
b10100010 (
0%
#164
b1010010 9
b10100011 (
1%
#165
b10100100 (
0%
#166
b1010011 9
b10100101 (
1%
#167
b10100110 (
0%
#168
b1010100 9
b10100111 (
1%
#169
b10101000 (
0%
#170
b1010101 9
b10101001 (
1%
#171
b10101010 (
0%
#172
b1010110 9
b10101011 (
1%
#173
b10101100 (
0%
#174
b1010111 9
b10101101 (
1%
#175
b10101110 (
0%
#176
b1011000 9
b10101111 (
1%
#177
b10110000 (
0%
#178
b1011001 9
b10110001 (
1%
#179
b10110010 (
0%
#180
b1011010 9
b10110011 (
1%
#181
b10110100 (
0%
#182
b1011011 9
b10110101 (
1%
#183
b10110110 (
0%
#184
b1011100 9
b10110111 (
1%
#185
b10111000 (
0%
#186
b1011101 9
b10111001 (
1%
#187
b10111010 (
0%
#188
b1011110 9
b10111011 (
1%
#189
b10111100 (
0%
#190
b1011111 9
b10111101 (
1%
#191
b10111110 (
0%
#192
b1100000 9
b10111111 (
1%
#193
b11000000 (
0%
#194
b1100001 9
b11000001 (
1%
#195
b11000010 (
0%
#196
b1100010 9
b11000011 (
1%
#197
b11000100 (
0%
#198
b1100011 9
b11000101 (
1%
#199
b11000110 (
0%
#200
b1100100 9
b11000111 (
1%
#201
b11001000 (
0%
#202
b1100101 9
b11001001 (
1%
#203
b11001010 (
0%
#204
b1100110 9
b11001011 (
1%
#205
b11001100 (
0%
#206
b1100111 9
b11001101 (
1%
#207
b11001110 (
0%
#208
b1101000 9
b11001111 (
1%
#209
b11010000 (
0%
#210
b1101001 9
b11010001 (
1%
#211
b11010010 (
0%
#212
b1101010 9
b11010011 (
1%
#213
b11010100 (
0%
#214
b1101011 9
b11010101 (
1%
#215
b11010110 (
0%
#216
b1101100 9
b11010111 (
1%
#217
b11011000 (
0%
#218
b1101101 9
b11011001 (
1%
#219
b11011010 (
0%
#220
b1101110 9
b11011011 (
1%
#221
b11011100 (
0%
#222
b1101111 9
b11011101 (
1%
#223
b11011110 (
0%
#224
b1110000 9
b11011111 (
1%
#225
b11100000 (
0%
#226
b1110001 9
b11100001 (
1%
#227
b11100010 (
0%
#228
b1110010 9
b11100011 (
1%
#229
b11100100 (
0%
#230
b1110011 9
b11100101 (
1%
#231
b11100110 (
0%
#232
b1110100 9
b11100111 (
1%
#233
b11101000 (
0%
#234
b1110101 9
b11101001 (
1%
#235
b11101010 (
0%
#236
b1110110 9
b11101011 (
1%
#237
b11101100 (
0%
#238
b1110111 9
b11101101 (
1%
#239
b11101110 (
0%
#240
b1111000 9
b11101111 (
1%
#241
b11110000 (
0%
#242
b1111001 9
b11110001 (
1%
#243
b11110010 (
0%
#244
b1111010 9
b11110011 (
1%
#245
b11110100 (
0%
#246
b1111011 9
b11110101 (
1%
#247
b11110110 (
0%
#248
b1111100 9
b11110111 (
1%
#249
b11111000 (
0%
#250
b1111101 9
b11111001 (
1%
#251
b11111010 (
0%
#252
b1111110 9
b11111011 (
1%
#253
b11111100 (
0%
#254
b1111111 9
b11111101 (
1%
#255
b11111110 (
0%
#256
b10000000 9
b11111111 (
1%
#257
b100000000 (
0%
#258
b10000001 9
b100000001 (
1%
#259
b100000010 (
0%
#260
b10000010 9
b100000011 (
1%
#261
b100000100 (
0%
#262
b10000011 9
b100000101 (
1%
#263
b100000110 (
0%
#264
b10000100 9
b100000111 (
1%
#265
b100001000 (
0%
#266
b10000101 9
b100001001 (
1%
#267
b100001010 (
0%
#268
b10000110 9
b100001011 (
1%
#269
b100001100 (
0%
#270
b10000111 9
b100001101 (
1%
#271
b100001110 (
0%
#272
b10001000 9
b100001111 (
1%
#273
b100010000 (
0%
#274
b10001001 9
b100010001 (
1%
#275
b100010010 (
0%
#276
b10001010 9
b100010011 (
1%
#277
b100010100 (
0%
#278
b10001011 9
b100010101 (
1%
#279
b100010110 (
0%
#280
b10001100 9
b100010111 (
1%
#281
b100011000 (
0%
#282
b10001101 9
b100011001 (
1%
#283
b100011010 (
0%
#284
b10001110 9
b100011011 (
1%
#285
b100011100 (
0%
#286
b10001111 9
b100011101 (
1%
#287
b100011110 (
0%
#288
b10010000 9
b100011111 (
1%
#289
b100100000 (
0%
#290
b10010001 9
b100100001 (
1%
#291
b100100010 (
0%
#292
b10010010 9
b100100011 (
1%
#293
b100100100 (
0%
#294
b10010011 9
b100100101 (
1%
#295
b100100110 (
0%
#296
b10010100 9
b100100111 (
1%
#297
b100101000 (
0%
#298
b10010101 9
b100101001 (
1%
#299
b100101010 (
0%
#300
b10010110 9
b100101011 (
1%
#301
b100101100 (
0%
#302
b10010111 9
b100101101 (
1%
#303
b100101110 (
0%
#304
b10011000 9
b100101111 (
1%
#305
b100110000 (
0%
#306
b10011001 9
b100110001 (
1%
#307
b100110010 (
0%
#308
b10011010 9
b100110011 (
1%
#309
b100110100 (
0%
#310
b10011011 9
b100110101 (
1%
#311
b100110110 (
0%
#312
b10011100 9
b100110111 (
1%
#313
b100111000 (
0%
#314
b10011101 9
b100111001 (
1%
#315
b100111010 (
0%
#316
b10011110 9
b100111011 (
1%
#317
b100111100 (
0%
#318
b10011111 9
b100111101 (
1%
#319
b100111110 (
0%
#320
b10100000 9
b100111111 (
1%
#321
b101000000 (
0%
#322
b10100001 9
b101000001 (
1%
#323
b101000010 (
0%
#324
b10100010 9
b101000011 (
1%
#325
b101000100 (
0%
#326
b10100011 9
b101000101 (
1%
#327
b101000110 (
0%
#328
b10100100 9
b101000111 (
1%
#329
b101001000 (
0%
#330
b10100101 9
b101001001 (
1%
#331
b101001010 (
0%
#332
b10100110 9
b101001011 (
1%
#333
b101001100 (
0%
#334
b10100111 9
b101001101 (
1%
#335
b101001110 (
0%
#336
b10101000 9
b101001111 (
1%
#337
b101010000 (
0%
#338
b10101001 9
b101010001 (
1%
#339
b101010010 (
0%
#340
b10101010 9
b101010011 (
1%
#341
b101010100 (
0%
#342
b10101011 9
b101010101 (
1%
#343
b101010110 (
0%
#344
b10101100 9
b101010111 (
1%
#345
b101011000 (
0%
#346
b10101101 9
b101011001 (
1%
#347
b101011010 (
0%
#348
b10101110 9
b101011011 (
1%
#349
b101011100 (
0%
#350
b10101111 9
b101011101 (
1%
#351
b101011110 (
0%
#352
b10110000 9
b101011111 (
1%
#353
b101100000 (
0%
#354
b10110001 9
b101100001 (
1%
#355
b101100010 (
0%
#356
b10110010 9
b101100011 (
1%
#357
b101100100 (
0%
#358
b10110011 9
b101100101 (
1%
#359
b101100110 (
0%
#360
b10110100 9
b101100111 (
1%
#361
b101101000 (
0%
#362
b10110101 9
b101101001 (
1%
#363
b101101010 (
0%
#364
b10110110 9
b101101011 (
1%
#365
b101101100 (
0%
#366
b10110111 9
b101101101 (
1%
#367
b101101110 (
0%
#368
b10111000 9
b101101111 (
1%
#369
b101110000 (
0%
#370
b10111001 9
b101110001 (
1%
#371
b101110010 (
0%
#372
b10111010 9
b101110011 (
1%
#373
b101110100 (
0%
#374
b10111011 9
b101110101 (
1%
#375
b101110110 (
0%
#376
b10111100 9
b101110111 (
1%
#377
b101111000 (
0%
#378
b10111101 9
b101111001 (
1%
#379
b101111010 (
0%
#380
b10111110 9
b101111011 (
1%
#381
b101111100 (
0%
#382
b10111111 9
b101111101 (
1%
#383
b101111110 (
0%
#384
b11000000 9
b101111111 (
1%
#385
b110000000 (
0%
#386
b11000001 9
b110000001 (
1%
#387
b110000010 (
0%
#388
b11000010 9
b110000011 (
1%
#389
b110000100 (
0%
#390
b11000011 9
b110000101 (
1%
#391
b110000110 (
0%
#392
b11000100 9
b110000111 (
1%
#393
b110001000 (
0%
#394
b11000101 9
b110001001 (
1%
#395
b110001010 (
0%
#396
b11000110 9
b110001011 (
1%
#397
b110001100 (
0%
#398
b11000111 9
b110001101 (
1%
#399
b110001110 (
0%
#400
b11001000 9
b110001111 (
1%
#401
b110010000 (
0%
#402
b11001001 9
b110010001 (
1%
#403
b110010010 (
0%
#404
b11001010 9
b110010011 (
1%
#405
b110010100 (
0%
#406
b11001011 9
b110010101 (
1%
#407
b110010110 (
0%
#408
b11001100 9
b110010111 (
1%
#409
b110011000 (
0%
#410
b11001101 9
b110011001 (
1%
#411
b110011010 (
0%
#412
b11001110 9
b110011011 (
1%
#413
b110011100 (
0%
#414
b11001111 9
b110011101 (
1%
#415
b110011110 (
0%
#416
b11010000 9
b110011111 (
1%
#417
b110100000 (
0%
#418
b11010001 9
b110100001 (
1%
#419
b110100010 (
0%
#420
b11010010 9
b110100011 (
1%
#421
b110100100 (
0%
#422
b11010011 9
b110100101 (
1%
#423
b110100110 (
0%
#424
b11010100 9
b110100111 (
1%
#425
b110101000 (
0%
#426
b11010101 9
b110101001 (
1%
#427
b110101010 (
0%
#428
b11010110 9
b110101011 (
1%
#429
b110101100 (
0%
#430
b11010111 9
b110101101 (
1%
#431
b110101110 (
0%
#432
b11011000 9
b110101111 (
1%
#433
b110110000 (
0%
#434
b11011001 9
b110110001 (
1%
#435
b110110010 (
0%
#436
b11011010 9
b110110011 (
1%
#437
b110110100 (
0%
#438
b11011011 9
b110110101 (
1%
#439
b110110110 (
0%
#440
b11011100 9
b110110111 (
1%
#441
b110111000 (
0%
#442
b11011101 9
b110111001 (
1%
#443
b110111010 (
0%
#444
b11011110 9
b110111011 (
1%
#445
b110111100 (
0%
#446
b11011111 9
b110111101 (
1%
#447
b110111110 (
0%
#448
b11100000 9
b110111111 (
1%
#449
b111000000 (
0%
#450
b11100001 9
b111000001 (
1%
#451
b111000010 (
0%
#452
b11100010 9
b111000011 (
1%
#453
b111000100 (
0%
#454
b11100011 9
b111000101 (
1%
#455
b111000110 (
0%
#456
b11100100 9
b111000111 (
1%
#457
b111001000 (
0%
#458
b11100101 9
b111001001 (
1%
#459
b111001010 (
0%
#460
b11100110 9
b111001011 (
1%
#461
b111001100 (
0%
#462
b11100111 9
b111001101 (
1%
#463
b111001110 (
0%
#464
b11101000 9
b111001111 (
1%
#465
b111010000 (
0%
#466
b11101001 9
b111010001 (
1%
#467
b111010010 (
0%
#468
b11101010 9
b111010011 (
1%
#469
b111010100 (
0%
#470
b11101011 9
b111010101 (
1%
#471
b111010110 (
0%
#472
b11101100 9
b111010111 (
1%
#473
b111011000 (
0%
#474
b11101101 9
b111011001 (
1%
#475
b111011010 (
0%
#476
b11101110 9
b111011011 (
1%
#477
b111011100 (
0%
#478
b11101111 9
b111011101 (
1%
#479
b111011110 (
0%
#480
b11110000 9
b111011111 (
1%
#481
b111100000 (
0%
#482
b11110001 9
b111100001 (
1%
#483
b111100010 (
0%
#484
b11110010 9
b111100011 (
1%
#485
b111100100 (
0%
#486
b11110011 9
b111100101 (
1%
#487
b111100110 (
0%
#488
b11110100 9
b111100111 (
1%
#489
b111101000 (
0%
#490
b11110101 9
b111101001 (
1%
#491
b111101010 (
0%
#492
b11110110 9
b111101011 (
1%
#493
b111101100 (
0%
#494
b11110111 9
b111101101 (
1%
#495
b111101110 (
0%
#496
b11111000 9
b111101111 (
1%
#497
b111110000 (
0%
#498
b11111001 9
b111110001 (
1%
#499
b111110010 (
0%
#500
b11111010 9
b111110011 (
1%
#501
b111110100 (
0%
#502
b11111011 9
b111110101 (
1%
#503
b111110110 (
0%
#504
b11111100 9
b111110111 (
1%
#505
b111111000 (
0%
#506
b11111101 9
b111111001 (
1%
#507
b111111010 (
0%
#508
b11111110 9
b111111011 (
1%
#509
b111111100 (
0%
#510
b11111111 9
b111111101 (
1%
#511
b111111110 (
0%
#512
b100000000 9
b111111111 (
1%
#513
b1000000000 (
0%
#514
b100000001 9
b1000000001 (
1%
#515
b1000000010 (
0%
#516
b100000010 9
b1000000011 (
1%
#517
b1000000100 (
0%
#518
b100000011 9
b1000000101 (
1%
#519
b1000000110 (
0%
#520
b100000100 9
b1000000111 (
1%
#521
b1000001000 (
0%
#522
b100000101 9
b1000001001 (
1%
#523
b1000001010 (
0%
#524
b100000110 9
b1000001011 (
1%
#525
b1000001100 (
0%
#526
b100000111 9
b1000001101 (
1%
#527
b1000001110 (
0%
#528
b100001000 9
b1000001111 (
1%
#529
b1000010000 (
0%
#530
b100001001 9
b1000010001 (
1%
#531
b1000010010 (
0%
#532
b100001010 9
b1000010011 (
1%
#533
b1000010100 (
0%
#534
b100001011 9
b1000010101 (
1%
#535
b1000010110 (
0%
#536
b100001100 9
b1000010111 (
1%
#537
b1000011000 (
0%
#538
b100001101 9
b1000011001 (
1%
#539
b1000011010 (
0%
#540
b100001110 9
b1000011011 (
1%
#541
b1000011100 (
0%
#542
b100001111 9
b1000011101 (
1%
#543
b1000011110 (
0%
#544
b100010000 9
b1000011111 (
1%
#545
b1000100000 (
0%
#546
b100010001 9
b1000100001 (
1%
#547
b1000100010 (
0%
#548
b100010010 9
b1000100011 (
1%
#549
b1000100100 (
0%
#550
b100010011 9
b1000100101 (
1%
#551
b1000100110 (
0%
#552
b100010100 9
b1000100111 (
1%
#553
b1000101000 (
0%
#554
b100010101 9
b1000101001 (
1%
#555
b1000101010 (
0%
#556
b100010110 9
b1000101011 (
1%
#557
b1000101100 (
0%
#558
b100010111 9
b1000101101 (
1%
#559
b1000101110 (
0%
#560
b100011000 9
b1000101111 (
1%
#561
b1000110000 (
0%
#562
b100011001 9
b1000110001 (
1%
#563
b1000110010 (
0%
#564
b100011010 9
b1000110011 (
1%
#565
b1000110100 (
0%
#566
b100011011 9
b1000110101 (
1%
#567
b1000110110 (
0%
#568
b100011100 9
b1000110111 (
1%
#569
b1000111000 (
0%
#570
b100011101 9
b1000111001 (
1%
#571
b1000111010 (
0%
#572
b100011110 9
b1000111011 (
1%
#573
b1000111100 (
0%
#574
b100011111 9
b1000111101 (
1%
#575
b1000111110 (
0%
#576
b100100000 9
b1000111111 (
1%
#577
b1001000000 (
0%
#578
b100100001 9
b1001000001 (
1%
#579
b1001000010 (
0%
#580
b100100010 9
b1001000011 (
1%
#581
b1001000100 (
0%
#582
b100100011 9
b1001000101 (
1%
#583
b1001000110 (
0%
#584
b100100100 9
b1001000111 (
1%
#585
b1001001000 (
0%
#586
b100100101 9
b1001001001 (
1%
#587
b1001001010 (
0%
#588
b100100110 9
b1001001011 (
1%
#589
b1001001100 (
0%
#590
b100100111 9
b1001001101 (
1%
#591
b1001001110 (
0%
#592
b100101000 9
b1001001111 (
1%
#593
b1001010000 (
0%
#594
b100101001 9
b1001010001 (
1%
#595
b1001010010 (
0%
#596
b100101010 9
b1001010011 (
1%
#597
b1001010100 (
0%
#598
b100101011 9
b1001010101 (
1%
#599
b1001010110 (
0%
#600
b100101100 9
b1001010111 (
1%
#601
b1001011000 (
0%
#602
b100101101 9
b1001011001 (
1%
#603
b1001011010 (
0%
#604
b100101110 9
b1001011011 (
1%
#605
b1001011100 (
0%
#606
b100101111 9
b1001011101 (
1%
#607
b1001011110 (
0%
#608
b100110000 9
b1001011111 (
1%
#609
b1001100000 (
0%
#610
b100110001 9
b1001100001 (
1%
#611
b1001100010 (
0%
#612
b100110010 9
b1001100011 (
1%
#613
b1001100100 (
0%
#614
b100110011 9
b1001100101 (
1%
#615
b1001100110 (
0%
#616
b100110100 9
b1001100111 (
1%
#617
b1001101000 (
0%
#618
b100110101 9
b1001101001 (
1%
#619
b1001101010 (
0%
#620
b100110110 9
b1001101011 (
1%
#621
b1001101100 (
0%
#622
b100110111 9
b1001101101 (
1%
#623
b1001101110 (
0%
#624
b100111000 9
b1001101111 (
1%
#625
b1001110000 (
0%
#626
b100111001 9
b1001110001 (
1%
#627
b1001110010 (
0%
#628
b100111010 9
b1001110011 (
1%
#629
b1001110100 (
0%
#630
b100111011 9
b1001110101 (
1%
#631
b1001110110 (
0%
#632
b100111100 9
b1001110111 (
1%
#633
b1001111000 (
0%
#634
b100111101 9
b1001111001 (
1%
#635
b1001111010 (
0%
#636
b100111110 9
b1001111011 (
1%
#637
b1001111100 (
0%
#638
b100111111 9
b1001111101 (
1%
#639
b1001111110 (
0%
#640
b101000000 9
b1001111111 (
1%
#641
b1010000000 (
0%
#642
b101000001 9
b1010000001 (
1%
#643
b1010000010 (
0%
#644
b101000010 9
b1010000011 (
1%
#645
b1010000100 (
0%
#646
b101000011 9
b1010000101 (
1%
#647
b1010000110 (
0%
#648
b101000100 9
b1010000111 (
1%
#649
b1010001000 (
0%
#650
b101000101 9
b1010001001 (
1%
#651
b1010001010 (
0%
#652
b101000110 9
b1010001011 (
1%
#653
b1010001100 (
0%
#654
b101000111 9
b1010001101 (
1%
#655
b1010001110 (
0%
#656
b101001000 9
b1010001111 (
1%
#657
b1010010000 (
0%
#658
b101001001 9
b1010010001 (
1%
#659
b1010010010 (
0%
#660
b101001010 9
b1010010011 (
1%
#661
b1010010100 (
0%
#662
b101001011 9
b1010010101 (
1%
#663
b1010010110 (
0%
#664
b101001100 9
b1010010111 (
1%
#665
b1010011000 (
0%
#666
b101001101 9
b1010011001 (
1%
#667
b1010011010 (
0%
#668
b101001110 9
b1010011011 (
1%
#669
b1010011100 (
0%
