Report9/Ex2/LEDMatrix.v
module LEDMatrix(clk, rst, sel, row, col);
	input clk, rst, sel;
	
	output reg[7:0]row, col;
	
	always@(posedge clk or posedge rst)begin
		if(rst) row<=8'b00000001;
		else if(row==8'b10000000) row<=8'b00000001;
		else row=row<<1'b1;
	end
	
	always@(*)begin
		if(sel==1'b0)begin
			case(row)
				8'b00000001:col=8'b01100110;
				8'b00000010:col=8'b10011001;
				8'b00000100:col=8'b10000001;
				8'b00001000:col=8'b10000001;
				8'b00010000:col=8'b10000001;
				8'b00100000:col=8'b01000010;
				8'b01000000:col=8'b00100100;
				8'b10000000:col=8'b00011000;
			endcase
		end
		else begin
			case(row)
				8'b00000001:col=8'b01100110;
				8'b00000010:col=8'b10011001;
				8'b00000100:col=8'b10001001;
				8'b00001000:col=8'b10010001;
				8'b00010000:col=8'b10001001;
				8'b00100000:col=8'b01010010;
				8'b01000000:col=8'b00100100;
				8'b10000000:col=8'b00011000;
			endcase
		end
	end
	
endmodule

Report9/Ex2/system.v
module system(clk, rst, row, col, sel);
	input clk, rst, sel;
	
	output[7:0]row, col;
	
	wire dclk;
	
	//freqDevider FD(.clk(clk), .dclk(dclk));
	LEDMatrix LM(.clk(clk), .rst(rst), .row(row), .col(col), .sel(sel));
	
endmodule

Report9/Ex2/test.v
module test;
	reg clk, rst, sel;	
	
	wire[7:0]row, col;
	
	integer cnt=0;
	
	system S(.clk(clk), .rst(rst), .row(row), .col(col), .sel(sel));
	
	initial begin
		rst=1'b1;#1 rst=1'b0;
		sel=1'b0; clk=1'd0;
		for(cnt=0; cnt<32'd100; cnt=cnt+1)begin
			clk=~clk;
			#1;
		end
		sel=1'b1;
		for(cnt=0; cnt<32'd100; cnt=cnt+1)begin
			clk=~clk;
			#1;
		end
	end
	
	initial begin
		$monitor("row:%b, col:%b, sel:%b", row, col, sel);
	end
	
	initial begin
		$dumpfile("test.vcd");
		$dumpvars;
	end	
endmodule

Report9/Ex3/freqDevider.v
module freqDevider(clk, rst, dclk);
	input clk, rst;
	
	output reg dclk;
	
	reg[24:0]count;
	
	always@(posedge clk, posedge rst)begin
		if(rst)begin
			dclk<=1'b0;
			count<=25'd0;
		end
		
		else if(count==25'd24000)begin
			dclk<=~dclk;
			count<=25'd0;
		end
		
		else count<=count+25'd1;
		
	end

endmodule

Report9/Ex2/test.vcd
$date
	Tue May 22 11:53:20 2018
$end
$version
	Icarus Verilog
$end
$timescale
	1s
$end
$scope module freqDevider $end
$var wire 1 ! clk $end
$var wire 1 " rst $end
$var reg 25 # count [24:0] $end
$var reg 1 $ dclk $end
$upscope $end
$scope module test $end
$var wire 8 % row [7:0] $end
$var wire 8 & col [7:0] $end
$var reg 1 ' clk $end
$var reg 1 ( rst $end
$var reg 1 ) sel $end
$var integer 32 * cnt [31:0] $end
$scope module S $end
$var wire 1 ' clk $end
$var wire 1 ( rst $end
$var wire 1 ) sel $end
$var wire 8 + row [7:0] $end
$var wire 8 , col [7:0] $end
$scope module LM $end
$var wire 1 ' clk $end
$var wire 1 ( rst $end
$var wire 1 ) sel $end
$var reg 8 - col [7:0] $end
$var reg 8 . row [7:0] $end
$upscope $end
$upscope $end
$upscope $end
$enddefinitions $end
#0
$dumpvars
b1 .
b1100110 -
b1100110 ,
b1 +
b0 *
x)
1(
x'
b1100110 &
b1 %
x$
bx #
z"
z!
$end
#1
b10011001 &
b10011001 ,
b10011001 -
b10 %
b10 +
b10 .
1'
0)
0(
#2
0'
b1 *
#3
b10000001 &
b10000001 ,
b10000001 -
b100 %
b100 +
b100 .
1'
b10 *
#4
0'
b11 *
#5
b1000 %
b1000 +
b1000 .
1'
b100 *
#6
0'
b101 *
#7
b10000 %
b10000 +
b10000 .
1'
b110 *
#8
0'
b111 *
#9
b1000010 &
b1000010 ,
b1000010 -
b100000 %
b100000 +
b100000 .
1'
b1000 *
#10
0'
b1001 *
#11
b100100 &
b100100 ,
b100100 -
b1000000 %
b1000000 +
b1000000 .
1'
b1010 *
#12
0'
b1011 *
#13
b11000 &
b11000 ,
b11000 -
b10000000 %
b10000000 +
b10000000 .
1'
b1100 *
#14
0'
b1101 *
#15
b1100110 &
b1100110 ,
b1100110 -
b1 %
b1 +
b1 .
1'
b1110 *
#16
0'
b1111 *
#17
b10011001 &
b10011001 ,
b10011001 -
b10 %
b10 +
b10 .
1'
b10000 *
#18
0'
b10001 *
#19
b10000001 &
b10000001 ,
b10000001 -
b100 %
b100 +
b100 .
1'
b10010 *
#20
0'
b10011 *
#21
b1000 %
b1000 +
b1000 .
1'
b10100 *
#22
0'
b10101 *
#23
b10000 %
b10000 +
b10000 .
1'
b10110 *
#24
0'
b10111 *
#25
b1000010 &
b1000010 ,
b1000010 -
b100000 %
b100000 +
b100000 .
1'
b11000 *
#26
0'
b11001 *
#27
b100100 &
b100100 ,
b100100 -
b1000000 %
b1000000 +
b1000000 .
1'
b11010 *
#28
0'
b11011 *
#29
b11000 &
b11000 ,
b11000 -
b10000000 %
b10000000 +
b10000000 .
1'
b11100 *
#30
0'
b11101 *
#31
b1100110 &
b1100110 ,
b1100110 -
b1 %
b1 +
b1 .
1'
b11110 *
#32
0'
b11111 *
#33
b10011001 &
b10011001 ,
b10011001 -
b10 %
b10 +
b10 .
1'
b100000 *
#34
0'
b100001 *
#35
b10000001 &
b10000001 ,
b10000001 -
b100 %
b100 +
b100 .
1'
b100010 *
#36
0'
b100011 *
#37
b1000 %
b1000 +
b1000 .
1'
b100100 *
#38
0'
b100101 *
#39
b10000 %
b10000 +
b10000 .
1'
b100110 *
#40
0'
b100111 *
#41
b1000010 &
b1000010 ,
b1000010 -
b100000 %
b100000 +
b100000 .
1'
b101000 *
#42
0'
b101001 *
#43
b100100 &
b100100 ,
b100100 -
b1000000 %
b1000000 +
b1000000 .
1'
b101010 *
#44
0'
b101011 *
#45
b11000 &
b11000 ,
b11000 -
b10000000 %
b10000000 +
b10000000 .
1'
b101100 *
#46
0'
b101101 *
#47
b1100110 &
b1100110 ,
b1100110 -
b1 %
b1 +
b1 .
1'
b101110 *
#48
0'
b101111 *
#49
b10011001 &
b10011001 ,
b10011001 -
b10 %
b10 +
b10 .
1'
b110000 *
#50
0'
b110001 *
#51
b10000001 &
b10000001 ,
b10000001 -
b100 %
b100 +
b100 .
1'
b110010 *
#52
0'
b110011 *
#53
b1000 %
b1000 +
b1000 .
1'
b110100 *
#54
0'
b110101 *
#55
b10000 %
b10000 +
b10000 .
1'
b110110 *
#56
0'
b110111 *
#57
b1000010 &
b1000010 ,
b1000010 -
b100000 %
b100000 +
b100000 .
1'
b111000 *
#58
0'
b111001 *
#59
b100100 &
b100100 ,
b100100 -
b1000000 %
b1000000 +
b1000000 .
1'
b111010 *
#60
0'
b111011 *
#61
b11000 &
b11000 ,
b11000 -
b10000000 %
b10000000 +
b10000000 .
1'
b111100 *
#62
0'
b111101 *
#63
b1100110 &
b1100110 ,
b1100110 -
b1 %
b1 +
b1 .
1'
b111110 *
#64
0'
b111111 *
#65
b10011001 &
b10011001 ,
b10011001 -
b10 %
b10 +
b10 .
1'
b1000000 *
#66
0'
b1000001 *
#67
b10000001 &
b10000001 ,
b10000001 -
b100 %
b100 +
b100 .
1'
b1000010 *
#68
0'
b1000011 *
#69
b1000 %
b1000 +
b1000 .
1'
b1000100 *
#70
0'
b1000101 *
#71
b10000 %
b10000 +
b10000 .
1'
b1000110 *
#72
0'
b1000111 *
#73
b1000010 &
b1000010 ,
b1000010 -
b100000 %
b100000 +
b100000 .
1'
b1001000 *
#74
0'
b1001001 *
#75
b100100 &
b100100 ,
b100100 -
b1000000 %
b1000000 +
b1000000 .
1'
b1001010 *
#76
0'
b1001011 *
#77
b11000 &
b11000 ,
b11000 -
b10000000 %
b10000000 +
b10000000 .
1'
b1001100 *
#78
0'
b1001101 *
#79
b1100110 &
b1100110 ,
b1100110 -
b1 %
b1 +
b1 .
1'
b1001110 *
#80
0'
b1001111 *
#81
b10011001 &
b10011001 ,
b10011001 -
b10 %
b10 +
b10 .
1'
b1010000 *
#82
0'
b1010001 *
#83
b10000001 &
b10000001 ,
b10000001 -
b100 %
b100 +
b100 .
1'
b1010010 *
#84
0'
b1010011 *
#85
b1000 %
b1000 +
b1000 .
1'
b1010100 *
#86
0'
b1010101 *
#87
b10000 %
b10000 +
b10000 .
1'
b1010110 *
#88
0'
b1010111 *
#89
b1000010 &
b1000010 ,
b1000010 -
b100000 %
b100000 +
b100000 .
1'
b1011000 *
#90
0'
b1011001 *
#91
b100100 &
b100100 ,
b100100 -
b1000000 %
b1000000 +
b1000000 .
1'
b1011010 *
#92
0'
b1011011 *
#93
b11000 &
b11000 ,
b11000 -
b10000000 %
b10000000 +
b10000000 .
1'
b1011100 *
#94
0'
b1011101 *
#95
b1100110 &
b1100110 ,
b1100110 -
b1 %
b1 +
b1 .
1'
b1011110 *
#96
0'
b1011111 *
#97
b10011001 &
b10011001 ,
b10011001 -
b10 %
b10 +
b10 .
1'
b1100000 *
#98
0'
b1100001 *
#99
b10000001 &
b10000001 ,
b10000001 -
b100 %
b100 +
b100 .
1'
b1100010 *
#100
0'
b1100011 *
#101
b1000 %
b1000 +
b1000 .
b10010001 &
b10010001 ,
b10010001 -
1'
1)
b0 *
#102
0'
b1 *
#103
b10001001 &
b10001001 ,
b10001001 -
b10000 %
b10000 +
b10000 .
1'
b10 *
#104
0'
b11 *
#105
b1010010 &
b1010010 ,
b1010010 -
b100000 %
b100000 +
b100000 .
1'
b100 *
#106
0'
b101 *
#107
b100100 &
b100100 ,
b100100 -
b1000000 %
b1000000 +
b1000000 .
1'
b110 *
#108
0'
b111 *
#109
b11000 &
b11000 ,
b11000 -
b10000000 %
b10000000 +
b10000000 .
1'
b1000 *
#110
0'
b1001 *
#111
b1100110 &
b1100110 ,
b1100110 -
b1 %
b1 +
b1 .
1'
b1010 *
#112
0'
b1011 *
#113
b10011001 &
b10011001 ,
b10011001 -
b10 %
b10 +
b10 .
1'
b1100 *
#114
0'
b1101 *
#115
b10001001 &
b10001001 ,
b10001001 -
b100 %
b100 +
b100 .
1'
b1110 *
#116
0'
b1111 *
#117
b10010001 &
b10010001 ,
b10010001 -
b1000 %
b1000 +
b1000 .
1'
b10000 *
#118
0'
b10001 *
#119
b10001001 &
b10001001 ,
b10001001 -
b10000 %
b10000 +
b10000 .
1'
b10010 *
#120
0'
b10011 *
#121
b1010010 &
b1010010 ,
b1010010 -
b100000 %
b100000 +
b100000 .
1'
b10100 *
#122
0'
b10101 *
#123
b100100 &
b100100 ,
b100100 -
b1000000 %
b1000000 +
b1000000 .
1'
b10110 *
#124
0'
b10111 *
#125
b11000 &
b11000 ,
b11000 -
b10000000 %
b10000000 +
b10000000 .
1'
b11000 *
#126
0'
b11001 *
#127
b1100110 &
b1100110 ,
b1100110 -
b1 %
b1 +
b1 .
1'
b11010 *
#128
0'
b11011 *
#129
b10011001 &
b10011001 ,
b10011001 -
b10 %
b10 +
b10 .
1'
b11100 *
#130
0'
b11101 *
#131
b10001001 &
b10001001 ,
b10001001 -
b100 %
b100 +
b100 .
1'
b11110 *
#132
0'
b11111 *
#133
b10010001 &
b10010001 ,
b10010001 -
b1000 %
b1000 +
b1000 .
1'
b100000 *
#134
0'
b100001 *
#135
b10001001 &
b10001001 ,
b10001001 -
b10000 %
b10000 +
b10000 .
1'
b100010 *
#136
0'
b100011 *
#137
b1010010 &
b1010010 ,
b1010010 -
b100000 %
b100000 +
b100000 .
1'
b100100 *
#138
0'
b100101 *
#139
b100100 &
b100100 ,
b100100 -
b1000000 %
b1000000 +
b1000000 .
1'
b100110 *
#140
0'
b100111 *
#141
b11000 &
b11000 ,
b11000 -
b10000000 %
b10000000 +
b10000000 .
1'
b101000 *
#142
0'
b101001 *
#143
b1100110 &
b1100110 ,
b1100110 -
b1 %
b1 +
b1 .
1'
b101010 *
#144
0'
b101011 *
#145
b10011001 &
b10011001 ,
b10011001 -
b10 %
b10 +
b10 .
1'
b101100 *
#146
0'
b101101 *
#147
b10001001 &
b10001001 ,
b10001001 -
b100 %
b100 +
b100 .
1'
b101110 *
#148
0'
b101111 *
#149
b10010001 &
b10010001 ,
b10010001 -
b1000 %
b1000 +
b1000 .
1'
b110000 *
#150
0'
b110001 *
#151
b10001001 &
b10001001 ,
b10001001 -
b10000 %
b10000 +
b10000 .
1'
b110010 *
#152
0'
b110011 *
#153
b1010010 &
b1010010 ,
b1010010 -
b100000 %
b100000 +
b100000 .
1'
b110100 *
#154
0'
b110101 *
#155
b100100 &
b100100 ,
b100100 -
b1000000 %
b1000000 +
b1000000 .
1'
b110110 *
#156
0'
b110111 *
#157
b11000 &
b11000 ,
b11000 -
b10000000 %
b10000000 +
b10000000 .
1'
b111000 *
#158
0'
b111001 *
#159
b1100110 &
b1100110 ,
b1100110 -
b1 %
b1 +
b1 .
1'
b111010 *
#160
0'
b111011 *
#161
b10011001 &
b10011001 ,
b10011001 -
b10 %
b10 +
b10 .
1'
b111100 *
#162
0'
b111101 *
#163
b10001001 &
b10001001 ,
b10001001 -
b100 %
b100 +
b100 .
1'
b111110 *
#164
0'
b111111 *
#165
b10010001 &
b10010001 ,
b10010001 -
b1000 %
b1000 +
b1000 .
1'
b1000000 *
#166
0'
b1000001 *
#167
b10001001 &
b10001001 ,
b10001001 -
b10000 %
b10000 +
b10000 .
1'
b1000010 *
#168
0'
b1000011 *
#169
b1010010 &
b1010010 ,
b1010010 -
b100000 %
b100000 +
b100000 .
1'
b1000100 *
#170
0'
b1000101 *
#171
b100100 &
b100100 ,
b100100 -
b1000000 %
b1000000 +
b1000000 .
1'
b1000110 *
#172
0'
b1000111 *
#173
b11000 &
b11000 ,
b11000 -
b10000000 %
b10000000 +
b10000000 .
1'
b1001000 *
#174
0'
b1001001 *
#175
b1100110 &
b1100110 ,
b1100110 -
b1 %
b1 +
b1 .
1'
b1001010 *
#176
0'
b1001011 *
#177
b10011001 &
b10011001 ,
b10011001 -
b10 %
b10 +
b10 .
1'
b1001100 *
#178
0'
b1001101 *
#179
b10001001 &
b10001001 ,
b10001001 -
b100 %
b100 +
b100 .
1'
b1001110 *
#180
0'
b1001111 *
#181
b10010001 &
b10010001 ,
b10010001 -
b1000 %
b1000 +
b1000 .
1'
b1010000 *
#182
0'
b1010001 *
#183
b10001001 &
b10001001 ,
b10001001 -
b10000 %
b10000 +
b10000 .
1'
b1010010 *
#184
0'
b1010011 *
#185
b1010010 &
b1010010 ,
b1010010 -
b100000 %
b100000 +
b100000 .
1'
b1010100 *
#186
0'
b1010101 *
#187
b100100 &
b100100 ,
b100100 -
b1000000 %
b1000000 +
b1000000 .
1'
b1010110 *
#188
0'
b1010111 *
#189
b11000 &
b11000 ,
b11000 -
b10000000 %
b10000000 +
b10000000 .
1'
b1011000 *
#190
0'
b1011001 *
#191
b1100110 &
b1100110 ,
b1100110 -
b1 %
b1 +
b1 .
1'
b1011010 *
#192
0'
b1011011 *
#193
b10011001 &
b10011001 ,
b10011001 -
b10 %
b10 +
b10 .
1'
b1011100 *
#194
0'
b1011101 *
#195
b10001001 &
b10001001 ,
b10001001 -
b100 %
b100 +
b100 .
1'
b1011110 *
#196
0'
b1011111 *
#197
b10010001 &
b10010001 ,
b10010001 -
b1000 %
b1000 +
b1000 .
1'
b1100000 *
#198
0'
b1100001 *
#199
b10001001 &
b10001001 ,
b10001001 -
b10000 %
b10000 +
b10000 .
1'
b1100010 *
#200
0'
b1100011 *
#201
b1100100 *
