Report4/Lab4-1/SemiAdder.v
module SemiAdder(in0, in1, sum, carry);
	input in0, in1;
	output sum, carry;
	
	assign sum=in0^in1;
	assign carry=in0*in1;

endmodule

Report4/Lab4-1/FullAdder.v
module FullAdder(in, sum, carry);
	
	input [2:0]in;
	output sum, carry;
	
	wire carry0, carry1, sum0;
	
	SemiAdder SA0(in[0], in[1], sum0, carry0);
	SemiAdder SA1(in[2], sum0, sum, carry1);
	assign carry=carry0+carry1;
	
endmodule

Report4/Lab4-1/Test_FullAdder.v


////////////////////////////////////////////////////////////////////////////////
// Company: 
// Engineer:
//
// Create Date:   13:10:35 04/11/2018
// Design Name:   FullAdder
// Module Name:   C:/Users/10310/Desktop/Logic_Design/Report4/Lab4-1/Test_FullAdder.v
// Project Name:  Lab4-1
// Target Device:  
// Tool versions:  
// Description: 
//
// Verilog Test Fixture created by ISE for module: FullAdder
//
// Dependencies:
// 
// Revision:
// Revision 0.01 - File Created
// Additional Comments:
// 
////////////////////////////////////////////////////////////////////////////////

module Test_FullAdder;

	// Inputs
	reg [2:0] in;

	// Outputs
	wire sum;
	wire carry;

	// Instantiate the Unit Under Test (UUT)
	FullAdder uut (
		.in(in), 
		.sum(sum), 
		.carry(carry)
	);

	initial begin
		for(in=3'd0; in<7; in=in+1)begin
			#1;
		end
		#1;
	end
      
	initial begin
		$monitor($time, "in0=%b, in1=%b, in2=%b, sum=%b, carry=%b", in[0], in[1], in[2], sum, carry);
	end
	
	initial begin
		$dumpfile("test_fulladder.vcd");
		$dumpvars;
	end
		
endmodule

Report4/Lab4-1/test_fulladder.vcd
$date
	Wed Apr 11 13:29:11 2018
$end
$version
	Icarus Verilog
$end
$timescale
	1s
$end
$scope module Test_FullAdder $end
$var wire 1 ! sum $end
$var wire 1 " carry $end
$var reg 3 # in [2:0] $end
$scope module uut $end
$var wire 3 $ in [2:0] $end
$var wire 1 % sum0 $end
$var wire 1 ! sum $end
$var wire 1 & carry1 $end
$var wire 1 ' carry0 $end
$var wire 1 " carry $end
$scope module SA0 $end
$var wire 1 ( in0 $end
$var wire 1 ) in1 $end
$var wire 1 % sum $end
$var wire 1 ' carry $end
$upscope $end
$scope module SA1 $end
$var wire 1 * in0 $end
$var wire 1 % in1 $end
$var wire 1 ! sum $end
$var wire 1 & carry $end
$upscope $end
$upscope $end
$upscope $end
$enddefinitions $end
#0
$dumpvars
0*
0)
0(
0'
0&
0%
b0 $
b0 #
0"
0!
$end
#1
1!
1%
1(
b1 #
b1 $
#2
0(
0"
0'
1)
b10 #
b10 $
#3
0!
0%
1"
1'
1(
b11 #
b11 $
#4
1!
0(
0"
0'
0)
1*
b100 #
b100 $
#5
0!
1"
1&
1%
1(
b101 #
b101 $
#6
0(
1"
0'
1)
b110 #
b110 $
#7
1!
0&
0%
1"
1'
1(
b111 #
b111 $
