Report6/Ex3/fourBitBCD.v
module fourBitBCD(in, out);
	input [3:0]in;
	
	output[6:0]out;
	reg[6:0]out;
	
	always@(*)begin
		case(in)
			4'b0000:out=7'b0111111;
			4'b0001:out=7'b0000110;
			4'b0010:out=7'b1011011;
			4'b0011:out=7'b1001111;
			4'b0100:out=7'b1100110;
			4'b0101:out=7'b1101101;
			4'b0110:out=7'b1111101;
			4'b0111:out=7'b0000111;
			4'b1000:out=7'b1111111;
			4'b1001:out=7'b1101111;
			4'b1010:out=7'b1110111;
			4'b1011:out=7'b1111100;
			4'b1100:out=7'b0111001;
			4'b1101:out=7'b1011110;
			4'b1110:out=7'b1110001;
			4'b1111:out=7'b0000000;
			default:out=7'b0000000;
		endcase		
	end	
endmodule

Report6/Ex3/binToBCD.v
module binToBCD(in, outA, outB);
	input [3:0]in;
	
	output[3:0]outA, outB;
	reg[3:0]outA, outB;
	
	always@(*)begin
		if(in>4'b1001)begin
			outA=1;
			outB=in-'d10;
		end
		else begin
			outA=0;
			outB=in;
		end
	end	
	
endmodule

Report6/Ex3/absVal.v
module absVal(in, out);
	input [4:0]in;
	
	output[3:0]out;
	reg[3:0]out;
	
	always@(*)begin
		if(in[4]==1'b1)out=(~in[3:0])+1;
		else out=in[3:0];
	end
endmodule

Report6/Ex3/fiveBitALU.v
module fiveBitALU(inA, inB, sel, out);
	input [4:0]inA, inB;
	input [2:0]sel;
	
	output[4:0]out;
	reg	  [4:0]out;

	parameter   ADD=3'b000,
				SUB=3'b001,
				AND=3'b010,
				OR =3'b011,
				XOR=3'b100,
				SHR=3'b101,
				SHL=3'b110,
				CMP=3'b111;
	
	always@(*)begin
		case(sel)
			ADD:out=inA+inB;
			SUB:out=inA-inB;
			AND:out=inA&inB;
			OR :out=inA|inB;
			XOR:out=inA^inB;
			SHR:out=inA>>inB;
			SHL:out=inA<<inB;
			CMP:out=inA>inB;
			default:out=5'b0;
		endcase
	end	
endmodule

Report6/Ex3/system.v
module system(clk, inA, inB, sel, SevenSegA, SevenSegB, SevenSegOne, SevenSegTen, signal);
	
	input clk;
	input[4:0] inA, inB;
	input[2:0] sel;
	
	output[6:0]SevenSegA, SevenSegB, SevenSegOne, SevenSegTen;
	output signal;
	
	wire [4:0]ALUOut0;
	wire [3:0]absValOut0, BCDOutA, BCDOutB;
	
	fourBitBCD SS0(.in(inA[3:0]), .out(SevenSegA));
	fourBitBCD SS1(.in(inB[3:0]), .out(SevenSegB));
	
	fiveBitALU ALU0(.inA(inA), .inB(inB), .sel(sel), .out(ALUOut0));
	
	absVal ABS0(.in(ALUOut0), .out(absValOut0));
	
	assign signal=ALUOut0[4];
	
	binToBCD BTB0(.in(absValOut0), .outA(BCDOutA), .outB(BCDOutB));
	
	fourBitBCD SS2(.in(BCDOutA), .out(SevenSegA));
	fourBitBCD SS3(.in(BCDOutB), .out(SevenSegB));

endmodule

Report6/Ex3/testSystem.v
module testSystem;
	reg [4:0]inA, inB;
	reg [2:0]sel;
	
	wire[6:0]SevenSegA, SevenSegB, SevenSegOne, SevenSegTen;
	wire signal;
	
	integer A, B;
	
	system s0(.inA(inA), .inB(inB), .sel(sel), .SevenSegA(SevenSegA), .SevenSegB(SevenSegB), .SevenSegOne(SevenSegOne), .SevenSegTen(SevenSegTen), .signal(signal));
	
	initial begin
		for(A=0; A<16; A=A+1)begin
			for(B=0; B<16; B=B+1)begin
				inA=A; inB=B; sel=0;
				#1 inA=A; inB=B; sel=1;
				#1;
			end
		end
	end
	
	initial begin
		$monitor("A:%d, AS:%b, B:%d, BS:%b, neg:%b, Ten:%b, One:%b", inA, SevenSegA, inB, SevenSegB, signal, SevenSegTen, SevenSegTen);
	end
	
	initial begin
		$dumpfile("testSystem.vcd");
		$dumpvars;
	end
	
endmodule

Report6/Ex3/testSystem.vcd
$date
	Wed Apr 25 13:14:03 2018
$end
$version
	Icarus Verilog
$end
$timescale
	1s
$end
$scope module testSystem $end
$var wire 7 ! SevenSegA [6:0] $end
$var wire 7 " SevenSegB [6:0] $end
$var wire 7 # SevenSegOne [6:0] $end
$var wire 7 $ SevenSegTen [6:0] $end
$var wire 1 % signal $end
$var reg 5 & inA [4:0] $end
$var reg 5 ' inB [4:0] $end
$var reg 3 ( sel [2:0] $end
$var integer 32 ) A [31:0] $end
$var integer 32 * B [31:0] $end
$scope module s0 $end
$var wire 7 + SevenSegA [6:0] $end
$var wire 7 , SevenSegB [6:0] $end
$var wire 7 - SevenSegOne [6:0] $end
$var wire 7 . SevenSegTen [6:0] $end
$var wire 1 / clk $end
$var wire 5 0 inA [4:0] $end
$var wire 5 1 inB [4:0] $end
$var wire 3 2 sel [2:0] $end
$var wire 1 % signal $end
$var wire 4 3 absValOut0 [3:0] $end
$var wire 4 4 BCDOutB [3:0] $end
$var wire 4 5 BCDOutA [3:0] $end
$var wire 5 6 ALUOut0 [4:0] $end
$scope module ABS0 $end
$var wire 5 7 in [4:0] $end
$var reg 4 8 out [3:0] $end
$upscope $end
$scope module ALU0 $end
$var wire 5 9 inA [4:0] $end
$var wire 5 : inB [4:0] $end
$var wire 3 ; sel [2:0] $end
$var reg 5 < out [4:0] $end
$upscope $end
$scope module BTB0 $end
$var wire 4 = in [3:0] $end
$var reg 4 > outA [3:0] $end
$var reg 4 ? outB [3:0] $end
$upscope $end
$scope module SS0 $end
$var wire 4 @ in [3:0] $end
$var reg 7 A out [6:0] $end
$upscope $end
$scope module SS1 $end
$var wire 4 B in [3:0] $end
$var reg 7 C out [6:0] $end
$upscope $end
$scope module SS2 $end
$var wire 4 D in [3:0] $end
$var reg 7 E out [6:0] $end
$upscope $end
$scope module SS3 $end
$var wire 4 F in [3:0] $end
$var reg 7 G out [6:0] $end
$upscope $end
$upscope $end
$upscope $end
$enddefinitions $end
#0
$dumpvars
b111111 G
b0 F
b111111 E
b0 D
b111111 C
b0 B
b111111 A
b0 @
b0 ?
b0 >
b0 =
b0 <
b0 ;
b0 :
b0 9
b0 8
b0 7
b0 6
b0 5
b0 4
b0 3
b0 2
b0 1
b0 0
z/
bz .
bz -
b111111 ,
b111111 +
b0 *
b0 )
b0 (
b0 '
b0 &
0%
bz $
bz #
b111111 "
b111111 !
$end
#1
b1 (
b1 2
b1 ;
#2
b110 G
b1 4
b1 ?
b1 F
b110 "
b110 ,
b110 C
b1 3
b1 8
b1 =
b1 B
b1 6
b1 7
b1 <
b0 (
b0 2
b0 ;
b1 '
b1 1
b1 :
b1 *
#3
1%
b11111 6
b11111 7
b11111 <
b1 (
b1 2
b1 ;
#4
b1011011 G
b10 4
b10 ?
b10 F
b1011011 "
b1011011 ,
b1011011 C
0%
b10 3
b10 8
b10 =
b10 B
b10 6
b10 7
b10 <
b0 (
b0 2
b0 ;
b10 '
b10 1
b10 :
b10 *
#5
1%
b11110 6
b11110 7
b11110 <
b1 (
b1 2
b1 ;
#6
b1001111 G
b11 4
b11 ?
b11 F
b1001111 "
b1001111 ,
b1001111 C
0%
b11 3
b11 8
b11 =
b11 B
b11 6
b11 7
b11 <
b0 (
b0 2
b0 ;
b11 '
b11 1
b11 :
b11 *
#7
1%
b11101 6
b11101 7
b11101 <
b1 (
b1 2
b1 ;
#8
b1100110 G
b100 4
b100 ?
b100 F
b1100110 "
b1100110 ,
b1100110 C
0%
b100 3
b100 8
b100 =
b100 B
b100 6
b100 7
b100 <
b0 (
b0 2
b0 ;
b100 '
b100 1
b100 :
b100 *
#9
1%
b11100 6
b11100 7
b11100 <
b1 (
b1 2
b1 ;
#10
b1101101 G
b101 4
b101 ?
b101 F
b1101101 "
b1101101 ,
b1101101 C
0%
b101 3
b101 8
b101 =
b101 B
b101 6
b101 7
b101 <
b0 (
b0 2
b0 ;
b101 '
b101 1
b101 :
b101 *
#11
1%
b11011 6
b11011 7
b11011 <
b1 (
b1 2
b1 ;
#12
b1111101 G
b110 4
b110 ?
b110 F
b1111101 "
b1111101 ,
b1111101 C
0%
b110 3
b110 8
b110 =
b110 B
b110 6
b110 7
b110 <
b0 (
b0 2
b0 ;
b110 '
b110 1
b110 :
b110 *
#13
1%
b11010 6
b11010 7
b11010 <
b1 (
b1 2
b1 ;
#14
b111 G
b111 4
b111 ?
b111 F
b111 "
b111 ,
b111 C
0%
b111 3
b111 8
b111 =
b111 B
b111 6
b111 7
b111 <
b0 (
b0 2
b0 ;
b111 '
b111 1
b111 :
b111 *
#15
1%
b11001 6
b11001 7
b11001 <
b1 (
b1 2
b1 ;
#16
b1111111 G
b1000 4
b1000 ?
b1000 F
b1111111 "
b1111111 ,
b1111111 C
0%
b1000 3
b1000 8
b1000 =
b1000 B
b1000 6
b1000 7
b1000 <
b0 (
b0 2
b0 ;
b1000 '
b1000 1
b1000 :
b1000 *
#17
1%
b11000 6
b11000 7
b11000 <
b1 (
b1 2
b1 ;
#18
b1101111 G
b1001 4
b1001 ?
b1001 F
b1101111 "
b1101111 ,
b1101111 C
0%
b1001 3
b1001 8
b1001 =
b1001 B
b1001 6
b1001 7
b1001 <
b0 (
b0 2
b0 ;
b1001 '
b1001 1
b1001 :
b1001 *
#19
1%
b10111 6
b10111 7
b10111 <
b1 (
b1 2
b1 ;
#20
b111111 G
b0xxx11x !
b0xxx11x +
b110 E
b0 4
b0 ?
b0 F
b1 5
b1 >
b1 D
bx11x111 "
bx11x111 ,
b1110111 C
0%
b1010 3
b1010 8
b1010 =
b1010 B
b1010 6
b1010 7
b1010 <
b0 (
b0 2
b0 ;
b1010 '
b1010 1
b1010 :
b1010 *
#21
1%
b10110 6
b10110 7
b10110 <
b1 (
b1 2
b1 ;
#22
b110 G
b1 4
b1 ?
b1 F
bx1x0 "
bx1x0 ,
b1111100 C
0%
b1011 3
b1011 8
b1011 =
b1011 B
b1011 6
b1011 7
b1011 <
b0 (
b0 2
b0 ;
b1011 '
b1011 1
b1011 :
b1011 *
#23
1%
b10101 6
b10101 7
b10101 <
b1 (
b1 2
b1 ;
#24
b1011011 G
b10 4
b10 ?
b10 F
bx110x1 "
bx110x1 ,
b111001 C
0%
b1100 3
b1100 8
b1100 =
b1100 B
b1100 6
b1100 7
b1100 <
b0 (
b0 2
b0 ;
b1100 '
b1100 1
b1100 :
b1100 *
#25
1%
b10100 6
b10100 7
b10100 <
b1 (
b1 2
b1 ;
#26
b1001111 G
b11 4
b11 ?
b11 F
b10x111x "
b10x111x ,
b1011110 C
0%
b1101 3
b1101 8
b1101 =
b1101 B
b1101 6
b1101 7
b1101 <
b0 (
b0 2
b0 ;
b1101 '
b1101 1
b1101 :
b1101 *
#27
1%
b10011 6
b10011 7
b10011 <
b1 (
b1 2
b1 ;
#28
b1100110 G
b100 4
b100 ?
b100 F
b11x0xxx "
b11x0xxx ,
b1110001 C
0%
b1110 3
b1110 8
b1110 =
b1110 B
b1110 6
b1110 7
b1110 <
b0 (
b0 2
b0 ;
b1110 '
b1110 1
b1110 :
b1110 *
#29
1%
b10010 6
b10010 7
b10010 <
b1 (
b1 2
b1 ;
#30
b1101101 G
b101 4
b101 ?
b101 F
bx0xx0x "
bx0xx0x ,
b0 C
0%
b1111 3
b1111 8
b1111 =
b1111 B
b1111 6
b1111 7
b1111 <
b0 (
b0 2
b0 ;
b1111 '
b1111 1
b1111 :
b1111 *
#31
1%
b10001 6
b10001 7
b10001 <
b1 (
b1 2
b1 ;
#32
b110 G
b111111 E
b1 4
b1 ?
b1 F
b0 5
b0 >
b0 D
b0xxx11x "
b0xxx11x ,
b111111 C
b0xxx11x !
b0xxx11x +
b110 A
0%
b1 3
b1 8
b1 =
b0 B
b1 @
b1 6
b1 7
b1 <
b0 (
b0 2
b0 ;
b0 '
b0 1
b0 :
b1 &
b1 0
b1 9
b1 )
b0 *
#33
b1 (
b1 2
b1 ;
#34
b1011011 G
b10 4
b10 ?
b10 F
bx0xxx1x "
bx0xxx1x ,
b110 C
b10 3
b10 8
b10 =
b1 B
b10 6
b10 7
b10 <
b0 (
b0 2
b0 ;
b1 '
b1 1
b1 :
b1 *
#35
b0xxx11x "
b0xxx11x ,
b111111 G
b0 4
b0 ?
b0 F
b0 3
b0 8
b0 =
b0 6
b0 7
b0 <
b1 (
b1 2
b1 ;
#36
b1001111 G
b11 4
b11 ?
b11 F
b10x1x11 "
b10x1x11 ,
b1011011 C
b11 3
b11 8
b11 =
b10 B
b11 6
b11 7
b11 <
b0 (
b0 2
b0 ;
b10 '
b10 1
b10 :
b10 *
#37
bx0xxx1x "
bx0xxx1x ,
b110 G
b1 4
b1 ?
b1 F
1%
b1 3
b1 8
b1 =
b11111 6
b11111 7
b11111 <
b1 (
b1 2
b1 ;
#38
b1100110 G
b100 4
b100 ?
b100 F
b1x0x11x "
b1x0x11x ,
b1001111 C
0%
b100 3
b100 8
b100 =
b11 B
b100 6
b100 7
b100 <
b0 (
b0 2
b0 ;
b11 '
b11 1
b11 :
b11 *
#39
b10x1x11 "
b10x1x11 ,
b1011011 G
b10 4
b10 ?
b10 F
1%
b10 3
b10 8
b10 =
b11110 6
b11110 7
b11110 <
b1 (
b1 2
b1 ;
#40
b1101101 G
b101 4
b101 ?
b101 F
b110x1xx "
b110x1xx ,
b1100110 C
0%
b101 3
b101 8
b101 =
b100 B
b101 6
b101 7
b101 <
b0 (
b0 2
b0 ;
b100 '
b100 1
b100 :
b100 *
#41
b1x0x11x "
b1x0x11x ,
b1001111 G
b11 4
b11 ?
b11 F
1%
b11 3
b11 8
b11 =
b11101 6
b11101 7
b11101 <
b1 (
b1 2
b1 ;
#42
b1111101 G
b110 4
b110 ?
b110 F
b11x1101 "
b11x1101 ,
b1101101 C
0%
b110 3
b110 8
b110 =
b101 B
b110 6
b110 7
b110 <
b0 (
b0 2
b0 ;
b101 '
b101 1
b101 :
b101 *
#43
b110x1xx "
b110x1xx ,
b1100110 G
b100 4
b100 ?
b100 F
1%
b100 3
b100 8
b100 =
b11100 6
b11100 7
b11100 <
b1 (
b1 2
b1 ;
#44
b111 G
b111 4
b111 ?
b111 F
bx1x1 "
bx1x1 ,
b1111101 C
0%
b111 3
b111 8
b111 =
b110 B
b111 6
b111 7
b111 <
b0 (
b0 2
b0 ;
b110 '
b110 1
b110 :
b110 *
#45
b11x1101 "
b11x1101 ,
b1101101 G
b101 4
b101 ?
b101 F
1%
b101 3
b101 8
b101 =
b11011 6
b11011 7
b11011 <
b1 (
b1 2
b1 ;
#46
b1111111 G
b1000 4
b1000 ?
b1000 F
bx111 "
bx111 ,
b111 C
0%
b1000 3
b1000 8
b1000 =
b111 B
b1000 6
b1000 7
b1000 <
b0 (
b0 2
b0 ;
b111 '
b111 1
b111 :
b111 *
#47
bx1x1 "
bx1x1 ,
b1111101 G
b110 4
b110 ?
b110 F
1%
b110 3
b110 8
b110 =
b11010 6
b11010 7
b11010 <
b1 (
b1 2
b1 ;
#48
b1101111 G
b1001 4
b1001 ?
b1001 F
b11x1111 "
b11x1111 ,
b1111111 C
0%
b1001 3
b1001 8
b1001 =
b1000 B
b1001 6
b1001 7
b1001 <
b0 (
b0 2
b0 ;
b1000 '
b1000 1
b1000 :
b1000 *
#49
bx111 "
bx111 ,
b111 G
b111 4
b111 ?
b111 F
1%
b111 3
b111 8
b111 =
b11001 6
b11001 7
b11001 <
b1 (
b1 2
b1 ;
#50
b111111 G
b110 !
b110 +
b110 E
b0 4
b0 ?
b0 F
b1 5
b1 >
b1 D
bx1x1111 "
bx1x1111 ,
b1101111 C
0%
b1010 3
b1010 8
b1010 =
b1001 B
b1010 6
b1010 7
b1010 <
b0 (
b0 2
b0 ;
b1001 '
b1001 1
b1001 :
b1001 *
#51
b11x1111 "
b11x1111 ,
b1111111 G
b0xxx11x !
b0xxx11x +
b111111 E
b1000 4
b1000 ?
b1000 F
b0 5
b0 >
b0 D
1%
b1000 3
b1000 8
b1000 =
b11000 6
b11000 7
b11000 <
b1 (
b1 2
b1 ;
#52
b110 G
b110 !
b110 +
b110 E
b1 4
b1 ?
b1 F
b1 5
b1 >
b1 D
bx011x "
bx011x ,
b1110111 C
0%
b1011 3
b1011 8
b1011 =
b1010 B
b1011 6
b1011 7
b1011 <
b0 (
b0 2
b0 ;
b1010 '
b1010 1
b1010 :
b1010 *
#53
b11xx111 "
b11xx111 ,
b1101111 G
b0xxx11x !
b0xxx11x +
b111111 E
b1001 4
b1001 ?
b1001 F
b0 5
b0 >
b0 D
1%
b1001 3
b1001 8
b1001 =
b10111 6
b10111 7
b10111 <
b1 (
b1 2
b1 ;
#54
b1011011 G
b110 !
b110 +
b110 E
b10 4
b10 ?
b10 F
b1 5
b1 >
b1 D
b1x11xxx "
b1x11xxx ,
b1111100 C
0%
b1100 3
b1100 8
b1100 =
b1011 B
b1100 6
b1100 7
b1100 <
b0 (
b0 2
b0 ;
b1011 '
b1011 1
b1011 :
b1011 *
#55
bx1111xx "
bx1111xx ,
b111111 G
b0 4
b0 ?
b0 F
1%
b1010 3
b1010 8
b1010 =
b10110 6
b10110 7
b10110 <
b1 (
b1 2
b1 ;
#56
b1001111 G
b11 4
b11 ?
b11 F
bx1xx1 "
bx1xx1 ,
b111001 C
0%
b1101 3
b1101 8
b1101 =
b1100 B
b1101 6
b1101 7
b1101 <
b0 (
b0 2
b0 ;
b1100 '
b1100 1
b1100 :
b1100 *
#57
b0xxxxxx "
b0xxxxxx ,
b110 G
b1 4
b1 ?
b1 F
1%
b1011 3
b1011 8
b1011 =
b10101 6
b10101 7
b10101 <
b1 (
b1 2
b1 ;
#58
b1100110 G
b100 4
b100 ?
b100 F
b1xxx110 "
b1xxx110 ,
b1011110 C
0%
b1110 3
b1110 8
b1110 =
b1101 B
b1110 6
b1110 7
b1110 <
b0 (
b0 2
b0 ;
b1101 '
b1101 1
b1101 :
b1101 *
#59
b1011x1x "
b1011x1x ,
b1011011 G
b10 4
b10 ?
b10 F
1%
b1100 3
b1100 8
b1100 =
b10100 6
b10100 7
b10100 <
b1 (
b1 2
b1 ;
#60
b1101101 G
b101 4
b101 ?
b101 F
b11xxx01 "
b11xxx01 ,
b1110001 C
0%
b1111 3
b1111 8
b1111 =
b1110 B
b1111 6
b1111 7
b1111 <
b0 (
b0 2
b0 ;
b1110 '
b1110 1
b1110 :
b1110 *
#61
b1xxxxx1 "
b1xxxxx1 ,
b1001111 G
b11 4
b11 ?
b11 F
1%
b1101 3
b1101 8
b1101 =
b10011 6
b10011 7
b10011 <
b1 (
b1 2
b1 ;
#62
b111111 G
b0xxx11x !
b0xxx11x +
b111111 E
b0 4
b0 ?
b0 F
b0 5
b0 >
b0 D
b0xxxxxx "
b0xxxxxx ,
b0 C
b0 3
b0 8
b0 =
b1111 B
b10000 6
b10000 7
b10000 <
b0 (
b0 2
b0 ;
b1111 '
b1111 1
b1111 :
b1111 *
#63
bx00xx0 "
bx00xx0 ,
b1100110 G
b110 !
b110 +
b110 E
b100 4
b100 ?
b100 F
b1 5
b1 >
b1 D
b1110 3
b1110 8
b1110 =
b10010 6
b10010 7
b10010 <
b1 (
b1 2
b1 ;
#64
b1011011 G
b111111 E
b10 4
b10 ?
b10 F
b0 5
b0 >
b0 D
bx11x11 "
bx11x11 ,
b111111 C
bx11x11 !
bx11x11 +
b1011011 A
0%
b10 3
b10 8
b10 =
b0 B
b10 @
b10 6
b10 7
b10 <
b0 (
b0 2
b0 ;
b0 '
b0 1
b0 :
b10 &
b10 0
b10 9
b10 )
b0 *
#65
b1 (
b1 2
b1 ;
#66
b1001111 G
b11 4
b11 ?
b11 F
bx00x11x "
bx00x11x ,
b110 C
b11 3
b11 8
b11 =
b1 B
b11 6
b11 7
b11 <
b0 (
b0 2
b0 ;
b1 '
b1 1
b1 :
b1 *
#67
b110 "
b110 ,
b110 G
b1 4
b1 ?
b1 F
b1 3
b1 8
b1 =
b1 6
b1 7
b1 <
b1 (
b1 2
b1 ;
#68
b1100110 G
b100 4
b100 ?
b100 F
b1xxxx1x "
b1xxxx1x ,
b1011011 C
b100 3
b100 8
b100 =
b10 B
b100 6
b100 7
b100 <
b0 (
b0 2
b0 ;
b10 '
b10 1
b10 :
b10 *
#69
bx11x11 "
bx11x11 ,
b111111 G
b0 4
b0 ?
b0 F
b0 3
b0 8
b0 =
b0 6
b0 7
b0 <
b1 (
b1 2
b1 ;
#70
b1101101 G
b101 4
b101 ?
b101 F
b1x011x1 "
b1x011x1 ,
b1001111 C
b101 3
b101 8
b101 =
b11 B
b101 6
b101 7
b101 <
b0 (
b0 2
b0 ;
b11 '
b11 1
b11 :
b11 *
#71
bx00x11x "
bx00x11x ,
b110 G
b1 4
b1 ?
b1 F
1%
b1 3
b1 8
b1 =
b11111 6
b11111 7
b11111 <
b1 (
b1 2
b1 ;
#72
b1111101 G
b110 4
b110 ?
b110 F
b11xx1xx "
b11xx1xx ,
b1100110 C
0%
b110 3
b110 8
b110 =
b100 B
b110 6
b110 7
b110 <
b0 (
b0 2
b0 ;
b100 '
b100 1
b100 :
b100 *
#73
b1xxxx1x "
b1xxxx1x ,
b1011011 G
b10 4
b10 ?
b10 F
1%
b10 3
b10 8
b10 =
b11110 6
b11110 7
b11110 <
b1 (
b1 2
b1 ;
#74
b111 G
b111 4
b111 ?
b111 F
bx0x1x1 "
bx0x1x1 ,
b1101101 C
0%
b111 3
b111 8
b111 =
b101 B
b111 6
b111 7
b111 <
b0 (
b0 2
b0 ;
b101 '
b101 1
b101 :
b101 *
#75
b1x011x1 "
b1x011x1 ,
b1001111 G
b11 4
b11 ?
b11 F
1%
b11 3
b11 8
b11 =
b11101 6
b11101 7
b11101 <
b1 (
b1 2
b1 ;
#76
b1111111 G
b1000 4
b1000 ?
b1000 F
b11111x1 "
b11111x1 ,
b1111101 C
0%
b1000 3
b1000 8
b1000 =
b110 B
b1000 6
b1000 7
b1000 <
b0 (
b0 2
b0 ;
b110 '
b110 1
b110 :
b110 *
#77
b11xx1xx "
b11xx1xx ,
b1100110 G
b100 4
b100 ?
b100 F
1%
b100 3
b100 8
b100 =
b11100 6
b11100 7
b11100 <
b1 (
b1 2
b1 ;
#78
b1101111 G
b1001 4
b1001 ?
b1001 F
bx0x111 "
bx0x111 ,
b111 C
0%
b1001 3
b1001 8
b1001 =
b111 B
b1001 6
b1001 7
b1001 <
b0 (
b0 2
b0 ;
b111 '
b111 1
b111 :
b111 *
#79
bx0x1x1 "
bx0x1x1 ,
b1101101 G
b101 4
b101 ?
b101 F
1%
b101 3
b101 8
b101 =
b11011 6
b11011 7
b11011 <
b1 (
b1 2
b1 ;
#80
b111111 G
bx0xxx1x !
bx0xxx1x +
b110 E
b0 4
b0 ?
b0 F
b1 5
b1 >
b1 D
bx111111 "
bx111111 ,
b1111111 C
0%
b1010 3
b1010 8
b1010 =
b1000 B
b1010 6
b1010 7
b1010 <
b0 (
b0 2
b0 ;
b1000 '
b1000 1
b1000 :
b1000 *
#81
b11111x1 "
b11111x1 ,
b1111101 G
bx11x11 !
bx11x11 +
b111111 E
b110 4
b110 ?
b110 F
b0 5
b0 >
b0 D
1%
b110 3
b110 8
b110 =
b11010 6
b11010 7
b11010 <
b1 (
b1 2
b1 ;
#82
b110 G
bx0xxx1x !
bx0xxx1x +
b110 E
b1 4
b1 ?
b1 F
b1 5
b1 >
b1 D
bx0x11x "
bx0x11x ,
b1101111 C
0%
b1011 3
b1011 8
b1011 =
b1001 B
b1011 6
b1011 7
b1011 <
b0 (
b0 2
b0 ;
b1001 '
b1001 1
b1001 :
b1001 *
#83
bx0x111 "
bx0x111 ,
b111 G
bx11x11 !
bx11x11 +
b111111 E
b111 4
b111 ?
b111 F
b0 5
b0 >
b0 D
1%
b111 3
b111 8
b111 =
b11001 6
b11001 7
b11001 <
b1 (
b1 2
b1 ;
#84
b1011011 G
bx0xxx1x !
bx0xxx1x +
b110 E
b10 4
b10 ?
b10 F
b1 5
b1 >
b1 D
b1x1xx11 "
b1x1xx11 ,
b1110111 C
0%
b1100 3
b1100 8
b1100 =
b1010 B
b1100 6
b1100 7
b1100 <
b0 (
b0 2
b0 ;
b1010 '
b1010 1
b1010 :
b1010 *
#85
b111x111 "
b111x111 ,
b1111111 G
bx11x11 !
bx11x11 +
b111111 E
b1000 4
b1000 ?
b1000 F
b0 5
b0 >
b0 D
1%
b1000 3
b1000 8
b1000 =
b11000 6
b11000 7
b11000 <
b1 (
b1 2
b1 ;
#86
b1001111 G
bx0xxx1x !
bx0xxx1x +
b110 E
b11 4
b11 ?
b11 F
b1 5
b1 >
b1 D
b1xx11xx "
b1xx11xx ,
b1111100 C
0%
b1101 3
b1101 8
b1101 =
b1011 B
b1101 6
b1101 7
b1101 <
b0 (
b0 2
b0 ;
b1011 '
b1011 1
b1011 :
b1011 *
#87
b11x11xx "
b11x11xx ,
b1101111 G
bx11x11 !
bx11x11 +
b111111 E
b1001 4
b1001 ?
b1001 F
b0 5
b0 >
b0 D
1%
b1001 3
b1001 8
b1001 =
b10111 6
b10111 7
b10111 <
b1 (
b1 2
b1 ;
#88
b1100110 G
bx0xxx1x !
bx0xxx1x +
b110 E
b100 4
b100 ?
b100 F
b1 5
b1 >
b1 D
bx1xxxxx "
bx1xxxxx ,
b111001 C
0%
b1110 3
b1110 8
b1110 =
b1100 B
b1110 6
b1110 7
b1110 <
b0 (
b0 2
b0 ;
b1100 '
b1100 1
b1100 :
b1100 *
#89
b111xx1 "
b111xx1 ,
b111111 G
b0 4
b0 ?
b0 F
1%
b1010 3
b1010 8
b1010 =
b10110 6
b10110 7
b10110 <
b1 (
b1 2
b1 ;
#90
b1101101 G
b101 4
b101 ?
b101 F
b1xx11xx "
b1xx11xx ,
b1011110 C
0%
b1111 3
b1111 8
b1111 =
b1101 B
b1111 6
b1111 7
b1111 <
b0 (
b0 2
b0 ;
b1101 '
b1101 1
b1101 :
b1101 *
#91
bx0xx110 "
bx0xx110 ,
b110 G
b1 4
b1 ?
b1 F
1%
b1011 3
b1011 8
b1011 =
b10101 6
b10101 7
b10101 <
b1 (
b1 2
b1 ;
#92
b111111 G
bx11x11 !
bx11x11 +
b111111 E
b0 4
b0 ?
b0 F
b0 5
b0 >
b0 D
bx11xxx1 "
bx11xxx1 ,
b1110001 C
b0 3
b0 8
b0 =
b1110 B
b10000 6
b10000 7
b10000 <
b0 (
b0 2
b0 ;
b1110 '
b1110 1
b1110 :
b1110 *
#93
b1x1x0x1 "
b1x1x0x1 ,
b1011011 G
bx0xxx1x !
bx0xxx1x +
b110 E
b10 4
b10 ?
b10 F
b1 5
b1 >
b1 D
b1100 3
b1100 8
b1100 =
b10100 6
b10100 7
b10100 <
b1 (
b1 2
b1 ;
#94
b1101101 G
b101 4
b101 ?
b101 F
bx0xx0x "
bx0xx0x ,
b0 C
b1111 3
b1111 8
b1111 =
b1111 B
b10001 6
b10001 7
b10001 <
b0 (
b0 2
b0 ;
b1111 '
b1111 1
b1111 :
b1111 *
#95
bx00xxxx "
bx00xxxx ,
b1001111 G
b11 4
b11 ?
b11 F
b1101 3
b1101 8
b1101 =
b10011 6
b10011 7
b10011 <
b1 (
b1 2
b1 ;
#96
b111111 E
b0 5
b0 >
b0 D
bx1111 "
bx1111 ,
b111111 C
bx1111 !
bx1111 +
b1001111 A
0%
b11 3
b11 8
b11 =
b0 B
b11 @
b11 6
b11 7
b11 <
b0 (
b0 2
b0 ;
b0 '
b0 1
b0 :
b11 &
b11 0
b11 9
b11 )
b0 *
#97
b1 (
b1 2
b1 ;
#98
b1100110 G
b100 4
b100 ?
b100 F
bx00110 "
bx00110 ,
b110 C
b100 3
b100 8
b100 =
b1 B
b100 6
b100 7
b100 <
b0 (
b0 2
b0 ;
b1 '
b1 1
b1 :
b1 *
#99
bx0xxx1x "
bx0xxx1x ,
b1011011 G
b10 4
b10 ?
b10 F
b10 3
b10 8
b10 =
b10 6
b10 7
b10 <
b1 (
b1 2
b1 ;
#100
b1101101 G
b101 4
b101 ?
b101 F
b1xx1xx1 "
b1xx1xx1 ,
b1011011 C
b101 3
b101 8
b101 =
b10 B
b101 6
b101 7
b101 <
b0 (
b0 2
b0 ;
b10 '
b10 1
b10 :
b10 *
#101
bx0xxx1x "
bx0xxx1x ,
b110 G
b1 4
b1 ?
b1 F
b1 3
b1 8
b1 =
b1 6
b1 7
b1 <
b1 (
b1 2
b1 ;
#102
b1111101 G
b110 4
b110 ?
b110 F
b1xx11x1 "
b1xx11x1 ,
b1001111 C
b110 3
b110 8
b110 =
b11 B
b110 6
b110 7
b110 <
b0 (
b0 2
b0 ;
b11 '
b11 1
b11 :
b11 *
#103
bx1111 "
bx1111 ,
b111111 G
b0 4
b0 ?
b0 F
b0 3
b0 8
b0 =
b0 6
b0 7
b0 <
b1 (
b1 2
b1 ;
#104
b111 G
b111 4
b111 ?
b111 F
bx0011x "
bx0011x ,
b1100110 C
b111 3
b111 8
b111 =
b100 B
b111 6
b111 7
b111 <
b0 (
b0 2
b0 ;
b100 '
b100 1
b100 :
b100 *
#105
bx00110 "
bx00110 ,
b110 G
b1 4
b1 ?
b1 F
1%
b1 3
b1 8
b1 =
b11111 6
b11111 7
b11111 <
b1 (
b1 2
b1 ;
#106
b1111111 G
b1000 4
b1000 ?
b1000 F
b11x11x1 "
b11x11x1 ,
b1101101 C
0%
b1000 3
b1000 8
b1000 =
b101 B
b1000 6
b1000 7
b1000 <
b0 (
b0 2
b0 ;
b101 '
b101 1
b101 :
b101 *
#107
b1xx1xx1 "
b1xx1xx1 ,
b1011011 G
b10 4
b10 ?
b10 F
1%
b10 3
b10 8
b10 =
b11110 6
b11110 7
b11110 <
b1 (
b1 2
b1 ;
#108
b1101111 G
b1001 4
b1001 ?
b1001 F
b11x11x1 "
b11x11x1 ,
b1111101 C
0%
b1001 3
b1001 8
b1001 =
b110 B
b1001 6
b1001 7
b1001 <
b0 (
b0 2
b0 ;
b110 '
b110 1
b110 :
b110 *
