Report8/Ex1/fsm.v
module fsm(clk, rst, in, out);
	input clk, rst;
	input [1:0] in;
	output reg [3:0] out;
	
	reg [1:0] stateNow, stateNext;
	
	parameter 	stateA=2'd0,
				stateB=2'd1, 
				stateC=2'd2, 
				stateD=2'd3;
	
	//combinatorial component to determine the next state
	always@(*)begin
		case(stateNow)
			stateA: stateNext =	(in==2'd0)?stateB:
								(in==2'd1)?stateB:
								(in==2'd2)?stateD:
								stateD;
								
			stateB: stateNext =	(in==2'd0)?stateD:
								(in==2'd1)?stateC:
								(in==2'd2)?stateA:
								stateC;
								
			stateC: stateNext =	(in==2'd0)?stateA:
								(in==2'd1)?stateD:
								(in==2'd2)?stateB:
								stateA;
								
			stateD: stateNext =	(in==2'd0)?stateC:
								(in==2'd1)?stateA:
								(in==2'd2)?stateC:
								stateB;
		
		endcase
	end
	
	
	//memory component to remember the current state
	always@(posedge clk or posedge rst)begin
		if(rst)stateNow<=stateA;
		else stateNow<=stateNext;
	end
	
	
	//combinatorial component to out put the current state
	always@(*)begin
		case(stateNow)
			stateA: out=4'b0001;
			stateB: out=4'b0010;
			stateC: out=4'b0100;
			stateD: out=4'b1000;
			default:out=4'b0000;
		endcase
	end	

endmodule

Report9/Ex3/freqDevider.v
module freqDevider(clk, rst, dclk);
	input clk, rst;
	
	output reg dclk;
	
	reg[24:0]count;
	
	always@(posedge clk, posedge rst)begin
		if(rst)begin
			dclk<=1'b0;
			count<=25'd0;
		end
		
		else if(count==25'd24000)begin
			dclk<=~dclk;
			count<=25'd0;
		end
		
		else count<=count+25'd1;
		
	end

endmodule

Report8/Ex1/system.v
module system(clk, rst, in, out);
	input clk, rst;
	input [1:0]in;
	
	output [3:0]out;
	
	wire dclk;
	
	freqDevider FD(.clk(clk), .rst(rst), .dclk(dclk));
	fsm fsm1(.clk(clk), .rst(rst), .in(in), .out(out));	
	
endmodule

Report8/Ex1/test.v
module test;
	reg [1:0] in=2'd0;
	reg clk, rst;
	wire [3:0]out;	
	
	integer cnt=0;
	
	system S(.clk(clk), .rst(rst), .in(in), .out(out));
	
	initial begin
		rst=1'b1;#1 rst=1'b0;
		clk=1'd0;
		for(cnt=0; cnt<32'd100; cnt=cnt+1)begin
			if(cnt==32'd0) in=2'd0;
			else if(cnt==32'd25) in=2'd1;
			else if(cnt==32'd50) in=2'd2;
			else if(cnt==32'd75) in=2'd3;
			else in=in;
			clk=~clk;
			#1;
		end
	end
	
	initial begin
		$monitor("in:%b, out:%b, cnt:%d", in, out, cnt);
	end
	
	initial begin
		$dumpfile("test.vcd");
		$dumpvars;
	end	
endmodule

Report8/Ex1/test.vcd
$date
	Tue May 08 15:59:45 2018
$end
$version
	Icarus Verilog
$end
$timescale
	1s
$end
$scope module test $end
$var wire 4 ! out [3:0] $end
$var reg 1 " clk $end
$var reg 2 # in [1:0] $end
$var reg 1 $ rst $end
$var integer 32 % cnt [31:0] $end
$scope module S $end
$var wire 1 " clk $end
$var wire 2 & in [1:0] $end
$var wire 1 $ rst $end
$var wire 4 ' out [3:0] $end
$var wire 1 ( dclk $end
$scope module FD $end
$var wire 1 " clk $end
$var wire 1 $ rst $end
$var reg 25 ) count [24:0] $end
$var reg 1 ( dclk $end
$upscope $end
$scope module fsm1 $end
$var wire 1 " clk $end
$var wire 2 * in [1:0] $end
$var wire 1 $ rst $end
$var reg 4 + out [3:0] $end
$var reg 2 , stateNext [1:0] $end
$var reg 2 - stateNow [1:0] $end
$upscope $end
$upscope $end
$upscope $end
$enddefinitions $end
#0
$dumpvars
b0 -
b1 ,
b1 +
b0 *
b0 )
0(
b1 '
b0 &
b0 %
1$
b0 #
x"
b1 !
$end
#1
b10 !
b10 '
b10 +
b11 ,
b1 -
b1 )
1"
0$
#2
0"
b1 %
#3
b1000 !
b1000 '
b1000 +
b10 ,
b10 )
b11 -
1"
b10 %
#4
0"
b11 %
#5
b100 !
b100 '
b100 +
b0 ,
b10 -
b11 )
1"
b100 %
#6
0"
b101 %
#7
b1 !
b1 '
b1 +
b1 ,
b100 )
b0 -
1"
b110 %
#8
0"
b111 %
#9
b10 !
b10 '
b10 +
b11 ,
b1 -
b101 )
1"
b1000 %
#10
0"
b1001 %
#11
b1000 !
b1000 '
b1000 +
b10 ,
b110 )
b11 -
1"
b1010 %
#12
0"
b1011 %
#13
b100 !
b100 '
b100 +
b0 ,
b10 -
b111 )
1"
b1100 %
#14
0"
b1101 %
#15
b1 !
b1 '
b1 +
b1 ,
b1000 )
b0 -
1"
b1110 %
#16
0"
b1111 %
#17
b10 !
b10 '
b10 +
b11 ,
b1 -
b1001 )
1"
b10000 %
#18
0"
b10001 %
#19
b1000 !
b1000 '
b1000 +
b10 ,
b1010 )
b11 -
1"
b10010 %
#20
0"
b10011 %
#21
b100 !
b100 '
b100 +
b0 ,
b10 -
b1011 )
1"
b10100 %
#22
0"
b10101 %
#23
b1 !
b1 '
b1 +
b1 ,
b1100 )
b0 -
1"
b10110 %
#24
0"
b10111 %
#25
b10 !
b10 '
b10 +
b11 ,
b1 -
b1101 )
1"
b11000 %
#26
b10 ,
0"
b1 #
b1 &
b1 *
b11001 %
#27
b100 !
b100 '
b100 +
b11 ,
b1110 )
b10 -
1"
b11010 %
#28
0"
b11011 %
#29
b1000 !
b1000 '
b1000 +
b0 ,
b11 -
b1111 )
1"
b11100 %
#30
0"
b11101 %
#31
b1 !
b1 '
b1 +
b1 ,
b10000 )
b0 -
1"
b11110 %
#32
0"
b11111 %
#33
b10 !
b10 '
b10 +
b10 ,
b1 -
b10001 )
1"
b100000 %
#34
0"
b100001 %
#35
b100 !
b100 '
b100 +
b11 ,
b10010 )
b10 -
1"
b100010 %
#36
0"
b100011 %
#37
b1000 !
b1000 '
b1000 +
b0 ,
b11 -
b10011 )
1"
b100100 %
#38
0"
b100101 %
#39
b1 !
b1 '
b1 +
b1 ,
b10100 )
b0 -
1"
b100110 %
#40
0"
b100111 %
#41
b10 !
b10 '
b10 +
b10 ,
b1 -
b10101 )
1"
b101000 %
#42
0"
b101001 %
#43
b100 !
b100 '
b100 +
b11 ,
b10110 )
b10 -
1"
b101010 %
#44
0"
b101011 %
#45
b1000 !
b1000 '
b1000 +
b0 ,
b11 -
b10111 )
1"
b101100 %
#46
0"
b101101 %
#47
b1 !
b1 '
b1 +
b1 ,
b11000 )
b0 -
1"
b101110 %
#48
0"
b101111 %
#49
b10 !
b10 '
b10 +
b10 ,
b1 -
b11001 )
1"
b110000 %
#50
0"
b110001 %
#51
b1 !
b1 '
b1 +
b11010 )
b0 -
b11 ,
1"
b10 #
b10 &
b10 *
b110010 %
#52
0"
b110011 %
#53
b1000 !
b1000 '
b1000 +
b10 ,
b11 -
b11011 )
1"
b110100 %
#54
0"
b110101 %
#55
b100 !
b100 '
b100 +
b1 ,
b11100 )
b10 -
1"
b110110 %
#56
0"
b110111 %
#57
b10 !
b10 '
b10 +
b0 ,
b1 -
b11101 )
1"
b111000 %
#58
0"
b111001 %
#59
b1 !
b1 '
b1 +
b11 ,
b11110 )
b0 -
1"
b111010 %
#60
0"
b111011 %
#61
b1000 !
b1000 '
b1000 +
b10 ,
b11 -
b11111 )
1"
b111100 %
#62
0"
b111101 %
#63
b100 !
b100 '
b100 +
b1 ,
b100000 )
b10 -
1"
b111110 %
#64
0"
b111111 %
#65
b10 !
b10 '
b10 +
b0 ,
b1 -
b100001 )
1"
b1000000 %
#66
0"
b1000001 %
#67
b1 !
b1 '
b1 +
b11 ,
b100010 )
b0 -
1"
b1000010 %
#68
0"
b1000011 %
#69
b1000 !
b1000 '
b1000 +
b10 ,
b11 -
b100011 )
1"
b1000100 %
#70
0"
b1000101 %
#71
b100 !
b100 '
b100 +
b1 ,
b100100 )
b10 -
1"
b1000110 %
#72
0"
b1000111 %
#73
b10 !
b10 '
b10 +
b0 ,
b1 -
b100101 )
1"
b1001000 %
#74
0"
b1001001 %
#75
b1 !
b1 '
b1 +
b11 ,
b100110 )
b0 -
1"
b1001010 %
#76
0"
b11 #
b11 &
b11 *
b1001011 %
#77
b1000 !
b1000 '
b1000 +
b1 ,
b11 -
b100111 )
1"
b1001100 %
#78
0"
b1001101 %
#79
b10 !
b10 '
b10 +
b10 ,
b101000 )
b1 -
1"
b1001110 %
#80
0"
b1001111 %
#81
b100 !
b100 '
b100 +
b0 ,
b10 -
b101001 )
1"
b1010000 %
#82
0"
b1010001 %
#83
b1 !
b1 '
b1 +
b11 ,
b101010 )
b0 -
1"
b1010010 %
#84
0"
b1010011 %
#85
b1000 !
b1000 '
b1000 +
b1 ,
b11 -
b101011 )
1"
b1010100 %
#86
0"
b1010101 %
#87
b10 !
b10 '
b10 +
b10 ,
b101100 )
b1 -
1"
b1010110 %
#88
0"
b1010111 %
#89
b100 !
b100 '
b100 +
b0 ,
b10 -
b101101 )
1"
b1011000 %
#90
0"
b1011001 %
#91
b1 !
b1 '
b1 +
b11 ,
b101110 )
b0 -
1"
b1011010 %
#92
0"
b1011011 %
#93
b1000 !
b1000 '
b1000 +
b1 ,
b11 -
b101111 )
1"
b1011100 %
#94
0"
b1011101 %
#95
b10 !
b10 '
b10 +
b10 ,
b110000 )
b1 -
1"
b1011110 %
#96
0"
b1011111 %
#97
b100 !
b100 '
b100 +
b0 ,
b10 -
b110001 )
1"
b1100000 %
#98
0"
b1100001 %
#99
b1 !
b1 '
b1 +
b11 ,
b110010 )
b0 -
1"
b1100010 %
#100
0"
b1100011 %
#101
b1100100 %
